Workbook
Name Inflation: Inputs!$B$23

Sheet NPV
C2: INPUTS
C3: Transaction Costs | G3: Financing Inputs
C4: Realtor fees | D4: 0.06 | E4: Selling | G4: Hurdle rate | H4: 0.1
C5: Closing costs (buyer) | D5: 0.02 | E5: Buying | G5: Sale price | H5: =F13 -> 780000
C6: Loan origination fees | D6: 0.015 | E6: Buying | G6: Mortgage at Sale | H6: =G13 -> 600860.19
C7: Inspections/appraisals | D7: 2500 | E7: Buying | G7: Selling costs | H7: =H5*(0.06)+F30*(D5+D6)+D7+D8 -> #N/A
C8: Capital repairs post-close | D8: 5000 | E8: Buying | G8: Net Equity Post Sale | H8: =H5-H6-H7 -> #N/A
C9: Home appreciation | D9: 0.025 | E9: Both | K9: Hold
K10: NPV | L10: IRR
C11: HOLD DUPLEX | D11: FP4 | J11: CoC | K11: =SUM(K13:K24) -> 242531.21 | L11: =IRR(L12:L24) -> 0.17774713
D12: Yr | E12: CF | F12: Prop Value | G12: Loan | H12: Equity | L12: =-H13 -> -179139.81
D13: 2025 | E13: 2764.3471 | F13: 780000 | G13: =_xlfn.XLOOKUP(D13,'FP3 Amort'!$A$3:$A$389,'FP3 Amort'!$G$3:$G$389,,0,-1) -> 600860.19 | H13: =F13-G13 -> 179139.81 | K13: =(E13)/(1+$H$4)^(D13-2025) -> 2764.3471 | L13: =E13 -> 2764.3471
D14: =D13+1 -> 2026 | E14: 3148.1678 | F14: =F13*(1+$D$9) -> 799500 | G14: =_xlfn.XLOOKUP(D14,'FP3 Amort'!$A$3:$A$389,'FP3 Amort'!$G$3:$G$389,,0,-1) -> 587097.21 | H14: =F14-G14 -> 212402.79 | K14: =(E14)/(1+$H$4)^(D14-2025) -> 2861.9707 | L14: =E14 -> 3148.1678
D15: =D14+1 -> 2027 | E15: 4534.206 | F15: =F14*(1+$D$9) -> 819487.5 | G15: =_xlfn.XLOOKUP(D15,'FP3 Amort'!$A$3:$A$389,'FP3 Amort'!$G$3:$G$389,,0,-1) -> 572817.7 | H15: =F15-G15 -> 246669.8 | K15: =(E15)/(1+$H$4)^(D15-2025) -> 3747.2777 | L15: =E15 -> 4534.206
D16: =D15+1 -> 2028 | E16: 5962.2555 | F16: =F15*(1+$D$9) -> 839974.69 | G16: =_xlfn.XLOOKUP(D16,'FP3 Amort'!$A$3:$A$389,'FP3 Amort'!$G$3:$G$389,,0,-1) -> 558002.27 | H16: =F16-G16 -> 281972.42 | K16: =(E16)/(1+$H$4)^(D16-2025) -> 4479.5308 | L16: =E16 -> 5962.2555
D17: =D16+1 -> 2029 | E17: 7433.5875 | F17: =F16*(1+$D$9) -> 860974.05 | G17: =_xlfn.XLOOKUP(D17,'FP3 Amort'!$A$3:$A$389,'FP3 Amort'!$G$3:$G$389,,0,-1) -> 542630.81 | H17: =F17-G17 -> 318343.25 | K17: =(E17)/(1+$H$4)^(D17-2025) -> 5077.2403 | L17: =E17 -> 7433.5875
D18: =D17+1 -> 2030 | E18: 8949.5113 | F18: =F17*(1+$D$9) -> 882498.41 | G18: =_xlfn.XLOOKUP(D18,'FP3 Amort'!$A$3:$A$389,'FP3 Amort'!$G$3:$G$389,,0,-1) -> 526682.44 | H18: =F18-G18 -> 355815.96 | K18: =(E18)/(1+$H$4)^(D18-2025) -> 5556.9424 | L18: =E18 -> 8949.5113
D19: =D18+1 -> 2031 | E19: 10511.376 | F19: =F18*(1+$D$9) -> 904560.87 | G19: =_xlfn.XLOOKUP(D19,'FP3 Amort'!$A$3:$A$389,'FP3 Amort'!$G$3:$G$389,,0,-1) -> 510135.53 | H19: =F19-G19 -> 394425.33 | K19: =(E19)/(1+$H$4)^(D19-2025) -> 5933.3978 | L19: =E19 -> 10511.376
D20: =D19+1 -> 2032 | E20: 12120.572 | F20: =F19*(1+$D$9) -> 927174.89 | G20: =_xlfn.XLOOKUP(D20,'FP3 Amort'!$A$3:$A$389,'FP3 Amort'!$G$3:$G$389,,0,-1) -> 492967.61 | H20: =F20-G20 -> 434207.28 | K20: =(E20)/(1+$H$4)^(D20-2025) -> 6219.7699 | L20: =E20 -> 12120.572
D21: =D20+1 -> 2033 | E21: 13778.53 | F21: =F20*(1+$D$9) -> 950354.26 | G21: =_xlfn.XLOOKUP(D21,'FP3 Amort'!$A$3:$A$389,'FP3 Amort'!$G$3:$G$389,,0,-1) -> 475155.36 | H21: =F21-G21 -> 475198.9 | K21: =(E21)/(1+$H$4)^(D21-2025) -> 6427.786 | L21: =E21 -> 13778.53
D22: =D21+1 -> 2034 | E22: 15486.726 | F22: =F21*(1+$D$9) -> 974113.12 | G22: =_xlfn.XLOOKUP(D22,'FP3 Amort'!$A$3:$A$389,'FP3 Amort'!$G$3:$G$389,,0,-1) -> 456674.61 | H22: =F22-G22 -> 517438.5 | K22: =(E22)/(1+$H$4)^(D22-2025) -> 6567.8836 | L22: =E22 -> 15486.726
D23: =D22+1 -> 2035 | E23: 17246.679 | F23: =F22*(1+$D$9) -> 998465.94 | G23: =_xlfn.XLOOKUP(D23,'FP3 Amort'!$A$3:$A$389,'FP3 Amort'!$G$3:$G$389,,0,-1) -> 437500.27 | H23: =F23-G23 -> 560965.67 | K23: =(E23)/(1+$H$4)^(D23-2025) -> 6649.3414 | L23: =E23 -> 17246.679
D24: =D23+1 -> 2036 | E24: 19059.955 | F24: =F23*(1+$D$9) -> 1023427.6 | G24: =_xlfn.XLOOKUP(D24,'FP3 Amort'!$A$3:$A$389,'FP3 Amort'!$G$3:$G$389,,0,-1) -> 417606.31 | H24: =F24-G24 -> 605821.28 | K24: =(E24)/(1+$H$4)^(D24-2025)+(F24)/(1+$H$4)^(D24-2025)-$H$13 -> 186245.72 | L24: =E24+F24 -> 1042487.5
D27: 1031 | K27: NPV | L27: IRR
D28: Yr | E28: CF | F28: Prop Value | G28: Loan | H28: Equity | K28: =SUM(K30:K41) -> #N/A | L28: =IRR(L29:L42) -> #VALUE!
L29: =-H8 -> #N/A
D30: 2025 | E30: =Financials!N80 -> #N/A | F30: =Inputs!B11 -> #N/A | G30: =_xlfn.XLOOKUP(D30,Amort!$A$3:$A$485,Amort!$C$3:$C$485) -> #N/A | H30: =F30-G30 -> #N/A | K30: =(E30)/(1+$H$4)^(D30-2025) -> #N/A | L30: =E30 -> #N/A
D31: =D30+1 -> 2026 | E31: =Financials!AA80 -> #N/A | F31: =F30*(1+$D$9) -> #N/A | G31: =_xlfn.XLOOKUP(D31,Amort!$A$3:$A$485,Amort!$C$3:$C$485) -> #N/A | H31: =F31-G31 -> #N/A | K31: =(E31)/(1+$H$4)^(D31-2025) -> #N/A | L31: =E31 -> #N/A
D32: =D31+1 -> 2027 | E32: =Financials!AN80 -> #N/A | F32: =F31*(1+$D$9) -> #N/A | G32: =_xlfn.XLOOKUP(D32,Amort!$A$3:$A$485,Amort!$C$3:$C$485) -> #N/A | H32: =F32-G32 -> #N/A | K32: =(E32)/(1+$H$4)^(D32-2025) -> #N/A | L32: =E32 -> #N/A
D33: =D32+1 -> 2028 | E33: =Financials!BA80 -> #N/A | F33: =F32*(1+$D$9) -> #N/A | G33: =_xlfn.XLOOKUP(D33,Amort!$A$3:$A$485,Amort!$C$3:$C$485) -> #N/A | H33: =F33-G33 -> #N/A | K33: =(E33)/(1+$H$4)^(D33-2025) -> #N/A | L33: =E33 -> #N/A
D34: =D33+1 -> 2029 | E34: =Financials!BN80 -> #N/A | F34: =F33*(1+$D$9) -> #N/A | G34: =_xlfn.XLOOKUP(D34,Amort!$A$3:$A$485,Amort!$C$3:$C$485) -> #N/A | H34: =F34-G34 -> #N/A | K34: =(E34)/(1+$H$4)^(D34-2025) -> #N/A | L34: =E34 -> #N/A
D35: =D34+1 -> 2030 | E35: =Financials!CA80 -> #N/A | F35: =F34*(1+$D$9) -> #N/A | G35: =_xlfn.XLOOKUP(D35,Amort!$A$3:$A$485,Amort!$C$3:$C$485) -> #N/A | H35: =F35-G35 -> #N/A | K35: =(E35)/(1+$H$4)^(D35-2025) -> #N/A | L35: =E35 -> #N/A
D36: =D35+1 -> 2031 | E36: =Financials!CN80 -> #N/A | F36: =F35*(1+$D$9) -> #N/A | G36: =_xlfn.XLOOKUP(D36,Amort!$A$3:$A$485,Amort!$C$3:$C$485) -> #N/A | H36: =F36-G36 -> #N/A | K36: =(E36)/(1+$H$4)^(D36-2025) -> #N/A | L36: =E36 -> #N/A
D37: =D36+1 -> 2032 | E37: =Financials!DA80 -> #N/A | F37: =F36*(1+$D$9) -> #N/A | G37: =_xlfn.XLOOKUP(D37,Amort!$A$3:$A$485,Amort!$C$3:$C$485) -> #N/A | H37: =F37-G37 -> #N/A | K37: =(E37)/(1+$H$4)^(D37-2025) -> #N/A | L37: =E37 -> #N/A
D38: =D37+1 -> 2033 | E38: =Financials!DN80 -> #N/A | F38: =F37*(1+$D$9) -> #N/A | G38: =_xlfn.XLOOKUP(D38,Amort!$A$3:$A$485,Amort!$C$3:$C$485) -> #N/A | H38: =F38-G38 -> #N/A | K38: =(E38)/(1+$H$4)^(D38-2025) -> #N/A | L38: =E38 -> #N/A
D39: =D38+1 -> 2034 | E39: =Financials!EA80 -> #N/A | F39: =F38*(1+$D$9) -> #N/A | G39: =_xlfn.XLOOKUP(D39,Amort!$A$3:$A$485,Amort!$C$3:$C$485) -> #N/A | H39: =F39-G39 -> #N/A | K39: =(E39)/(1+$H$4)^(D39-2025) -> #N/A | L39: =E39 -> #N/A
D40: =D39+1 -> 2035 | E40: =Financials!EN80 -> #N/A | F40: =F39*(1+$D$9) -> #N/A | G40: =_xlfn.XLOOKUP(D40,Amort!$A$3:$A$485,Amort!$C$3:$C$485) -> #N/A | H40: =F40-G40 -> #N/A | K40: =(E40)/(1+$H$4)^(D40-2025) -> #N/A | L40: =E40 -> #N/A
D41: =D40+1 -> 2036 | E41: =Financials!FA80 -> #N/A | F41: =F40*(1+$D$9) -> #N/A | G41: =_xlfn.XLOOKUP(D41,Amort!$A$3:$A$485,Amort!$C$3:$C$485) -> #N/A | H41: =F41-G41 -> #N/A | K41: =(E41)/(1+$H$4)^(D41-2025)+(F41)/(1+$H$4)^(D41-2025)-H8 -> #N/A | L41: =E41+F41 -> #N/A

Sheet FP3 Amort
C1: MORTGAGE
A2: Year | B2: Month | C2: Rate | D2: Payment | E2: Interest | F2: Principal | G2: Balance | H2: + | I2: Taxes | J2: PMI | K2: Insurance | L2: Total | M2: Notes
A3: =YEAR(B3) -> 2022 | B3: 44562 | C3: 0 | G3: 0
A4: =YEAR(B4) -> 2022 | B4: =EDATE(B3,1) -> 44593 | C4: 0.0369 | G4: 647200 | O4: 2022 | P4: Annually | Q4: Monthly | R4: YoY Inc.
A5: =YEAR(B5) -> 2022 | B5: =EDATE(B4,1) -> 44621 | C5: =C4 -> 0.0369 | G5: =G4 -> 647200 | O5: Taxes | P5: 3078.65 | Q5: =P5/12 -> 256.55417 | R5: 0.03
A6: =YEAR(B6) -> 2022 | B6: =EDATE(B5,1) -> 44652 | C6: =C5 -> 0.0369 | G6: =G5 -> 647200 | I6: =$P$5/12 -> 256.55417 | K6: =$P$7/12 -> 78.445 | L6: =SUM(I6:K6,D6) -> 334.99917 | O6: PMI | P6: =Q6*12 -> 588 | Q6: 49
A7: =YEAR(B7) -> 2022 | B7: =EDATE(B6,1) -> 44682 | C7: =C6 -> 0.0369 | D7: =-PMT($C$4/12,360,$G$4) -> 2975.2921 | E7: =G6*C6/12 -> 1990.14 | F7: =D7-E7 -> 985.15208 | G7: =IF(G6-F7<0,,G6-F7) -> 646214.85 | I7: =$P$5/12 -> 256.55417 | J7: =$P$6/12 -> 49 | K7: =$P$7/12 -> 78.445 | L7: =SUM(I7:K7,D7) -> 3359.2912 | O7: Hazard insurance | P7: 941.34 | Q7: =P7/12 -> 78.445 | R7: 0.03
A8: =YEAR(B8) -> 2022 | B8: =EDATE(B7,1) -> 44713 | C8: =C7 -> 0.0369 | D8: =IF(G7<=0,0,D7) -> 2975.2921 | E8: =G7*C7/12 -> 1987.1107 | F8: =D8-E8 -> 988.18142 | G8: =IF(G7-F8<0,,G7-F8) -> 645226.67 | I8: =$P$5/12 -> 256.55417 | J8: =$P$6/12 -> 49 | K8: =$P$7/12 -> 78.445 | L8: =SUM(I8:K8,D8) -> 3359.2912
A9: =YEAR(B9) -> 2022 | B9: =EDATE(B8,1) -> 44743 | C9: =C8 -> 0.0369 | D9: =IF(G8<=0,0,D8) -> 2975.2921 | E9: =G8*C8/12 -> 1984.072 | F9: =D9-E9 -> 991.22008 | G9: =IF(G8-F9<0,,G8-F9) -> 644235.45 | I9: =$P$5/12 -> 256.55417 | J9: =$P$6/12 -> 49 | K9: =$P$7/12 -> 78.445 | L9: =SUM(I9:K9,D9) -> 3359.2912
A10: =YEAR(B10) -> 2022 | B10: =EDATE(B9,1) -> 44774 | C10: =C9 -> 0.0369 | D10: =IF(G9<=0,0,D9) -> 2975.2921 | E10: =G9*C9/12 -> 1981.024 | F10: =D10-E10 -> 994.26808 | G10: =IF(G9-F10<0,,G9-F10) -> 643241.18 | I10: =$P$5/12 -> 256.55417 | J10: =$P$6/12 -> 49 | K10: =$P$7/12 -> 78.445 | L10: =SUM(I10:K10,D10) -> 3359.2912
A11: =YEAR(B11) -> 2022 | B11: =EDATE(B10,1) -> 44805 | C11: =C10 -> 0.0369 | D11: =IF(G10<=0,0,D10) -> 2975.2921 | E11: =G10*C10/12 -> 1977.9666 | F11: =D11-E11 -> 997.32545 | G11: =IF(G10-F11<0,,G10-F11) -> 642243.85 | I11: =$P$5/12 -> 256.55417 | J11: =$P$6/12 -> 49 | K11: =$P$7/12 -> 78.445 | L11: =SUM(I11:K11,D11) -> 3359.2912
A12: =YEAR(B12) -> 2022 | B12: =EDATE(B11,1) -> 44835 | C12: =C11 -> 0.0369 | D12: =IF(G11<=0,0,D11) -> 2975.2921 | E12: =G11*C11/12 -> 1974.8998 | F12: =D12-E12 -> 1000.3922 | G12: =IF(G11-F12<0,,G11-F12) -> 641243.46 | I12: =$P$5/12 -> 256.55417 | J12: =$P$6/12 -> 49 | K12: =$P$7/12 -> 78.445 | L12: =SUM(I12:K12,D12) -> 3359.2912
A13: =YEAR(B13) -> 2022 | B13: =EDATE(B12,1) -> 44866 | C13: =C12 -> 0.0369 | D13: =IF(G12<=0,0,D12) -> 2975.2921 | E13: =G12*C12/12 -> 1971.8236 | F13: =D13-E13 -> 1003.4684 | G13: =IF(G12-F13<0,,G12-F13) -> 640239.99 | I13: =$P$5/12 -> 256.55417 | J13: =$P$6/12 -> 49 | K13: =$P$7/12 -> 78.445 | L13: =SUM(I13:K13,D13) -> 3359.2912
A14: =YEAR(B14) -> 2022 | B14: =EDATE(B13,1) -> 44896 | C14: =C13 -> 0.0369 | D14: =IF(G13<=0,0,D13) -> 2975.2921 | E14: =G13*C13/12 -> 1968.738 | F14: =D14-E14 -> 1006.5541 | G14: =IF(G13-F14<0,,G13-F14) -> 639233.44 | I14: =$P$5/12 -> 256.55417 | J14: =$P$6/12 -> 49 | K14: =$P$7/12 -> 78.445 | L14: =SUM(I14:K14,D14) -> 3359.2912
A15: =YEAR(B15) -> 2023 | B15: =EDATE(B14,1) -> 44927 | C15: =C14 -> 0.0369 | D15: =IF(G14<=0,0,D14) -> 2975.2921 | E15: =G14*C14/12 -> 1965.6428 | F15: =D15-E15 -> 1009.6493 | G15: =IF(G14-F15<0,,G14-F15) -> 638223.79 | I15: =$Q$5*(1+$R$5)^(YEAR(B15)-$O$4)+53 -> 317.25079 | J15: =$P$6/12 -> 49 | K15: =K14*(1+$R$7)^(YEAR(B15)-YEAR(B14)) -> 80.79835 | L15: =SUM(I15:K15,D15) -> 3422.3412
A16: =YEAR(B16) -> 2023 | B16: =EDATE(B15,1) -> 44958 | C16: =C15 -> 0.0369 | D16: =IF(G15<=0,0,D15) -> 2975.2921 | E16: =G15*C15/12 -> 1962.5382 | F16: =D16-E16 -> 1012.7539 | G16: =IF(G15-F16<0,,G15-F16) -> 637211.03 | I16: =I15*(1+$R$5)^(YEAR(B16)-YEAR(B15)) -> 317.25079 | J16: =$P$6/12 -> 49 | K16: =K15*(1+$R$7)^(YEAR(B16)-YEAR(B15)) -> 80.79835 | L16: =SUM(I16:K16,D16) -> 3422.3412
A17: =YEAR(B17) -> 2023 | B17: =EDATE(B16,1) -> 44986 | C17: =C16 -> 0.0369 | D17: =IF(G16<=0,0,D16) -> 2975.2921 | E17: =G16*C16/12 -> 1959.4239 | F17: =D17-E17 -> 1015.8681 | G17: =IF(G16-F17<0,,G16-F17) -> 636195.17 | I17: =I16*(1+$R$5)^(YEAR(B17)-YEAR(B16)) -> 317.25079 | J17: =$P$6/12 -> 49 | K17: =K16*(1+$R$7)^(YEAR(B17)-YEAR(B16)) -> 80.79835 | L17: =SUM(I17:K17,D17) -> 3422.3412
A18: =YEAR(B18) -> 2023 | B18: =EDATE(B17,1) -> 45017 | C18: =C17 -> 0.0369 | D18: =IF(G17<=0,0,D17) -> 2975.2921 | E18: =G17*C17/12 -> 1956.3001 | F18: =D18-E18 -> 1018.9919 | G18: =IF(G17-F18<0,,G17-F18) -> 635176.17 | I18: =I17*(1+$R$5)^(YEAR(B18)-YEAR(B17)) -> 317.25079 | J18: =$P$6/12 -> 49 | K18: =K17*(1+$R$7)^(YEAR(B18)-YEAR(B17)) -> 80.79835 | L18: =SUM(I18:K18,D18) -> 3422.3412
A19: =YEAR(B19) -> 2023 | B19: =EDATE(B18,1) -> 45047 | C19: =C18 -> 0.0369 | D19: =IF(G18<=0,0,D18) -> 2975.2921 | E19: =G18*C18/12 -> 1953.1667 | F19: =D19-E19 -> 1022.1253 | G19: =IF(G18-F19<0,,G18-F19) -> 634154.05 | I19: =I18*(1+$R$5)^(YEAR(B19)-YEAR(B18)) -> 317.25079 | J19: =$P$6/12 -> 49 | K19: =K18*(1+$R$7)^(YEAR(B19)-YEAR(B18)) -> 80.79835 | L19: =SUM(I19:K19,D19) -> 3422.3412
A20: =YEAR(B20) -> 2023 | B20: =EDATE(B19,1) -> 45078 | C20: =C19 -> 0.0369 | D20: =IF(G19<=0,0,D19) -> 2975.2921 | E20: =G19*C19/12 -> 1950.0237 | F20: =D20-E20 -> 1025.2684 | G20: =IF(G19-F20<0,,G19-F20) -> 633128.78 | I20: =I19*(1+$R$5)^(YEAR(B20)-YEAR(B19)) -> 317.25079 | J20: =$P$6/12 -> 49 | K20: =K19*(1+$R$7)^(YEAR(B20)-YEAR(B19)) -> 80.79835 | L20: =SUM(I20:K20,D20) -> 3422.3412
A21: =YEAR(B21) -> 2023 | B21: =EDATE(B20,1) -> 45108 | C21: =C20 -> 0.0369 | D21: =IF(G20<=0,0,D20) -> 2975.2921 | E21: =G20*C20/12 -> 1946.871 | F21: =D21-E21 -> 1028.4211 | G21: =IF(G20-F21<0,,G20-F21) -> 632100.36 | I21: =I20*(1+$R$5)^(YEAR(B21)-YEAR(B20)) -> 317.25079 | J21: =$P$6/12 -> 49 | K21: =K20*(1+$R$7)^(YEAR(B21)-YEAR(B20)) -> 80.79835 | L21: =SUM(I21:K21,D21) -> 3422.3412
A22: =YEAR(B22) -> 2023 | B22: =EDATE(B21,1) -> 45139 | C22: =C21 -> 0.0369 | D22: =IF(G21<=0,0,D21) -> 2975.2921 | E22: =G21*C21/12 -> 1943.7086 | F22: =D22-E22 -> 1031.5835 | G22: =IF(G21-F22<0,,G21-F22) -> 631068.78 | I22: =I21*(1+$R$5)^(YEAR(B22)-YEAR(B21)) -> 317.25079 | J22: =$P$6/12 -> 49 | K22: =K21*(1+$R$7)^(YEAR(B22)-YEAR(B21)) -> 80.79835 | L22: =SUM(I22:K22,D22) -> 3422.3412
A23: =YEAR(B23) -> 2023 | B23: =EDATE(B22,1) -> 45170 | C23: =C22 -> 0.0369 | D23: =IF(G22<=0,0,D22) -> 2975.2921 | E23: =G22*C22/12 -> 1940.5365 | F23: =D23-E23 -> 1034.7556 | G23: =IF(G22-F23<0,,G22-F23) -> 630034.02 | I23: =I22*(1+$R$5)^(YEAR(B23)-YEAR(B22)) -> 317.25079 | J23: =$P$6/12 -> 49 | K23: =K22*(1+$R$7)^(YEAR(B23)-YEAR(B22)) -> 80.79835 | L23: =SUM(I23:K23,D23) -> 3422.3412
A24: =YEAR(B24) -> 2023 | B24: =EDATE(B23,1) -> 45200 | C24: =C23 -> 0.0369 | D24: =IF(G23<=0,0,D23) -> 2975.2921 | E24: =G23*C23/12 -> 1937.3546 | F24: =D24-E24 -> 1037.9375 | G24: =IF(G23-F24<0,,G23-F24) -> 628996.08 | I24: =I23*(1+$R$5)^(YEAR(B24)-YEAR(B23)) -> 317.25079 | J24: =$P$6/12 -> 49 | K24: =K23*(1+$R$7)^(YEAR(B24)-YEAR(B23)) -> 80.79835 | L24: =SUM(I24:K24,D24) -> 3422.3412
A25: =YEAR(B25) -> 2023 | B25: =EDATE(B24,1) -> 45231 | C25: =C24 -> 0.0369 | D25: =IF(G24<=0,0,D24) -> 2975.2921 | E25: =G24*C24/12 -> 1934.163 | F25: =D25-E25 -> 1041.1291 | G25: =IF(G24-F25<0,,G24-F25) -> 627954.95 | I25: =I24*(1+$R$5)^(YEAR(B25)-YEAR(B24)) -> 317.25079 | J25: =$P$6/12 -> 49 | K25: =K24*(1+$R$7)^(YEAR(B25)-YEAR(B24)) -> 80.79835 | L25: =SUM(I25:K25,D25) -> 3422.3412
A26: =YEAR(B26) -> 2023 | B26: =EDATE(B25,1) -> 45261 | C26: =C25 -> 0.0369 | D26: =IF(G25<=0,0,D25) -> 2975.2921 | E26: =G25*C25/12 -> 1930.9615 | F26: =D26-E26 -> 1044.3306 | G26: =IF(G25-F26<0,,G25-F26) -> 626910.62 | I26: =I25*(1+$R$5)^(YEAR(B26)-YEAR(B25)) -> 317.25079 | J26: =$P$6/12 -> 49 | K26: =K25*(1+$R$7)^(YEAR(B26)-YEAR(B25)) -> 80.79835 | L26: =SUM(I26:K26,D26) -> 3422.3412
A27: =YEAR(B27) -> 2024 | B27: =EDATE(B26,1) -> 45292 | C27: =C26 -> 0.0369 | D27: =IF(G26<=0,0,D26) -> 2975.2921 | E27: =G26*C26/12 -> 1927.7502 | F27: =D27-E27 -> 1047.5419 | G27: =IF(G26-F27<0,,G26-F27) -> 625863.08 | I27: =I26*(1+$R$5)^(YEAR(B27)-YEAR(B26)) -> 326.76832 | J27: =$P$6/12 -> 49 | K27: =K26*(1+$R$7)^(YEAR(B27)-YEAR(B26)) -> 83.222301 | L27: =SUM(I27:K27,D27) -> 3434.2827
... A389: =YEAR(B389) -> 2054 | B389: =EDATE(B388,1) -> 56309 | C389: =C388 -> 0.0369 | D389: =IF(G388<=0,0,D388) -> 0 | E389: =G388*C388/12 -> 0 | F389: =D389-E389 -> 0 | G389: =IF(G388-F389<0,,G388-F389) -> 0 | I389: =I388*(1+$R$5)^(YEAR(B389)-YEAR(B388)) -> 793.15247 | J389: =$P$6/12 -> 49 | K389: =K388*(1+$R$7)^(YEAR(B389)-YEAR(B388)) -> 202.00237 | L389: =SUM(I389:K389,D389) -> 1044.1548

Sheet Amort
C1: MORTGAGE | H1: 2ND LOAN
A2: Yr | C2: Balance | D2: Interest | E2: Principal | F2: Payment | H2: Balance | I2: Interest | J2: Principal | K2: Payment
A3: =YEAR(B3) -> 2025 | B3: =Financials!B1 -> 45658 | C3: =ROUND(Inputs!$B$11-Inputs!$B$13,2) -> #N/A | D3: =IF($C3<>0,Inputs!$B$14/12*C3,0) -> #N/A | E3: =F3-D3 -> #N/A | F3: =IF($C3>0,-PMT(Inputs!$B$14/12,Inputs!$B$15,Inputs!$B$11-Inputs!$B$13),0) -> #N/A | H3: =ROUND(Inputs!$B$27,2) -> 0 | I3: =IF($H3<>0,Inputs!$B$28/12*H3,0) -> 0 | J3: =K3-I3 -> 0 | K3: =H3*600/100000 -> 0
A4: =YEAR(B4) -> 2025 | B4: =EDATE(B3,1) -> 45689 | C4: =IF(C3>0,C3-E3,0) -> #N/A | D4: =IF($C4<>0,Inputs!$B$14/12*C4,0) -> #N/A | E4: =F4-D4 -> #N/A | F4: =IF($C4>0,-PMT(Inputs!$B$14/12,Inputs!$B$15,Inputs!$B$11-Inputs!$B$13),0) -> #N/A | H4: =IF(H3>0,H3-J3,0) -> 0 | I4: =IF($H4<>0,Inputs!$B$28/12*H4,0) -> 0 | J4: =K4-I4 -> 0 | K4: =IF(H4>0,IF(H4+I4>K3,K3,H4+I4),0) -> 0
A5: =YEAR(B5) -> 2025 | B5: =EDATE(B4,1) -> 45717 | C5: =IF(C4>0,C4-E4,0) -> #N/A | D5: =IF($C5<>0,Inputs!$B$14/12*C5,0) -> #N/A | E5: =F5-D5 -> #N/A | F5: =IF($C5>0,-PMT(Inputs!$B$14/12,Inputs!$B$15,Inputs!$B$11-Inputs!$B$13),0) -> #N/A | H5: =IF(H4>0,H4-J4,0) -> 0 | I5: =IF($H5<>0,Inputs!$B$28/12*H5,0) -> 0 | J5: =K5-I5 -> 0 | K5: =IF(H5>0,IF(H5+I5>K4,K4,H5+I5),0) -> 0
A6: =YEAR(B6) -> 2025 | B6: =EDATE(B5,1) -> 45748 | C6: =IF(C5>0,C5-E5,0) -> #N/A | D6: =IF($C6<>0,Inputs!$B$14/12*C6,0) -> #N/A | E6: =F6-D6 -> #N/A | F6: =IF($C6>0,-PMT(Inputs!$B$14/12,Inputs!$B$15,Inputs!$B$11-Inputs!$B$13),0) -> #N/A | H6: =IF(H5>0,H5-J5,0) -> 0 | I6: =IF($H6<>0,Inputs!$B$28/12*H6,0) -> 0 | J6: =K6-I6 -> 0 | K6: =IF(H6>0,IF(H6+I6>K5,K5,H6+I6),0) -> 0
A7: =YEAR(B7) -> 2025 | B7: =EDATE(B6,1) -> 45778 | C7: =IF(C6>0,C6-E6,0) -> #N/A | D7: =IF($C7<>0,Inputs!$B$14/12*C7,0) -> #N/A | E7: =F7-D7 -> #N/A | F7: =IF($C7>0,-PMT(Inputs!$B$14/12,Inputs!$B$15,Inputs!$B$11-Inputs!$B$13),0) -> #N/A | H7: =IF(H6>0,H6-J6,0) -> 0 | I7: =IF($H7<>0,Inputs!$B$28/12*H7,0) -> 0 | J7: =K7-I7 -> 0 | K7: =IF(H7>0,IF(H7+I7>K6,K6,H7+I7),0) -> 0
A8: =YEAR(B8) -> 2025 | B8: =EDATE(B7,1) -> 45809 | C8: =IF(C7>0,C7-E7,0) -> #N/A | D8: =IF($C8<>0,Inputs!$B$14/12*C8,0) -> #N/A | E8: =F8-D8 -> #N/A | F8: =IF($C8>0,-PMT(Inputs!$B$14/12,Inputs!$B$15,Inputs!$B$11-Inputs!$B$13),0) -> #N/A | H8: =IF(H7>0,H7-J7,0) -> 0 | I8: =IF($H8<>0,Inputs!$B$28/12*H8,0) -> 0 | J8: =K8-I8 -> 0 | K8: =IF(H8>0,IF(H8+I8>K7,K7,H8+I8),0) -> 0
A9: =YEAR(B9) -> 2025 | B9: =EDATE(B8,1) -> 45839 | C9: =IF(C8>0,C8-E8,0) -> #N/A | D9: =IF($C9<>0,Inputs!$B$14/12*C9,0) -> #N/A | E9: =F9-D9 -> #N/A | F9: =IF($C9>0,-PMT(Inputs!$B$14/12,Inputs!$B$15,Inputs!$B$11-Inputs!$B$13),0) -> #N/A | H9: =IF(H8>0,H8-J8,0) -> 0 | I9: =IF($H9<>0,Inputs!$B$28/12*H9,0) -> 0 | J9: =K9-I9 -> 0 | K9: =IF(H9>0,IF(H9+I9>K8,K8,H9+I9),0) -> 0
A10: =YEAR(B10) -> 2025 | B10: =EDATE(B9,1) -> 45870 | C10: =IF(C9>0,C9-E9,0) -> #N/A | D10: =IF($C10<>0,Inputs!$B$14/12*C10,0) -> #N/A | E10: =F10-D10 -> #N/A | F10: =IF($C10>0,-PMT(Inputs!$B$14/12,Inputs!$B$15,Inputs!$B$11-Inputs!$B$13),0) -> #N/A | H10: =IF(H9>0,H9-J9,0) -> 0 | I10: =IF($H10<>0,Inputs!$B$28/12*H10,0) -> 0 | J10: =K10-I10 -> 0 | K10: =IF(H10>0,IF(H10+I10>K9,K9,H10+I10),0) -> 0
A11: =YEAR(B11) -> 2025 | B11: =EDATE(B10,1) -> 45901 | C11: =IF(C10>0,C10-E10,0) -> #N/A | D11: =IF($C11<>0,Inputs!$B$14/12*C11,0) -> #N/A | E11: =F11-D11 -> #N/A | F11: =IF($C11>0,-PMT(Inputs!$B$14/12,Inputs!$B$15,Inputs!$B$11-Inputs!$B$13),0) -> #N/A | H11: =IF(H10>0,H10-J10,0) -> 0 | I11: =IF($H11<>0,Inputs!$B$28/12*H11,0) -> 0 | J11: =K11-I11 -> 0 | K11: =IF(H11>0,IF(H11+I11>K10,K10,H11+I11),0) -> 0
A12: =YEAR(B12) -> 2025 | B12: =EDATE(B11,1) -> 45931 | C12: =IF(C11>0,C11-E11,0) -> #N/A | D12: =IF($C12<>0,Inputs!$B$14/12*C12,0) -> #N/A | E12: =F12-D12 -> #N/A | F12: =IF($C12>0,-PMT(Inputs!$B$14/12,Inputs!$B$15,Inputs!$B$11-Inputs!$B$13),0) -> #N/A | H12: =IF(H11>0,H11-J11,0) -> 0 | I12: =IF($H12<>0,Inputs!$B$28/12*H12,0) -> 0 | J12: =K12-I12 -> 0 | K12: =IF(H12>0,IF(H12+I12>K11,K11,H12+I12),0) -> 0
A13: =YEAR(B13) -> 2025 | B13: =EDATE(B12,1) -> 45962 | C13: =IF(C12>0,C12-E12,0) -> #N/A | D13: =IF($C13<>0,Inputs!$B$14/12*C13,0) -> #N/A | E13: =F13-D13 -> #N/A | F13: =IF($C13>0,-PMT(Inputs!$B$14/12,Inputs!$B$15,Inputs!$B$11-Inputs!$B$13),0) -> #N/A | H13: =IF(H12>0,H12-J12,0) -> 0 | I13: =IF($H13<>0,Inputs!$B$28/12*H13,0) -> 0 | J13: =K13-I13 -> 0 | K13: =IF(H13>0,IF(H13+I13>K12,K12,H13+I13),0) -> 0
A14: =YEAR(B14) -> 2025 | B14: =EDATE(B13,1) -> 45992 | C14: =IF(C13>0,C13-E13,0) -> #N/A | D14: =IF($C14<>0,Inputs!$B$14/12*C14,0) -> #N/A | E14: =F14-D14 -> #N/A | F14: =IF($C14>0,-PMT(Inputs!$B$14/12,Inputs!$B$15,Inputs!$B$11-Inputs!$B$13),0) -> #N/A | H14: =IF(H13>0,H13-J13,0) -> 0 | I14: =IF($H14<>0,Inputs!$B$28/12*H14,0) -> 0 | J14: =K14-I14 -> 0 | K14: =IF(H14>0,IF(H14+I14>K13,K13,H14+I14),0) -> 0
A15: =YEAR(B15) -> 2026 | B15: =EDATE(B14,1) -> 46023 | C15: =IF(C14>0,C14-E14,0) -> #N/A | D15: =IF($C15<>0,Inputs!$B$14/12*C15,0) -> #N/A | E15: =F15-D15 -> #N/A | F15: =IF($C15>0,-PMT(Inputs!$B$14/12,Inputs!$B$15,Inputs!$B$11-Inputs!$B$13),0) -> #N/A | H15: =IF(H14>0,H14-J14,0) -> 0 | I15: =IF($H15<>0,Inputs!$B$28/12*H15,0) -> 0 | J15: =K15-I15 -> 0 | K15: =IF(H15>0,IF(H15+I15>K14,K14,H15+I15),0) -> 0
... A485: =YEAR(B485) -> 2065 | B485: =EDATE(B484,1) -> 60327 | C485: =IF(C484>0,C484-E484,0) -> #N/A | D485: =IF($C485<>0,Inputs!$B$14/12*C485,0) -> #N/A | E485: =F485-D485 -> #N/A | F485: =IF($C485>0,-PMT(Inputs!$B$14/12,Inputs!$B$15,Inputs!$B$11-Inputs!$B$13),0) -> #N/A | H485: =IF(H484>0,H484-J484,0) -> 0 | I485: =IF($H485<>0,Inputs!$B$28/12*H485,0) -> 0 | J485: =K485-I485 -> 0 | K485: =IF(H485>0,IF(H485+I485>K484,K484,H485+I485),0) -> 0

Sheet Pivot
D1: Purchase price | E1: 970000 | G1: Capital | H1: 350000 | P1: 4plex Guess Price (filter) | Q1: 650000 | S1: Select | T1: Address | U1: Rent | V1: Notes
D2: Beds | E2: 8 | G2: Downpayment (%) | H2: 0.25 | N2: =825000/200 -> 4125 | P2: Purchase price reduction | Q2: 0.1 | S2: 1 | T2: 3334 S 825 E, Salt Lake City, UT 84106 | U2: =1525+1400+1235+1350+1350+1385 -> 8245 | V2: CapRate: 4.9%; GRM: 178.8
A3: beds | B3: (All) | D3: Monthly Rent | E3: =2400+1400+1450 -> 5250 | G3: pp | H3: =H1/H2 -> 1400000 | K3: Max Price | L3: PMT | P3: Buyer's Commission | Q3: 0 | S3: 0 | T3: 1309 Hidden Creek Ct, Salt Lake City, UT 84117 | U3: =1450+1525+1445+1470 -> 5890 | V3: CapRate: 5.6%; GRM: 156.5
A4: homeStatus | B4: (All) | D4: Calc Rent Mult | E4: =E1/(E2*660) -> 183.71212 | F4: =_xlfn.RANK.AVG(E4,H10:H94) -> #N/A | G4: Target GRM | H4: 200 | J4: Investment | K4: =300000/0.25 -> 1200000 | L4: =PMT(0.07/12,30*360,-K4*0.97*0.75) -> 5092.5 | P4: Decrease of Listing | Q4: =(Q7/(1-Q2))-Q7 -> #N/A | S4: 0 | T4: 1711 W 400 N, Salt Lake City, UT 84116 | U4: 6345 | V4: CapRate: 5.9%; GRM: 149.1 | W4: Rose Park
A5: homeType | B5: (All) | D5: Rent Multiplier | E5: =E1/E3 -> 184.7619 | G5: Rent | H5: =H3/H4 -> 7000 | J5: Personal Home | K5: =300000/0.15 -> 2000000 | L5: =PMT(0.07/12,30*360,-K5*0.97*0.95) -> 10750.833 | P5: ="CapRate: "&TEXT(Inputs!B47,"0.0%") -> #N/A | Q5: =Inputs!B47 -> #N/A | S5: 0 | T5: 827 E 100 S, Salt Lake City, UT 84102 | U5: =950+1100+1100+1100 -> 4250 | V5: CapRate: 5.0%; GRM: 164.1
A6: addressZipcode | B6: (All) | D6: Inv GRM | E6: =E3/(E1)*1000 -> 5.4123711 | G6: Units | H6: 4 | P6: ="GRM: "&TEXT(Inputs!B48,"0.0") -> #N/A | Q6: =Inputs!B48 -> #N/A | R6: =_xlfn.TEXTJOIN("; ",TRUE,P5:P6) -> #N/A | S6: 0 | T6: 311 E 3360 S, Salt Lake City, UT 84115 | U6: =1500*4 -> 6000 | V6: CapRate: 4.1%; GRM: 188.6
A7: 4plex est? | B7: 1 | G7: Rent / Unit | H7: =H5/H6 -> 1750 | P7: PP | Q7: =Inputs!B11 -> #N/A
A9: address | B9: city_tag | C9: addressCity | D9: detailUrl | E9: unformattedPrice | F9: rentZestimate | G9: Sum of Rent Est. | H9: Sum of beds | I9: Sum of ReqDwnPmt | J9: Sum of Taxes | K9: Sum of Insurance | L9: Sum of DaysOnZillow | M9: Sum of SqFtMulti | N9: Sum of AvgRentMulti | O9: Select | P9: Rent Override | Q9: Rent | R9: Notes | S9: 0 | T9: 288 E 10th Ave, Salt Lake City, UT 84103 | U9: =1775+1295+1025+895 -> 4990 | V9: CapRate: 3.0%; GRM: 238.1
A10: 351 S 300 E, Salt Lake City, UT 84111 | B10: Salt Lake City | C10: Salt Lake City | D10: https://www.zillow.com/homedetails/351-S-300-E-Salt-Lake-City-UT-84111/141869764_zpid/ | E10: 700000 | F10: 1488 | G10: 3960 | H10: 6 | I10: 175000 | J10: 344.16667 | K10: 250.83333 | L10: 34.06522 | M10: 200 | N10: 332.43728 | O10: =IFERROR(_xlfn.XLOOKUP(A10,$T$1:$T$13,$S$1:$S$13,,0),0) -> 0 | P10: =IFERROR(_xlfn.XLOOKUP(A10,$T$1:$T$13,$U$1:$U$13,,0),0) -> 0 | Q10: =IF(P10>1,P10,G10) -> 3960 | R10: =IFERROR(_xlfn.XLOOKUP(A10,$T$1:$T$13,$V$1:$V$13,,0),0) -> 0 | S10: 0 | T10: 64 N F St, Salt Lake City, UT 84103 | U10: =1500+1215+1800 -> 4515 | V10: CapRate: 3.8%; GRM: 207.1
A11: 435 S 900 W, Salt Lake City, UT 84104 | B11: Salt Lake City | C11: Salt Lake City | D11: https://www.zillow.com/homedetails/435-S-900-W-Salt-Lake-City-UT-84104/339788697_zpid/ | E11: 789900 | F11: 1645 | G11: 4620 | H11: 7 | I11: 197475 | J11: 388.3675 | K11: 283.0475 | L11: 89.064444 | M11: 216.47027 | N11: 334.1269 | O11: =IFERROR(_xlfn.XLOOKUP(A11,$T$1:$T$13,$S$1:$S$13,,0),0) -> 0 | P11: =IFERROR(_xlfn.XLOOKUP(A11,$T$1:$T$13,$U$1:$U$13,,0),0) -> 0 | Q11: =IF(P11>1,P11,G11) -> 4620 | R11: =IFERROR(_xlfn.XLOOKUP(A11,$T$1:$T$13,$V$1:$V$13,,0),0) -> 0 | S11: 0 | T11: 2269 S Green St #1-4, Salt Lake City, UT 84106 | U11: =575+1650+900+800 -> 3925 | V11: CapRate: 4.6%; GRM: 187.8
A12: 509 E 800 S, Salt Lake City, UT 84102 | B12: Salt Lake City | C12: Salt Lake City | D12: https://www.zillow.com/homedetails/509-E-800-S-Salt-Lake-City-UT-84102/305058100_zpid/ | E12: 749000 | F12: 2725 | G12: 2640 | H12: 4 | I12: 187250 | J12: 368.25833 | K12: 268.39167 | L12: 25.073032 | M12: 225.33093 | N12: 293.47286 | O12: =IFERROR(_xlfn.XLOOKUP(A12,$T$1:$T$13,$S$1:$S$13,,0),0) -> 0 | P12: =IFERROR(_xlfn.XLOOKUP(A12,$T$1:$T$13,$U$1:$U$13,,0),0) -> 0 | Q12: =IF(P12>1,P12,G12) -> 2640 | R12: =IFERROR(_xlfn.XLOOKUP(A12,$T$1:$T$13,$V$1:$V$13,,0),0) -> 0 | S12: 0 | T12: 423 E 1st Ave, Salt Lake City, UT 84103 | U12: =1210+1140+1290 -> 3640 | V12: CapRate: 3.9%; GRM: 186.3
A13: 606 W North Temple, Salt Lake City, UT 84116 | B13: Salt Lake City | C13: Salt Lake City | D13: https://www.zillow.com/homedetails/606-W-North-Temple-Salt-Lake-City-UT-84116/446037534_zpid/ | E13: 6750000 | F13: (blank) | G13: 14520 | H13: 22 | I13: 1687500 | J13: 3318.75 | K13: 2418.75 | L13: 72.065243 | M13: 228.32595 | N13: 511.36364 | O13: =IFERROR(_xlfn.XLOOKUP(A13,$T$1:$T$13,$S$1:$S$13,,0),0) -> 0 | P13: =IFERROR(_xlfn.XLOOKUP(A13,$T$1:$T$13,$U$1:$U$13,,0),0) -> 0 | Q13: =IF(P13>1,P13,G13) -> 14520 | R13: =IFERROR(_xlfn.XLOOKUP(A13,$T$1:$T$13,$V$1:$V$13,,0),0) -> 0 | S13: 0 | T13: 152 E 3rd Ave N, Salt Lake City, UT 84103 | U13: =2700+1800 -> 4500 | V13: =R6 -> #N/A
A14: 228 S 900 E, Salt Lake City, UT 84102 | B14: Salt Lake City | C14: Salt Lake City | D14: https://www.zillow.com/homedetails/228-S-900-E-Salt-Lake-City-UT-84102/2069452025_zpid/ | E14: 1799000 | F14: 2041 | G14: 10560 | H14: 16 | I14: 449750 | J14: 884.50833 | K14: 644.64167 | L14: 187.0808 | M14: 230.8482 | N14: 534.41325 | O14: =IFERROR(_xlfn.XLOOKUP(A14,$T$1:$T$13,$S$1:$S$13,,0),0) -> 0 | P14: =IFERROR(_xlfn.XLOOKUP(A14,$T$1:$T$13,$U$1:$U$13,,0),0) -> 0 | Q14: =IF(P14>1,P14,G14) -> 10560 | R14: =IFERROR(_xlfn.XLOOKUP(A14,$T$1:$T$13,$V$1:$V$13,,0),0) -> 0
A15: 275 W 500 N, Salt Lake City, UT 84103 | B15: Salt Lake City | C15: Salt Lake City | D15: https://www.zillow.com/homedetails/275-W-500-N-Salt-Lake-City-UT-84103/2086478311_zpid/ | E15: 835000 | F15: 2245 | G15: 3960 | H15: 6 | I15: 208750 | J15: 410.54167 | K15: 299.20833 | L15: 213.06398 | M15: 234.74838 | N15: 301.94104 | O15: =IFERROR(_xlfn.XLOOKUP(A15,$T$1:$T$13,$S$1:$S$13,,0),0) -> 0 | P15: =IFERROR(_xlfn.XLOOKUP(A15,$T$1:$T$13,$U$1:$U$13,,0),0) -> 0 | Q15: =IF(P15>1,P15,G15) -> 3960 | R15: =IFERROR(_xlfn.XLOOKUP(A15,$T$1:$T$13,$V$1:$V$13,,0),0) -> 0
A16: 1019 E 1700 S, Salt Lake City, UT 84105 | B16: Salt Lake City | C16: Salt Lake City | D16: https://www.zillow.com/homedetails/1019-E-1700-S-Salt-Lake-City-UT-84105/350304499_zpid/ | E16: 1250000 | F16: 2712 | G16: 3960 | H16: 6 | I16: 312500 | J16: 614.58333 | K16: 447.91667 | L16: 104.06566 | M16: 239.69319 | N16: 404.06834 | O16: =IFERROR(_xlfn.XLOOKUP(A16,$T$1:$T$13,$S$1:$S$13,,0),0) -> 0 | P16: =IFERROR(_xlfn.XLOOKUP(A16,$T$1:$T$13,$U$1:$U$13,,0),0) -> 0 | Q16: =IF(P16>1,P16,G16) -> 3960 | R16: =IFERROR(_xlfn.XLOOKUP(A16,$T$1:$T$13,$V$1:$V$13,,0),0) -> 0
A17: 1162 E 400 S, Salt Lake City, UT 84102 | B17: Salt Lake City | C17: Salt Lake City | D17: https://www.zillow.com/homedetails/1162-E-400-S-Salt-Lake-City-UT-84102/2057508524_zpid/ | E17: 2300000 | F17: 1863 | G17: 10560 | H17: 16 | I17: 575000 | J17: 1130.8333 | K17: 824.16667 | L17: 240.06345 | M17: 240.5103 | N17: 737.07562 | O17: =IFERROR(_xlfn.XLOOKUP(A17,$T$1:$T$13,$S$1:$S$13,,0),0) -> 0 | P17: =IFERROR(_xlfn.XLOOKUP(A17,$T$1:$T$13,$U$1:$U$13,,0),0) -> 0 | Q17: =IF(P17>1,P17,G17) -> 10560 | R17: =IFERROR(_xlfn.XLOOKUP(A17,$T$1:$T$13,$V$1:$V$13,,0),0) -> 0
A18: 1612 S 500 E, Salt Lake City, UT 84105 | B18: Salt Lake City | C18: Salt Lake City | D18: https://www.zillow.com/homedetails/1612-S-500-E-Salt-Lake-City-UT-84105/12772179_zpid/ | E18: 724900 | F18: 2193 | G18: 5280 | H18: 8 | I18: 181225 | J18: 356.40917 | K18: 259.75583 | L18: 83.064248 | M18: 241.63333 | N18: 240.78629 | O18: =IFERROR(_xlfn.XLOOKUP(A18,$T$1:$T$13,$S$1:$S$13,,0),0) -> 0 | P18: =IFERROR(_xlfn.XLOOKUP(A18,$T$1:$T$13,$U$1:$U$13,,0),0) -> 0 | Q18: =IF(P18>1,P18,G18) -> 5280 | R18: =IFERROR(_xlfn.XLOOKUP(A18,$T$1:$T$13,$V$1:$V$13,,0),0) -> 0
A19: 1155 E 200 S, Salt Lake City, UT 84102 | B19: Salt Lake City | C19: Salt Lake City | D19: https://www.zillow.com/homedetails/1155-E-200-S-Salt-Lake-City-UT-84102/457834492_zpid/ | E19: 5300000 | F19: (blank) | G19: 15840 | H19: 24 | I19: 1325000 | J19: 2605.8333 | K19: 1899.1667 | L19: 18.064363 | M19: 243.34252 | N19: 368.05556 | O19: =IFERROR(_xlfn.XLOOKUP(A19,$T$1:$T$13,$S$1:$S$13,,0),0) -> 0 | P19: =IFERROR(_xlfn.XLOOKUP(A19,$T$1:$T$13,$U$1:$U$13,,0),0) -> 0 | Q19: =IF(P19>1,P19,G19) -> 15840 | R19: =IFERROR(_xlfn.XLOOKUP(A19,$T$1:$T$13,$V$1:$V$13,,0),0) -> 0
A20: 862 E Menlo Ave, Salt Lake City, UT 84102 | B20: Salt Lake City | C20: Salt Lake City | D20: https://www.zillow.com/homedetails/862-E-Menlo-Ave-Salt-Lake-City-UT-84102/12753475_zpid/ | E20: 699000 | F20: 2064 | G20: 4620 | H20: 7 | I20: 174750 | J20: 343.675 | K20: 250.475 | L20: 187.0808 | M20: 246.12676 | N20: 252.54568 | O20: =IFERROR(_xlfn.XLOOKUP(A20,$T$1:$T$13,$S$1:$S$13,,0),0) -> 0 | P20: =IFERROR(_xlfn.XLOOKUP(A20,$T$1:$T$13,$U$1:$U$13,,0),0) -> 0 | Q20: =IF(P20>1,P20,G20) -> 4620 | R20: =IFERROR(_xlfn.XLOOKUP(A20,$T$1:$T$13,$V$1:$V$13,,0),0) -> 0
A21: 2530 S Parkcrest Dr, West Valley City, UT 84119 | B21: Salt Lake City | C21: West Valley City | D21: https://www.zillow.com/homedetails/2530-S-Parkcrest-Dr-West-Valley-City-UT-84119/141854429_zpid/ | E21: 830000 | F21: 1555 | G21: 5280 | H21: 8 | I21: 207500 | J21: 408.08333 | K21: 297.41667 | L21: 26.064815 | M21: 246.14472 | N21: 353.33936 | O21: =IFERROR(_xlfn.XLOOKUP(A21,$T$1:$T$13,$S$1:$S$13,,0),0) -> 0 | P21: =IFERROR(_xlfn.XLOOKUP(A21,$T$1:$T$13,$U$1:$U$13,,0),0) -> 0 | Q21: =IF(P21>1,P21,G21) -> 5280 | R21: =IFERROR(_xlfn.XLOOKUP(A21,$T$1:$T$13,$V$1:$V$13,,0),0) -> 0
A22: 240 N Spencer Ct, Salt Lake City, UT 84103 | B22: Avenues | C22: Salt Lake City | D22: https://www.zillow.com/homedetails/240-N-Spencer-Ct-Salt-Lake-City-UT-84103/12718744_zpid/ | E22: 3699000 | F22: 2222 | G22: 19800 | H22: 30 | I22: 924750 | J22: 1818.675 | K22: 1325.475 | L22: 228.06343 | M22: 248.94004 | N22: 935.10824 | O22: =IFERROR(_xlfn.XLOOKUP(A22,$T$1:$T$13,$S$1:$S$13,,0),0) -> 0 | P22: =IFERROR(_xlfn.XLOOKUP(A22,$T$1:$T$13,$U$1:$U$13,,0),0) -> 0 | Q22: =IF(P22>1,P22,G22) -> 19800 | R22: =IFERROR(_xlfn.XLOOKUP(A22,$T$1:$T$13,$V$1:$V$13,,0),0) -> 0
A23: 416 E Scott Ave, Salt Lake City, UT 84115 | B23: Salt Lake City | C23: Salt Lake City | D23: https://www.zillow.com/homedetails/416-E-Scott-Ave-Salt-Lake-City-UT-84115/305059086_zpid/ | E23: 2200000 | F23: 1833 | G23: 11880 | H23: 18 | I23: 550000 | J23: 1081.6667 | K23: 788.33333 | L23: 167.06561 | M23: 253.9536 | N23: 701.96096 | O23: =IFERROR(_xlfn.XLOOKUP(A23,$T$1:$T$13,$S$1:$S$13,,0),0) -> 0 | P23: =IFERROR(_xlfn.XLOOKUP(A23,$T$1:$T$13,$U$1:$U$13,,0),0) -> 0 | Q23: =IF(P23>1,P23,G23) -> 11880 | R23: =IFERROR(_xlfn.XLOOKUP(A23,$T$1:$T$13,$V$1:$V$13,,0),0) -> 0
A24: 2870 W 3100 S, West Valley City, UT 84119 | B24: Salt Lake City | C24: West Valley City | D24: https://www.zillow.com/homedetails/2870-W-3100-S-West-Valley-City-UT-84119/12743620_zpid/ | E24: 869000 | F24: 2303 | G24: 4620 | H24: 7 | I24: 217250 | J24: 427.25833 | K24: 311.39167 | L24: 72.065579 | M24: 254.83871 | N24: 292.11934 | O24: =IFERROR(_xlfn.XLOOKUP(A24,$T$1:$T$13,$S$1:$S$13,,0),0) -> 0 | P24: =IFERROR(_xlfn.XLOOKUP(A24,$T$1:$T$13,$U$1:$U$13,,0),0) -> 0 | Q24: =IF(P24>1,P24,G24) -> 4620 | R24: =IFERROR(_xlfn.XLOOKUP(A24,$T$1:$T$13,$V$1:$V$13,,0),0) -> 0
A25: 1314 E Crandall Ave, Salt Lake City, UT 84106 | B25: Salt Lake City | C25: Salt Lake City | D25: https://www.zillow.com/homedetails/1314-E-Crandall-Ave-Salt-Lake-City-UT-84106/12783602_zpid/ | E25: 805000 | F25: 2234 | G25: 3960 | H25: 6 | I25: 201250 | J25: 395.79167 | K25: 288.45833 | L25: 81.065116 | M25: 259.84506 | N25: 291.97565 | O25: =IFERROR(_xlfn.XLOOKUP(A25,$T$1:$T$13,$S$1:$S$13,,0),0) -> 0 | P25: =IFERROR(_xlfn.XLOOKUP(A25,$T$1:$T$13,$U$1:$U$13,,0),0) -> 0 | Q25: =IF(P25>1,P25,G25) -> 3960 | R25: =IFERROR(_xlfn.XLOOKUP(A25,$T$1:$T$13,$V$1:$V$13,,0),0) -> 0
A26: 751 E Scott Ave, Millcreek, UT 84106 | B26: Millcreek | C26: Millcreek | D26: https://www.zillow.com/homedetails/751-E-Scott-Ave-Millcreek-UT-84106/305058922_zpid/ | E26: 1890000 | F26: 1761 | G26: 8580 | H26: 13 | I26: 472500 | J26: 929.25 | K26: 677.25 | L26: 177.06569 | M26: 261.77285 | N26: 657.78076 | O26: =IFERROR(_xlfn.XLOOKUP(A26,$T$1:$T$13,$S$1:$S$13,,0),0) -> 0 | P26: =IFERROR(_xlfn.XLOOKUP(A26,$T$1:$T$13,$U$1:$U$13,,0),0) -> 0 | Q26: =IF(P26>1,P26,G26) -> 8580 | R26: =IFERROR(_xlfn.XLOOKUP(A26,$T$1:$T$13,$V$1:$V$13,,0),0) -> 0
A27: 2754 W 3835 S, West Valley City, UT 84119 | B27: Salt Lake City | C27: West Valley City | D27: https://www.zillow.com/homedetails/2754-W-3835-S-West-Valley-City-UT-84119/333158912_zpid/ | E27: 800000 | F27: 1721 | G27: 3960 | H27: 6 | I27: 200000 | J27: 393.33333 | K27: 286.66667 | L27: 44.046771 | M27: 264.98841 | N27: 343.53412 | O27: =IFERROR(_xlfn.XLOOKUP(A27,$T$1:$T$13,$S$1:$S$13,,0),0) -> 0 | P27: =IFERROR(_xlfn.XLOOKUP(A27,$T$1:$T$13,$U$1:$U$13,,0),0) -> 0 | Q27: =IF(P27>1,P27,G27) -> 3960 | R27: =IFERROR(_xlfn.XLOOKUP(A27,$T$1:$T$13,$V$1:$V$13,,0),0) -> 0
A28: 64 N F St, Salt Lake City, UT 84103 | B28: Avenues | C28: Salt Lake City | D28: https://www.zillow.com/homedetails/64-N-F-St-Salt-Lake-City-UT-84103/305056275_zpid/ | E28: 960000 | F28: 2096 | G28: 3960 | H28: 6 | I28: 240000 | J28: 472 | K28: 344 | L28: 106.06528 | M28: 266.66667 | N28: 362.34097 | O28: =IFERROR(_xlfn.XLOOKUP(A28,$T$1:$T$13,$S$1:$S$13,,0),0) -> 0 | P28: =IFERROR(_xlfn.XLOOKUP(A28,$T$1:$T$13,$U$1:$U$13,,0),0) -> 4515 | Q28: =IF(P28>1,P28,G28) -> 4515 | R28: =IFERROR(_xlfn.XLOOKUP(A28,$T$1:$T$13,$V$1:$V$13,,0),0) -> CapRate: 3.8%; GRM: 207.1
A29: 745 S 600 E, Salt Lake City, UT 84102 | B29: Salt Lake City | C29: Salt Lake City | D29: https://www.zillow.com/homedetails/745-S-600-E-Salt-Lake-City-UT-84102/12756964_zpid/ | E29: 705000 | F29: 2125 | G29: 2640 | H29: 4 | I29: 176250 | J29: 346.625 | K29: 252.625 | L29: 113.06025 | M29: 268.46915 | N29: 312.75735 | O29: =IFERROR(_xlfn.XLOOKUP(A29,$T$1:$T$13,$S$1:$S$13,,0),0) -> 0 | P29: =IFERROR(_xlfn.XLOOKUP(A29,$T$1:$T$13,$U$1:$U$13,,0),0) -> 0 | Q29: =IF(P29>1,P29,G29) -> 2640 | R29: =IFERROR(_xlfn.XLOOKUP(A29,$T$1:$T$13,$V$1:$V$13,,0),0) -> 0
A30: 3532 S 900 E, Salt Lake City, UT 84106 | B30: Millcreek | C30: Salt Lake City | D30: https://www.zillow.com/homedetails/3532-S-900-E-Salt-Lake-City-UT-84106/2069834554_zpid/ | E30: 1900000 | F30: 3034 | G30: 3960 | H30: 6 | I30: 475000 | J30: 934.16667 | K30: 680.83333 | L30: 48.065463 | M30: 268.62717 | N30: 577.00688 | O30: =IFERROR(_xlfn.XLOOKUP(A30,$T$1:$T$13,$S$1:$S$13,,0),0) -> 0 | P30: =IFERROR(_xlfn.XLOOKUP(A30,$T$1:$T$13,$U$1:$U$13,,0),0) -> 0 | Q30: =IF(P30>1,P30,G30) -> 3960 | R30: =IFERROR(_xlfn.XLOOKUP(A30,$T$1:$T$13,$V$1:$V$13,,0),0) -> 0
A31: 1021 E Millbert Ave, Salt Lake City, UT 84106 | B31: Millcreek | C31: Salt Lake City | D31: https://www.zillow.com/homedetails/1021-E-Millbert-Ave-Salt-Lake-City-UT-84106/12790416_zpid/ | E31: 1140000 | F31: 2537 | G31: 5280 | H31: 8 | I31: 285000 | J31: 560.5 | K31: 408.5 | L31: 34.064282 | M31: 268.74116 | N31: 343.42481 | O31: =IFERROR(_xlfn.XLOOKUP(A31,$T$1:$T$13,$S$1:$S$13,,0),0) -> 0 | P31: =IFERROR(_xlfn.XLOOKUP(A31,$T$1:$T$13,$U$1:$U$13,,0),0) -> 0 | Q31: =IF(P31>1,P31,G31) -> 5280 | R31: =IFERROR(_xlfn.XLOOKUP(A31,$T$1:$T$13,$V$1:$V$13,,0),0) -> 0
A32: 182 E Kelsey Ave, Salt Lake City, UT 84111 | B32: Salt Lake City | C32: Salt Lake City | D32: https://www.zillow.com/homedetails/182-E-Kelsey-Ave-Salt-Lake-City-UT-84111/12757584_zpid/ | E32: 849900 | F32: 2806 | G32: 4620 | H32: 7 | I32: 212475 | J32: 417.8675 | K32: 304.5475 | L32: 86.065787 | M32: 271.18698 | N32: 252.62191 | O32: =IFERROR(_xlfn.XLOOKUP(A32,$T$1:$T$13,$S$1:$S$13,,0),0) -> 0 | P32: =IFERROR(_xlfn.XLOOKUP(A32,$T$1:$T$13,$U$1:$U$13,,0),0) -> 0 | Q32: =IF(P32>1,P32,G32) -> 4620 | R32: =IFERROR(_xlfn.XLOOKUP(A32,$T$1:$T$13,$V$1:$V$13,,0),0) -> 0
A33: 64 F St, Salt Lake City, UT 84103 | B33: Avenues | C33: Salt Lake City | D33: https://www.zillow.com/homedetails/64-F-St-Salt-Lake-City-UT-84103/2111734021_zpid/ | E33: 979000 | F33: 1942 | G33: 0 | I33: 244750 | J33: 481.34167 | K33: 350.80833 | L33: 66.086343 | M33: 271.94444 | N33: 1067.8931 | O33: =IFERROR(_xlfn.XLOOKUP(A33,$T$1:$T$13,$S$1:$S$13,,0),0) -> 0 | P33: =IFERROR(_xlfn.XLOOKUP(A33,$T$1:$T$13,$U$1:$U$13,,0),0) -> 0 | Q33: =IF(P33>1,P33,G33) -> 0 | R33: =IFERROR(_xlfn.XLOOKUP(A33,$T$1:$T$13,$V$1:$V$13,,0),0) -> 0
A34: 1309 Hidden Creek Ct, Salt Lake City, UT 84117 | B34: Millcreek | C34: Salt Lake City | D34: https://www.zillow.com/homedetails/1309-Hidden-Creek-Ct-Salt-Lake-City-UT-84117/12858462_zpid/ | E34: 950000 | F34: 2785 | G34: 2640 | H34: 4 | I34: 237500 | J34: 467.08333 | K34: 340.41667 | L34: 143.06534 | M34: 277.53433 | N34: 368.47322 | O34: =IFERROR(_xlfn.XLOOKUP(A34,$T$1:$T$13,$S$1:$S$13,,0),0) -> 0 | P34: =IFERROR(_xlfn.XLOOKUP(A34,$T$1:$T$13,$U$1:$U$13,,0),0) -> 5890 | Q34: =IF(P34>1,P34,G34) -> 5890 | R34: =IFERROR(_xlfn.XLOOKUP(A34,$T$1:$T$13,$V$1:$V$13,,0),0) -> CapRate: 5.6%; GRM: 156.5
A35: 1815 E Hillcrest Ave, Salt Lake City, UT 84106 | B35: Salt Lake City | C35: Salt Lake City | D35: https://www.zillow.com/homedetails/1815-E-Hillcrest-Ave-Salt-Lake-City-UT-84106/12777839_zpid/ | E35: 685000 | F35: 2084 | G35: 2640 | H35: 4 | I35: 171250 | J35: 336.79167 | K35: 245.45833 | L35: 9.8127199 | M35: 277.77778 | N35: 307.05574 | O35: =IFERROR(_xlfn.XLOOKUP(A35,$T$1:$T$13,$S$1:$S$13,,0),0) -> 0 | P35: =IFERROR(_xlfn.XLOOKUP(A35,$T$1:$T$13,$U$1:$U$13,,0),0) -> 0 | Q35: =IF(P35>1,P35,G35) -> 2640 | R35: =IFERROR(_xlfn.XLOOKUP(A35,$T$1:$T$13,$V$1:$V$13,,0),0) -> 0
A36: 2200 S Wasatch Dr, Salt Lake City, UT 84109 | B36: Salt Lake City | C36: Salt Lake City | D36: https://www.zillow.com/homedetails/2200-S-Wasatch-Dr-Salt-Lake-City-UT-84109/12779572_zpid/ | E36: 850000 | F36: 2717 | G36: 2640 | H36: 4 | I36: 212500 | J36: 417.91667 | K36: 304.58333 | L36: 163.06446 | M36: 281.64347 | N36: 333.50586 | O36: =IFERROR(_xlfn.XLOOKUP(A36,$T$1:$T$13,$S$1:$S$13,,0),0) -> 0 | P36: =IFERROR(_xlfn.XLOOKUP(A36,$T$1:$T$13,$U$1:$U$13,,0),0) -> 0 | Q36: =IF(P36>1,P36,G36) -> 2640 | R36: =IFERROR(_xlfn.XLOOKUP(A36,$T$1:$T$13,$V$1:$V$13,,0),0) -> 0
A37: 1145 E Kensington Ave, Salt Lake City, UT 84105 | B37: Salt Lake City | C37: Salt Lake City | D37: https://www.zillow.com/homedetails/1145-E-Kensington-Ave-Salt-Lake-City-UT-84105/12769747_zpid/ | E37: 734999 | F37: 1804 | G37: 2640 | H37: 4 | I37: 183749.75 | J37: 361.37451 | K37: 263.37464 | L37: 134.06436 | M37: 283.01848 | N37: 356.83848 | O37: =IFERROR(_xlfn.XLOOKUP(A37,$T$1:$T$13,$S$1:$S$13,,0),0) -> 0 | P37: =IFERROR(_xlfn.XLOOKUP(A37,$T$1:$T$13,$U$1:$U$13,,0),0) -> 0 | Q37: =IF(P37>1,P37,G37) -> 2640 | R37: =IFERROR(_xlfn.XLOOKUP(A37,$T$1:$T$13,$V$1:$V$13,,0),0) -> 0
A38: 1978 S Windsor St, Salt Lake City, UT 84105 | B38: Salt Lake City | C38: Salt Lake City | D38: https://www.zillow.com/homedetails/1978-S-Windsor-St-Salt-Lake-City-UT-84105/12770679_zpid/ | E38: 1149000 | F38: 3017 | G38: 3960 | H38: 6 | I38: 287250 | J38: 564.925 | K38: 411.725 | L38: 187.0645 | M38: 283.56367 | N38: 350.00428 | O38: =IFERROR(_xlfn.XLOOKUP(A38,$T$1:$T$13,$S$1:$S$13,,0),0) -> 0 | P38: =IFERROR(_xlfn.XLOOKUP(A38,$T$1:$T$13,$U$1:$U$13,,0),0) -> 0 | Q38: =IF(P38>1,P38,G38) -> 3960 | R38: =IFERROR(_xlfn.XLOOKUP(A38,$T$1:$T$13,$V$1:$V$13,,0),0) -> 0
A39: 365 S Elizabeth St, Salt Lake City, UT 84102 | B39: Salt Lake City | C39: Salt Lake City | D39: https://www.zillow.com/homedetails/365-S-Elizabeth-St-Salt-Lake-City-UT-84102/141868419_zpid/ | E39: 879000 | F39: 3100 | G39: 3960 | H39: 6 | I39: 219750 | J39: 432.175 | K39: 314.975 | L39: 106.85865 | M39: 286.13281 | N39: 263.85753 | O39: =IFERROR(_xlfn.XLOOKUP(A39,$T$1:$T$13,$S$1:$S$13,,0),0) -> 0 | P39: =IFERROR(_xlfn.XLOOKUP(A39,$T$1:$T$13,$U$1:$U$13,,0),0) -> 0 | Q39: =IF(P39>1,P39,G39) -> 3960 | R39: =IFERROR(_xlfn.XLOOKUP(A39,$T$1:$T$13,$V$1:$V$13,,0),0) -> 0
A40: 609 E 6th Ave, Salt Lake City, UT 84103 | B40: Avenues | C40: Salt Lake City | D40: https://www.zillow.com/homedetails/609-E-6th-Ave-Salt-Lake-City-UT-84103/305056306_zpid/ | E40: 1000000 | F40: 1758 | G40: 2640 | H40: 4 | I40: 250000 | J40: 491.66667 | K40: 358.33333 | L40: 11.063391 | M40: 288.35063 | N40: 492.74744 | O40: =IFERROR(_xlfn.XLOOKUP(A40,$T$1:$T$13,$S$1:$S$13,,0),0) -> 0 | P40: =IFERROR(_xlfn.XLOOKUP(A40,$T$1:$T$13,$U$1:$U$13,,0),0) -> 0 | Q40: =IF(P40>1,P40,G40) -> 2640 | R40: =IFERROR(_xlfn.XLOOKUP(A40,$T$1:$T$13,$V$1:$V$13,,0),0) -> 0
A41: 465 E 3300 S, Salt Lake City, UT 84115 | B41: Salt Lake City | C41: Salt Lake City | D41: https://www.zillow.com/homedetails/465-E-3300-S-Salt-Lake-City-UT-84115/83825002_zpid/ | E41: 1200000 | F41: 2270 | G41: 1980 | H41: 3 | I41: 300000 | J41: 590 | K41: 430 | L41: 124.06523 | M41: 291.61604 | N41: 597.65051 | O41: =IFERROR(_xlfn.XLOOKUP(A41,$T$1:$T$13,$S$1:$S$13,,0),0) -> 0 | P41: =IFERROR(_xlfn.XLOOKUP(A41,$T$1:$T$13,$U$1:$U$13,,0),0) -> 0 | Q41: =IF(P41>1,P41,G41) -> 1980 | R41: =IFERROR(_xlfn.XLOOKUP(A41,$T$1:$T$13,$V$1:$V$13,,0),0) -> 0
A42: 653 E 300 S, Salt Lake City, UT 84102 | B42: Salt Lake City | C42: Salt Lake City | D42: https://www.zillow.com/homedetails/653-E-300-S-Salt-Lake-City-UT-84102/2071449994_zpid/ | E42: 2400000 | F42: 2052 | G42: 11880 | H42: 18 | I42: 600000 | J42: 1180 | K42: 860 | L42: 261.06513 | M42: 293.54207 | N42: 695.90643 | O42: =IFERROR(_xlfn.XLOOKUP(A42,$T$1:$T$13,$S$1:$S$13,,0),0) -> 0 | P42: =IFERROR(_xlfn.XLOOKUP(A42,$T$1:$T$13,$U$1:$U$13,,0),0) -> 0 | Q42: =IF(P42>1,P42,G42) -> 11880 | R42: =IFERROR(_xlfn.XLOOKUP(A42,$T$1:$T$13,$V$1:$V$13,,0),0) -> 0
A43: 215 S 300 E, Salt Lake City, UT 84111 | B43: Salt Lake City | C43: Salt Lake City | D43: https://www.zillow.com/homedetails/215-S-300-E-Salt-Lake-City-UT-84111/447546849_zpid/ | E43: 2300000 | F43: (blank) | G43: 13200 | H43: 20 | I43: 575000 | J43: 1130.8333 | K43: 824.16667 | L43: 207.06522 | M43: 298.27519 | N43: 191.66667 | O43: =IFERROR(_xlfn.XLOOKUP(A43,$T$1:$T$13,$S$1:$S$13,,0),0) -> 0 | P43: =IFERROR(_xlfn.XLOOKUP(A43,$T$1:$T$13,$U$1:$U$13,,0),0) -> 0 | Q43: =IF(P43>1,P43,G43) -> 13200 | R43: =IFERROR(_xlfn.XLOOKUP(A43,$T$1:$T$13,$V$1:$V$13,,0),0) -> 0
A44: 1361 S 1000 W, Salt Lake City, UT 84104 | B44: Salt Lake City | C44: Salt Lake City | D44: https://www.zillow.com/homedetails/1361-S-1000-W-Salt-Lake-City-UT-84104/448481083_zpid/ | E44: 925000 | F44: (blank) | G44: 3960 | H44: 6 | I44: 231250 | J44: 454.79167 | K44: 331.45833 | L44: 110.96519 | M44: 298.3871 | N44: 256.94444 | O44: =IFERROR(_xlfn.XLOOKUP(A44,$T$1:$T$13,$S$1:$S$13,,0),0) -> 0 | P44: =IFERROR(_xlfn.XLOOKUP(A44,$T$1:$T$13,$U$1:$U$13,,0),0) -> 0 | Q44: =IF(P44>1,P44,G44) -> 3960 | R44: =IFERROR(_xlfn.XLOOKUP(A44,$T$1:$T$13,$V$1:$V$13,,0),0) -> 0
A45: 3605 S 900 E, Salt Lake City, UT 84106 | B45: Millcreek | C45: Salt Lake City | D45: https://www.zillow.com/homedetails/3605-S-900-E-Salt-Lake-City-UT-84106/2071960249_zpid/ | E45: 1800000 | F45: 1798 | G45: 10560 | H45: 16 | I45: 450000 | J45: 885 | K45: 645 | L45: 26.064178 | M45: 298.40849 | N45: 594.30617 | O45: =IFERROR(_xlfn.XLOOKUP(A45,$T$1:$T$13,$S$1:$S$13,,0),0) -> 0 | P45: =IFERROR(_xlfn.XLOOKUP(A45,$T$1:$T$13,$U$1:$U$13,,0),0) -> 0 | Q45: =IF(P45>1,P45,G45) -> 10560 | R45: =IFERROR(_xlfn.XLOOKUP(A45,$T$1:$T$13,$V$1:$V$13,,0),0) -> 0
A46: 1401 S 300 E, Salt Lake City, UT 84115 | B46: Salt Lake City | C46: Salt Lake City | D46: https://www.zillow.com/homedetails/1401-S-300-E-Salt-Lake-City-UT-84115/2071381728_zpid/ | E46: 2125000 | F46: 1554 | G46: 10560 | H46: 16 | I46: 531250 | J46: 1044.7917 | K46: 761.45833 | L46: 41.063229 | M46: 304.17979 | N46: 794.39652 | O46: =IFERROR(_xlfn.XLOOKUP(A46,$T$1:$T$13,$S$1:$S$13,,0),0) -> 0 | P46: =IFERROR(_xlfn.XLOOKUP(A46,$T$1:$T$13,$U$1:$U$13,,0),0) -> 0 | Q46: =IF(P46>1,P46,G46) -> 10560 | R46: =IFERROR(_xlfn.XLOOKUP(A46,$T$1:$T$13,$V$1:$V$13,,0),0) -> 0
A47: 2487 S 800 E, Salt Lake City, UT 84106 | B47: Salt Lake City | C47: Salt Lake City | D47: https://www.zillow.com/homedetails/2487-S-800-E-Salt-Lake-City-UT-84106/12775602_zpid/ | E47: 925000 | F47: 2344 | G47: 3300 | H47: 5 | I47: 231250 | J47: 454.79167 | K47: 331.45833 | L47: 107.06545 | M47: 304.67721 | N47: 351.47895 | O47: =IFERROR(_xlfn.XLOOKUP(A47,$T$1:$T$13,$S$1:$S$13,,0),0) -> 0 | P47: =IFERROR(_xlfn.XLOOKUP(A47,$T$1:$T$13,$U$1:$U$13,,0),0) -> 0 | Q47: =IF(P47>1,P47,G47) -> 3300 | R47: =IFERROR(_xlfn.XLOOKUP(A47,$T$1:$T$13,$V$1:$V$13,,0),0) -> 0
A48: 2519 S 300 E, Salt Lake City, UT 84115 | B48: Salt Lake City | C48: Salt Lake City | D48: https://www.zillow.com/homedetails/2519-S-300-E-Salt-Lake-City-UT-84115/2066606417_zpid/ | E48: 3800000 | F48: 1417 | G48: 15180 | H48: 23 | I48: 950000 | J48: 1868.3333 | K48: 1361.6667 | L48: 70.065729 | M48: 308.59185 | N48: 1478.5421 | O48: =IFERROR(_xlfn.XLOOKUP(A48,$T$1:$T$13,$S$1:$S$13,,0),0) -> 0 | P48: =IFERROR(_xlfn.XLOOKUP(A48,$T$1:$T$13,$U$1:$U$13,,0),0) -> 0 | Q48: =IF(P48>1,P48,G48) -> 15180 | R48: =IFERROR(_xlfn.XLOOKUP(A48,$T$1:$T$13,$V$1:$V$13,,0),0) -> 0
A49: 1027 E Emerson Ave S, Salt Lake City, UT 84105 | B49: Salt Lake City | C49: Salt Lake City | D49: https://www.zillow.com/homedetails/1027-E-Emerson-Ave-S-Salt-Lake-City-UT-84105/2069353394_zpid/ | E49: 1450000 | F49: 2098 | G49: 5280 | H49: 8 | I49: 362500 | J49: 712.91667 | K49: 519.58333 | L49: 46.065509 | M49: 312.36536 | N49: 496.60887 | O49: =IFERROR(_xlfn.XLOOKUP(A49,$T$1:$T$13,$S$1:$S$13,,0),0) -> 0 | P49: =IFERROR(_xlfn.XLOOKUP(A49,$T$1:$T$13,$U$1:$U$13,,0),0) -> 0 | Q49: =IF(P49>1,P49,G49) -> 5280 | R49: =IFERROR(_xlfn.XLOOKUP(A49,$T$1:$T$13,$V$1:$V$13,,0),0) -> 0
A50: 475 N Wall St, Salt Lake City, UT 84103 | B50: Avenues | C50: Salt Lake City | D50: https://www.zillow.com/homedetails/475-N-Wall-St-Salt-Lake-City-UT-84103/2056043816_zpid/ | E50: 2192000 | F50: 2552 | G50: 10560 | H50: 16 | I50: 548000 | J50: 1077.7333 | K50: 785.46667 | L50: 71.846007 | M50: 313.14286 | N50: 543.63375 | O50: =IFERROR(_xlfn.XLOOKUP(A50,$T$1:$T$13,$S$1:$S$13,,0),0) -> 0 | P50: =IFERROR(_xlfn.XLOOKUP(A50,$T$1:$T$13,$U$1:$U$13,,0),0) -> 0 | Q50: =IF(P50>1,P50,G50) -> 10560 | R50: =IFERROR(_xlfn.XLOOKUP(A50,$T$1:$T$13,$V$1:$V$13,,0),0) -> 0
A51: 714 S 600 E, Salt Lake City, UT 84102 | B51: Salt Lake City | C51: Salt Lake City | D51: https://www.zillow.com/homedetails/714-S-600-E-Salt-Lake-City-UT-84102/12756939_zpid/ | E51: 749000 | F51: 2192 | G51: 2640 | H51: 4 | I51: 187250 | J51: 368.25833 | K51: 268.39167 | L51: 104.06546 | M51: 316.16716 | N51: 326.89021 | O51: =IFERROR(_xlfn.XLOOKUP(A51,$T$1:$T$13,$S$1:$S$13,,0),0) -> 0 | P51: =IFERROR(_xlfn.XLOOKUP(A51,$T$1:$T$13,$U$1:$U$13,,0),0) -> 0 | Q51: =IF(P51>1,P51,G51) -> 2640 | R51: =IFERROR(_xlfn.XLOOKUP(A51,$T$1:$T$13,$V$1:$V$13,,0),0) -> 0
A52: 465 E 6th Ave, Salt Lake City, UT 84103 | B52: Avenues | C52: Salt Lake City | D52: https://www.zillow.com/homedetails/465-E-6th-Ave-Salt-Lake-City-UT-84103/12719546_zpid/ | E52: 1100000 | F52: 3341 | G52: 3960 | H52: 6 | I52: 275000 | J52: 540.83333 | K52: 394.16667 | L52: 11.063391 | M52: 316.54676 | N52: 317.39915 | O52: =IFERROR(_xlfn.XLOOKUP(A52,$T$1:$T$13,$S$1:$S$13,,0),0) -> 0 | P52: =IFERROR(_xlfn.XLOOKUP(A52,$T$1:$T$13,$U$1:$U$13,,0),0) -> 0 | Q52: =IF(P52>1,P52,G52) -> 3960 | R52: =IFERROR(_xlfn.XLOOKUP(A52,$T$1:$T$13,$V$1:$V$13,,0),0) -> 0
A53: 548 N Redwood Rd W, Salt Lake City, UT 84116 | B53: Salt Lake City | C53: Salt Lake City | D53: https://www.zillow.com/homedetails/548-N-Redwood-Rd-W-Salt-Lake-City-UT-84116/2069403483_zpid/ | E53: 799000 | F53: 1882 | G53: 5280 | H53: 8 | I53: 199750 | J53: 392.84167 | K53: 286.30833 | L53: 57.06456 | M53: 317.06349 | N53: 295.50334 | O53: =IFERROR(_xlfn.XLOOKUP(A53,$T$1:$T$13,$S$1:$S$13,,0),0) -> 0 | P53: =IFERROR(_xlfn.XLOOKUP(A53,$T$1:$T$13,$U$1:$U$13,,0),0) -> 0 | Q53: =IF(P53>1,P53,G53) -> 5280 | R53: =IFERROR(_xlfn.XLOOKUP(A53,$T$1:$T$13,$V$1:$V$13,,0),0) -> 0
A54: 1838 E Hillcrest Ave, Salt Lake City, UT 84106 | B54: Salt Lake City | C54: Salt Lake City | D54: https://www.zillow.com/homedetails/1838-E-Hillcrest-Ave-Salt-Lake-City-UT-84106/12777941_zpid/ | E54: 834900 | F54: 2393 | G54: 3300 | H54: 5 | I54: 208725 | J54: 410.4925 | K54: 299.1725 | L54: 38.537697 | M54: 317.69406 | N54: 313.5963 | O54: =IFERROR(_xlfn.XLOOKUP(A54,$T$1:$T$13,$S$1:$S$13,,0),0) -> 0 | P54: =IFERROR(_xlfn.XLOOKUP(A54,$T$1:$T$13,$U$1:$U$13,,0),0) -> 0 | Q54: =IF(P54>1,P54,G54) -> 3300 | R54: =IFERROR(_xlfn.XLOOKUP(A54,$T$1:$T$13,$V$1:$V$13,,0),0) -> 0
A55: 1175 S 300 E, Salt Lake City, UT 84111 | B55: Salt Lake City | C55: Salt Lake City | D55: https://www.zillow.com/homedetails/1175-S-300-E-Salt-Lake-City-UT-84111/305058154_zpid/ | E55: 925000 | F55: 3864 | G55: 2640 | H55: 4 | I55: 231250 | J55: 454.79167 | K55: 331.45833 | L55: 27.063345 | M55: 318.96552 | N55: 312.40295 | O55: =IFERROR(_xlfn.XLOOKUP(A55,$T$1:$T$13,$S$1:$S$13,,0),0) -> 0 | P55: =IFERROR(_xlfn.XLOOKUP(A55,$T$1:$T$13,$U$1:$U$13,,0),0) -> 0 | Q55: =IF(P55>1,P55,G55) -> 2640 | R55: =IFERROR(_xlfn.XLOOKUP(A55,$T$1:$T$13,$V$1:$V$13,,0),0) -> 0
A56: 288 E 10th Ave, Salt Lake City, UT 84103 | B56: Avenues | C56: Salt Lake City | D56: https://www.zillow.com/homedetails/288-E-10th-Ave-Salt-Lake-City-UT-84103/305056208_zpid/ | E56: 1225000 | F56: 3300 | G56: 3960 | H56: 6 | I56: 306250 | J56: 602.29167 | K56: 438.95833 | L56: 67.06566 | M56: 320.68063 | N56: 355.74495 | O56: =IFERROR(_xlfn.XLOOKUP(A56,$T$1:$T$13,$S$1:$S$13,,0),0) -> 0 | P56: =IFERROR(_xlfn.XLOOKUP(A56,$T$1:$T$13,$U$1:$U$13,,0),0) -> 4990 | Q56: =IF(P56>1,P56,G56) -> 4990 | R56: =IFERROR(_xlfn.XLOOKUP(A56,$T$1:$T$13,$V$1:$V$13,,0),0) -> CapRate: 3.0%; GRM: 238.1
A57: 4401 S 700 E, Millcreek, UT 84107 | B57: Millcreek | C57: Millcreek | D57: https://www.zillow.com/homedetails/4401-S-700-E-Millcreek-UT-84107/12854231_zpid/ | E57: 657000 | F57: 2560 | G57: 2640 | H57: 4 | I57: 164250 | J57: 323.025 | K57: 235.425 | L57: 96.759711 | M57: 320.80078 | N57: 265.19531 | O57: =IFERROR(_xlfn.XLOOKUP(A57,$T$1:$T$13,$S$1:$S$13,,0),0) -> 0 | P57: =IFERROR(_xlfn.XLOOKUP(A57,$T$1:$T$13,$U$1:$U$13,,0),0) -> 0 | Q57: =IF(P57>1,P57,G57) -> 2640 | R57: =IFERROR(_xlfn.XLOOKUP(A57,$T$1:$T$13,$V$1:$V$13,,0),0) -> 0
A58: 146 E 2nd Ave, Salt Lake City, UT 84103 | B58: Avenues | C58: Salt Lake City | D58: https://www.zillow.com/homedetails/146-E-2nd-Ave-Salt-Lake-City-UT-84103/448903538_zpid/ | E58: 4795000 | F58: (blank) | G58: 18480 | H58: 28 | I58: 1198750 | J58: 2357.5417 | K58: 1718.2083 | L58: 233.06462 | M58: 322.89562 | N58: 285.41667 | O58: =IFERROR(_xlfn.XLOOKUP(A58,$T$1:$T$13,$S$1:$S$13,,0),0) -> 0 | P58: =IFERROR(_xlfn.XLOOKUP(A58,$T$1:$T$13,$U$1:$U$13,,0),0) -> 0 | Q58: =IF(P58>1,P58,G58) -> 18480 | R58: =IFERROR(_xlfn.XLOOKUP(A58,$T$1:$T$13,$V$1:$V$13,,0),0) -> 0
A59: 1169 E 200 S, Salt Lake City, UT 84102 | B59: Salt Lake City | C59: Salt Lake City | D59: https://www.zillow.com/homedetails/1169-E-200-S-Salt-Lake-City-UT-84102/2129868447_zpid/ | E59: 1700000 | F59: 1939 | G59: 5280 | H59: 8 | I59: 425000 | J59: 835.83333 | K59: 609.16667 | L59: 11.063403 | M59: 326.17038 | N59: 615.45363 | O59: =IFERROR(_xlfn.XLOOKUP(A59,$T$1:$T$13,$S$1:$S$13,,0),0) -> 0 | P59: =IFERROR(_xlfn.XLOOKUP(A59,$T$1:$T$13,$U$1:$U$13,,0),0) -> 0 | Q59: =IF(P59>1,P59,G59) -> 5280 | R59: =IFERROR(_xlfn.XLOOKUP(A59,$T$1:$T$13,$V$1:$V$13,,0),0) -> 0
A60: 807 S 500 E, Salt Lake City, UT 84102 | B60: Salt Lake City | C60: Salt Lake City | D60: https://www.zillow.com/homedetails/807-S-500-E-Salt-Lake-City-UT-84102/305058123_zpid/ | E60: 1150000 | F60: 3002 | G60: 3960 | H60: 6 | I60: 287500 | J60: 565.41667 | K60: 412.08333 | L60: 166.06345 | M60: 326.24113 | N60: 351.2612 | O60: =IFERROR(_xlfn.XLOOKUP(A60,$T$1:$T$13,$S$1:$S$13,,0),0) -> 0 | P60: =IFERROR(_xlfn.XLOOKUP(A60,$T$1:$T$13,$U$1:$U$13,,0),0) -> 0 | Q60: =IF(P60>1,P60,G60) -> 3960 | R60: =IFERROR(_xlfn.XLOOKUP(A60,$T$1:$T$13,$V$1:$V$13,,0),0) -> 0
A61: 679 E 2nd Ave N, Salt Lake City, UT 84103 | B61: Avenues | C61: Salt Lake City | D61: https://www.zillow.com/homedetails/679-E-2nd-Ave-N-Salt-Lake-City-UT-84103/2072852614_zpid/ | E61: 1725000 | F61: 1789 | G61: 7260 | H61: 11 | I61: 431250 | J61: 848.125 | K61: 618.125 | L61: 43.065324 | M61: 326.27199 | N61: 612.79473 | O61: =IFERROR(_xlfn.XLOOKUP(A61,$T$1:$T$13,$S$1:$S$13,,0),0) -> 0 | P61: =IFERROR(_xlfn.XLOOKUP(A61,$T$1:$T$13,$U$1:$U$13,,0),0) -> 0 | Q61: =IF(P61>1,P61,G61) -> 7260 | R61: =IFERROR(_xlfn.XLOOKUP(A61,$T$1:$T$13,$V$1:$V$13,,0),0) -> 0
A62: 3366 S 700 E, South Salt Lake, UT 84106 | B62: Millcreek | C62: South Salt Lake | D62: https://www.zillow.com/homedetails/3366-S-700-E-South-Salt-Lake-UT-84106/12786814_zpid/ | E62: 720000 | F62: 2013 | G62: 2640 | H62: 4 | I62: 180000 | J62: 354 | K62: 258 | L62: 13.064005 | M62: 327.27273 | N62: 328.83756 | O62: =IFERROR(_xlfn.XLOOKUP(A62,$T$1:$T$13,$S$1:$S$13,,0),0) -> 0 | P62: =IFERROR(_xlfn.XLOOKUP(A62,$T$1:$T$13,$U$1:$U$13,,0),0) -> 0 | Q62: =IF(P62>1,P62,G62) -> 2640 | R62: =IFERROR(_xlfn.XLOOKUP(A62,$T$1:$T$13,$V$1:$V$13,,0),0) -> 0
A63: 182 N N St, Salt Lake City, UT 84103 | B63: Avenues | C63: Salt Lake City | D63: https://www.zillow.com/homedetails/182-N-N-St-Salt-Lake-City-UT-84103/2054779738_zpid/ | E63: 850000 | F63: 2380 | G63: 3300 | H63: 5 | I63: 212500 | J63: 417.91667 | K63: 304.58333 | L63: 18.063403 | M63: 333.20267 | N63: 320.2381 | O63: =IFERROR(_xlfn.XLOOKUP(A63,$T$1:$T$13,$S$1:$S$13,,0),0) -> 0 | P63: =IFERROR(_xlfn.XLOOKUP(A63,$T$1:$T$13,$U$1:$U$13,,0),0) -> 0 | Q63: =IF(P63>1,P63,G63) -> 3300 | R63: =IFERROR(_xlfn.XLOOKUP(A63,$T$1:$T$13,$V$1:$V$13,,0),0) -> 0
A64: 1843 S 900 E, Salt Lake City, UT 84105 | B64: Salt Lake City | C64: Salt Lake City | D64: https://www.zillow.com/homedetails/1843-S-900-E-Salt-Lake-City-UT-84105/305058432_zpid/ | E64: 1200000 | F64: 1924 | G64: 3300 | H64: 5 | I64: 300000 | J64: 590 | K64: 430 | L64: 95.06559 | M64: 333.24077 | N64: 511.85031 | O64: =IFERROR(_xlfn.XLOOKUP(A64,$T$1:$T$13,$S$1:$S$13,,0),0) -> 0 | P64: =IFERROR(_xlfn.XLOOKUP(A64,$T$1:$T$13,$U$1:$U$13,,0),0) -> 0 | Q64: =IF(P64>1,P64,G64) -> 3300 | R64: =IFERROR(_xlfn.XLOOKUP(A64,$T$1:$T$13,$V$1:$V$13,,0),0) -> 0
A65: 311 E 3360 S, Salt Lake City, UT 84115 | B65: Salt Lake City | C65: Salt Lake City | D65: https://www.zillow.com/homedetails/311-E-3360-S-Salt-Lake-City-UT-84115/141900683_zpid/ | E65: 1200000 | F65: 2042 | G65: 5280 | H65: 8 | I65: 300000 | J65: 590 | K65: 430 | L65: 95.065833 | M65: 333.33333 | N65: 418.82958 | O65: =IFERROR(_xlfn.XLOOKUP(A65,$T$1:$T$13,$S$1:$S$13,,0),0) -> 0 | P65: =IFERROR(_xlfn.XLOOKUP(A65,$T$1:$T$13,$U$1:$U$13,,0),0) -> 6000 | Q65: =IF(P65>1,P65,G65) -> 6000 | R65: =IFERROR(_xlfn.XLOOKUP(A65,$T$1:$T$13,$V$1:$V$13,,0),0) -> CapRate: 4.1%; GRM: 188.6
A66: 1099 S 900 E, Salt Lake City, UT 84105 | B66: Salt Lake City | C66: Salt Lake City | D66: https://www.zillow.com/homedetails/1099-S-900-E-Salt-Lake-City-UT-84105/2070086984_zpid/ | E66: 1250000 | F66: 3179 | G66: 3960 | H66: 6 | I66: 312500 | J66: 614.58333 | K66: 447.91667 | L66: 145.91895 | M66: 337.83784 | N66: 370.21382 | O66: =IFERROR(_xlfn.XLOOKUP(A66,$T$1:$T$13,$S$1:$S$13,,0),0) -> 0 | P66: =IFERROR(_xlfn.XLOOKUP(A66,$T$1:$T$13,$U$1:$U$13,,0),0) -> 0 | Q66: =IF(P66>1,P66,G66) -> 3960 | R66: =IFERROR(_xlfn.XLOOKUP(A66,$T$1:$T$13,$V$1:$V$13,,0),0) -> 0
A67: 1470 S Edison St, Salt Lake City, UT 84115 | B67: Salt Lake City | C67: Salt Lake City | D67: https://www.zillow.com/homedetails/1470-S-Edison-St-Salt-Lake-City-UT-84115/305058480_zpid/ | E67: 930000 | F67: 2264 | G67: 3960 | H67: 6 | I67: 232500 | J67: 457.25 | K67: 333.25 | L67: 199.06425 | M67: 341.15921 | N67: 334.55536 | O67: =IFERROR(_xlfn.XLOOKUP(A67,$T$1:$T$13,$S$1:$S$13,,0),0) -> 0 | P67: =IFERROR(_xlfn.XLOOKUP(A67,$T$1:$T$13,$U$1:$U$13,,0),0) -> 0 | Q67: =IF(P67>1,P67,G67) -> 3960 | R67: =IFERROR(_xlfn.XLOOKUP(A67,$T$1:$T$13,$V$1:$V$13,,0),0) -> 0
A68: 778 N 300 W, Salt Lake City, UT 84103 | B68: Salt Lake City | C68: Salt Lake City | D68: https://www.zillow.com/homedetails/778-N-300-W-Salt-Lake-City-UT-84103/2070079252_zpid/ | E68: 5750000 | F68: 2189 | G68: 17160 | H68: 26 | I68: 1437500 | J68: 2827.0833 | K68: 2060.4167 | L68: 33.06522 | M68: 342.2619 | N68: 1497.68 | O68: =IFERROR(_xlfn.XLOOKUP(A68,$T$1:$T$13,$S$1:$S$13,,0),0) -> 0 | P68: =IFERROR(_xlfn.XLOOKUP(A68,$T$1:$T$13,$U$1:$U$13,,0),0) -> 0 | Q68: =IF(P68>1,P68,G68) -> 17160 | R68: =IFERROR(_xlfn.XLOOKUP(A68,$T$1:$T$13,$V$1:$V$13,,0),0) -> 0
A69: 564 E 800 S, Salt Lake City, UT 84102 | B69: Salt Lake City | C69: Salt Lake City | D69: https://www.zillow.com/homedetails/564-E-800-S-Salt-Lake-City-UT-84102/12757225_zpid/ | E69: 659000 | F69: 1694 | G69: 2640 | H69: 4 | I69: 164750 | J69: 324.00833 | K69: 236.14167 | L69: 21.032535 | M69: 343.22917 | N69: 331.8017 | O69: =IFERROR(_xlfn.XLOOKUP(A69,$T$1:$T$13,$S$1:$S$13,,0),0) -> 0 | P69: =IFERROR(_xlfn.XLOOKUP(A69,$T$1:$T$13,$U$1:$U$13,,0),0) -> 0 | Q69: =IF(P69>1,P69,G69) -> 2640 | R69: =IFERROR(_xlfn.XLOOKUP(A69,$T$1:$T$13,$V$1:$V$13,,0),0) -> 0
A70: 828 E Logan Ave S, Salt Lake City, UT 84105 | B70: Salt Lake City | C70: Salt Lake City | D70: https://www.zillow.com/homedetails/828-E-Logan-Ave-S-Salt-Lake-City-UT-84105/448294568_zpid/ | E70: 1550000 | F70: (blank) | G70: 5940 | H70: 9 | I70: 387500 | J70: 762.08333 | K70: 555.41667 | L70: 33.063542 | M70: 352.27273 | N70: 287.03704 | O70: =IFERROR(_xlfn.XLOOKUP(A70,$T$1:$T$13,$S$1:$S$13,,0),0) -> 0 | P70: =IFERROR(_xlfn.XLOOKUP(A70,$T$1:$T$13,$U$1:$U$13,,0),0) -> 0 | Q70: =IF(P70>1,P70,G70) -> 5940 | R70: =IFERROR(_xlfn.XLOOKUP(A70,$T$1:$T$13,$V$1:$V$13,,0),0) -> 0
A71: 221 L St, Salt Lake City, UT 84103 | B71: Avenues | C71: Salt Lake City | D71: https://www.zillow.com/homedetails/221-L-St-Salt-Lake-City-UT-84103/457554835_zpid/ | E71: 715000 | F71: (blank) | G71: 1980 | H71: 3 | I71: 178750 | J71: 351.54167 | K71: 256.20833 | L71: 28.064444 | M71: 357.5 | N71: 397.22222 | O71: =IFERROR(_xlfn.XLOOKUP(A71,$T$1:$T$13,$S$1:$S$13,,0),0) -> 0 | P71: =IFERROR(_xlfn.XLOOKUP(A71,$T$1:$T$13,$U$1:$U$13,,0),0) -> 0 | Q71: =IF(P71>1,P71,G71) -> 1980 | R71: =IFERROR(_xlfn.XLOOKUP(A71,$T$1:$T$13,$V$1:$V$13,,0),0) -> 0
A72: 359 E 900 S, Salt Lake City, UT 84111 | B72: Salt Lake City | C72: Salt Lake City | D72: https://www.zillow.com/homedetails/359-E-900-S-Salt-Lake-City-UT-84111/305058103_zpid/ | E72: 824900 | F72: 2195 | G72: 2640 | H72: 4 | I72: 206225 | J72: 405.57583 | K72: 295.58917 | L72: 59.064248 | M72: 357.71899 | N72: 359.75849 | O72: =IFERROR(_xlfn.XLOOKUP(A72,$T$1:$T$13,$S$1:$S$13,,0),0) -> 0 | P72: =IFERROR(_xlfn.XLOOKUP(A72,$T$1:$T$13,$U$1:$U$13,,0),0) -> 0 | Q72: =IF(P72>1,P72,G72) -> 2640 | R72: =IFERROR(_xlfn.XLOOKUP(A72,$T$1:$T$13,$V$1:$V$13,,0),0) -> 0
A73: 1127 E South Temple S, Salt Lake City, UT 84102 | B73: Avenues | C73: Salt Lake City | D73: https://www.zillow.com/homedetails/1127-E-South-Temple-S-Salt-Lake-City-UT-84102/449590119_zpid/ | E73: 2750000 | F73: (blank) | G73: 6600 | H73: 10 | I73: 687500 | J73: 1352.0833 | K73: 985.41667 | L73: 222.06343 | M73: 361.50914 | N73: 458.33333 | O73: =IFERROR(_xlfn.XLOOKUP(A73,$T$1:$T$13,$S$1:$S$13,,0),0) -> 0 | P73: =IFERROR(_xlfn.XLOOKUP(A73,$T$1:$T$13,$U$1:$U$13,,0),0) -> 0 | Q73: =IF(P73>1,P73,G73) -> 6600 | R73: =IFERROR(_xlfn.XLOOKUP(A73,$T$1:$T$13,$V$1:$V$13,,0),0) -> 0
A74: 1902 S Main St, Salt Lake City, UT 84115 | B74: Salt Lake City | C74: Salt Lake City | D74: https://www.zillow.com/homedetails/1902-S-Main-St-Salt-Lake-City-UT-84115/455517659_zpid/ | E74: 999995 | F74: (blank) | G74: 2640 | H74: 4 | I74: 249998.75 | J74: 491.66421 | K74: 358.33154 | L74: 109.95903 | M74: 363.8992 | N74: 416.66458 | O74: =IFERROR(_xlfn.XLOOKUP(A74,$T$1:$T$13,$S$1:$S$13,,0),0) -> 0 | P74: =IFERROR(_xlfn.XLOOKUP(A74,$T$1:$T$13,$U$1:$U$13,,0),0) -> 0 | Q74: =IF(P74>1,P74,G74) -> 2640 | R74: =IFERROR(_xlfn.XLOOKUP(A74,$T$1:$T$13,$V$1:$V$13,,0),0) -> 0
A75: 1330 S 1100 E, Salt Lake City, UT 84105 | B75: Salt Lake City | C75: Salt Lake City | D75: https://www.zillow.com/homedetails/1330-S-1100-E-Salt-Lake-City-UT-84105/2067895645_zpid/ | E75: 799000 | F75: 2118 | G75: 1980 | H75: 3 | I75: 199750 | J75: 392.84167 | K75: 286.30833 | L75: 288.06586 | M75: 370.93779 | N75: 410.56579 | O75: =IFERROR(_xlfn.XLOOKUP(A75,$T$1:$T$13,$S$1:$S$13,,0),0) -> 0 | P75: =IFERROR(_xlfn.XLOOKUP(A75,$T$1:$T$13,$U$1:$U$13,,0),0) -> 0 | Q75: =IF(P75>1,P75,G75) -> 1980 | R75: =IFERROR(_xlfn.XLOOKUP(A75,$T$1:$T$13,$V$1:$V$13,,0),0) -> 0
A76: 2692 S Preston St, Salt Lake City, UT 84106 | B76: Salt Lake City | C76: Salt Lake City | D76: https://www.zillow.com/homedetails/2692-S-Preston-St-Salt-Lake-City-UT-84106/12778275_zpid/ | E76: 1250000 | F76: 2490 | G76: 5280 | H76: 8 | I76: 312500 | J76: 614.58333 | K76: 447.91667 | L76: 116.06546 | M76: 372.02381 | N76: 381.21235 | O76: =IFERROR(_xlfn.XLOOKUP(A76,$T$1:$T$13,$S$1:$S$13,,0),0) -> 0 | P76: =IFERROR(_xlfn.XLOOKUP(A76,$T$1:$T$13,$U$1:$U$13,,0),0) -> 0 | Q76: =IF(P76>1,P76,G76) -> 5280 | R76: =IFERROR(_xlfn.XLOOKUP(A76,$T$1:$T$13,$V$1:$V$13,,0),0) -> 0
A77: 3139 S 300 E, Salt Lake City, UT 84115 | B77: Salt Lake City | C77: Salt Lake City | D77: https://www.zillow.com/homedetails/3139-S-300-E-Salt-Lake-City-UT-84115/141900655_zpid/ | E77: 1550000 | F77: 1470 | G77: 5280 | H77: 8 | I77: 387500 | J77: 762.08333 | K77: 555.41667 | L77: 97.065833 | M77: 372.59615 | N77: 688.66922 | O77: =IFERROR(_xlfn.XLOOKUP(A77,$T$1:$T$13,$S$1:$S$13,,0),0) -> 0 | P77: =IFERROR(_xlfn.XLOOKUP(A77,$T$1:$T$13,$U$1:$U$13,,0),0) -> 0 | Q77: =IF(P77>1,P77,G77) -> 5280 | R77: =IFERROR(_xlfn.XLOOKUP(A77,$T$1:$T$13,$V$1:$V$13,,0),0) -> 0
A78: 1260 E Emerson Ave, Salt Lake City, UT 84105 | B78: Salt Lake City | C78: Salt Lake City | D78: https://www.zillow.com/homedetails/1260-E-Emerson-Ave-Salt-Lake-City-UT-84105/305058405_zpid/ | E78: 999900 | F78: 2098 | G78: 2640 | H78: 4 | I78: 249975 | J78: 491.6175 | K78: 358.2975 | L78: 49.063981 | M78: 373.23628 | N78: 446.61088 | O78: =IFERROR(_xlfn.XLOOKUP(A78,$T$1:$T$13,$S$1:$S$13,,0),0) -> 0 | P78: =IFERROR(_xlfn.XLOOKUP(A78,$T$1:$T$13,$U$1:$U$13,,0),0) -> 0 | Q78: =IF(P78>1,P78,G78) -> 2640 | R78: =IFERROR(_xlfn.XLOOKUP(A78,$T$1:$T$13,$V$1:$V$13,,0),0) -> 0
A79: 1436 S Roberta St E, Salt Lake City, UT 84115 | B79: Salt Lake City | C79: Salt Lake City | D79: https://www.zillow.com/homedetails/1436-S-Roberta-St-E-Salt-Lake-City-UT-84115/2072633717_zpid/ | E79: 899000 | F79: 2287 | G79: 2640 | H79: 4 | I79: 224750 | J79: 442.00833 | K79: 322.14167 | L79: 93.065602 | M79: 374.11569 | N79: 383.83736 | O79: =IFERROR(_xlfn.XLOOKUP(A79,$T$1:$T$13,$S$1:$S$13,,0),0) -> 0 | P79: =IFERROR(_xlfn.XLOOKUP(A79,$T$1:$T$13,$U$1:$U$13,,0),0) -> 0 | Q79: =IF(P79>1,P79,G79) -> 2640 | R79: =IFERROR(_xlfn.XLOOKUP(A79,$T$1:$T$13,$V$1:$V$13,,0),0) -> 0
A80: 350 E Mansfield Ave, Salt Lake City, UT 84115 | B80: Salt Lake City | C80: Salt Lake City | D80: https://www.zillow.com/homedetails/350-E-Mansfield-Ave-Salt-Lake-City-UT-84115/141900771_zpid/ | E80: 1125000 | F80: 1616 | G80: 5280 | H80: 8 | I80: 281250 | J80: 553.125 | K80: 403.125 | L80: 156.06512 | M80: 376.00267 | N80: 465.26918 | O80: =IFERROR(_xlfn.XLOOKUP(A80,$T$1:$T$13,$S$1:$S$13,,0),0) -> 0 | P80: =IFERROR(_xlfn.XLOOKUP(A80,$T$1:$T$13,$U$1:$U$13,,0),0) -> 0 | Q80: =IF(P80>1,P80,G80) -> 5280 | R80: =IFERROR(_xlfn.XLOOKUP(A80,$T$1:$T$13,$V$1:$V$13,,0),0) -> 0
A81: 1150 E 500 S, Salt Lake City, UT 84102 | B81: Salt Lake City | C81: Salt Lake City | D81: https://www.zillow.com/homedetails/1150-E-500-S-Salt-Lake-City-UT-84102/2072954111_zpid/ | E81: 1100000 | F81: 1961 | G81: 3300 | H81: 5 | I81: 275000 | J81: 540.83333 | K81: 394.16667 | L81: 20.063437 | M81: 376.58336 | N81: 463.80248 | O81: =IFERROR(_xlfn.XLOOKUP(A81,$T$1:$T$13,$S$1:$S$13,,0),0) -> 0 | P81: =IFERROR(_xlfn.XLOOKUP(A81,$T$1:$T$13,$U$1:$U$13,,0),0) -> 0 | Q81: =IF(P81>1,P81,G81) -> 3300 | R81: =IFERROR(_xlfn.XLOOKUP(A81,$T$1:$T$13,$V$1:$V$13,,0),0) -> 0
A82: 376 E Broadway St, Salt Lake City, UT 84111 | B82: Salt Lake City | C82: Salt Lake City | D82: https://www.zillow.com/homedetails/376-E-Broadway-St-Salt-Lake-City-UT-84111/452275124_zpid/ | E82: 1530000 | F82: (blank) | G82: 5940 | H82: 9 | I82: 382500 | J82: 752.25 | K82: 548.25 | L82: 178.06573 | M82: 387.24374 | N82: 283.33333 | O82: =IFERROR(_xlfn.XLOOKUP(A82,$T$1:$T$13,$S$1:$S$13,,0),0) -> 0 | P82: =IFERROR(_xlfn.XLOOKUP(A82,$T$1:$T$13,$U$1:$U$13,,0),0) -> 0 | Q82: =IF(P82>1,P82,G82) -> 5940 | R82: =IFERROR(_xlfn.XLOOKUP(A82,$T$1:$T$13,$V$1:$V$13,,0),0) -> 0
A83: 906 E 3rd Ave, Salt Lake City, UT 84103 | B83: Avenues | C83: Salt Lake City | D83: https://www.zillow.com/homedetails/906-E-3rd-Ave-Salt-Lake-City-UT-84103/305056345_zpid/ | E83: 1175000 | F83: 1302 | G83: 3960 | H83: 6 | I83: 293750 | J83: 577.70833 | K83: 421.04167 | L83: 125.06405 | M83: 389.45973 | N83: 614.42332 | O83: =IFERROR(_xlfn.XLOOKUP(A83,$T$1:$T$13,$S$1:$S$13,,0),0) -> 0 | P83: =IFERROR(_xlfn.XLOOKUP(A83,$T$1:$T$13,$U$1:$U$13,,0),0) -> 0 | Q83: =IF(P83>1,P83,G83) -> 3960 | R83: =IFERROR(_xlfn.XLOOKUP(A83,$T$1:$T$13,$V$1:$V$13,,0),0) -> 0
A84: 3428 S 300 E, Salt Lake City, UT 84115 | B84: Salt Lake City | C84: Salt Lake City | D84: https://www.zillow.com/homedetails/3428-S-300-E-Salt-Lake-City-UT-84115/141900680_zpid/ | E84: 815000 | F84: 2260 | G84: 2640 | H84: 4 | I84: 203750 | J84: 400.70833 | K84: 292.04167 | L84: 166.06319 | M84: 393.33977 | N84: 350.1014 | O84: =IFERROR(_xlfn.XLOOKUP(A84,$T$1:$T$13,$S$1:$S$13,,0),0) -> 0 | P84: =IFERROR(_xlfn.XLOOKUP(A84,$T$1:$T$13,$U$1:$U$13,,0),0) -> 0 | Q84: =IF(P84>1,P84,G84) -> 2640 | R84: =IFERROR(_xlfn.XLOOKUP(A84,$T$1:$T$13,$V$1:$V$13,,0),0) -> 0
A85: 1769 S Foothill Dr, Salt Lake City, UT 84108 | B85: Salt Lake City | C85: Salt Lake City | D85: https://www.zillow.com/homedetails/1769-S-Foothill-Dr-Salt-Lake-City-UT-84108/12765918_zpid/ | E85: 885000 | F85: 3054 | G85: 3300 | H85: 5 | I85: 221250 | J85: 435.125 | K85: 317.125 | L85: 159.06608 | M85: 395.97315 | N85: 292.39194 | O85: =IFERROR(_xlfn.XLOOKUP(A85,$T$1:$T$13,$S$1:$S$13,,0),0) -> 0 | P85: =IFERROR(_xlfn.XLOOKUP(A85,$T$1:$T$13,$U$1:$U$13,,0),0) -> 0 | Q85: =IF(P85>1,P85,G85) -> 3300 | R85: =IFERROR(_xlfn.XLOOKUP(A85,$T$1:$T$13,$V$1:$V$13,,0),0) -> 0
A86: 1237 S Lake St E, Salt Lake City, UT 84105 | B86: Salt Lake City | C86: Salt Lake City | D86: https://www.zillow.com/homedetails/1237-S-Lake-St-E-Salt-Lake-City-UT-84105/2072768030_zpid/ | E86: 1300000 | F86: 3125 | G86: 3960 | H86: 6 | I86: 325000 | J86: 639.16667 | K86: 465.83333 | L86: 53.065359 | M86: 400.24631 | N86: 388.55556 | O86: =IFERROR(_xlfn.XLOOKUP(A86,$T$1:$T$13,$S$1:$S$13,,0),0) -> 0 | P86: =IFERROR(_xlfn.XLOOKUP(A86,$T$1:$T$13,$U$1:$U$13,,0),0) -> 0 | Q86: =IF(P86>1,P86,G86) -> 3960 | R86: =IFERROR(_xlfn.XLOOKUP(A86,$T$1:$T$13,$V$1:$V$13,,0),0) -> 0
A87: 1326 S Green St E, Salt Lake City, UT 84105 | B87: Salt Lake City | C87: Salt Lake City | D87: https://www.zillow.com/homedetails/1326-S-Green-St-E-Salt-Lake-City-UT-84105/2071958599_zpid/ | E87: 1100000 | F87: 2159 | G87: 3960 | H87: 6 | I87: 275000 | J87: 540.83333 | K87: 394.16667 | L87: 73.063252 | M87: 402.9304 | N87: 407.52535 | O87: =IFERROR(_xlfn.XLOOKUP(A87,$T$1:$T$13,$S$1:$S$13,,0),0) -> 0 | P87: =IFERROR(_xlfn.XLOOKUP(A87,$T$1:$T$13,$U$1:$U$13,,0),0) -> 0 | Q87: =IF(P87>1,P87,G87) -> 3960 | R87: =IFERROR(_xlfn.XLOOKUP(A87,$T$1:$T$13,$V$1:$V$13,,0),0) -> 0
A88: 1860 S 1600 E, Salt Lake City, UT 84105 | B88: Salt Lake City | C88: Salt Lake City | D88: https://www.zillow.com/homedetails/1860-S-1600-E-Salt-Lake-City-UT-84105/12767993_zpid/ | E88: 799900 | F88: 2151 | G88: 2640 | H88: 4 | I88: 199975 | J88: 393.28417 | K88: 286.63083 | L88: 108.06494 | M88: 405.01266 | N88: 352.58261 | O88: =IFERROR(_xlfn.XLOOKUP(A88,$T$1:$T$13,$S$1:$S$13,,0),0) -> 0 | P88: =IFERROR(_xlfn.XLOOKUP(A88,$T$1:$T$13,$U$1:$U$13,,0),0) -> 0 | Q88: =IF(P88>1,P88,G88) -> 2640 | R88: =IFERROR(_xlfn.XLOOKUP(A88,$T$1:$T$13,$V$1:$V$13,,0),0) -> 0
A89: 692 N Cortez St, Salt Lake City, UT 84103 | B89: Avenues | C89: Salt Lake City | D89: https://www.zillow.com/homedetails/692-N-Cortez-St-Salt-Lake-City-UT-84103/12717625_zpid/ | E89: 899000 | F89: 2163 | G89: 2640 | H89: 4 | I89: 224750 | J89: 442.00833 | K89: 322.14167 | L89: 44.906088 | M89: 405.32011 | N89: 395.10489 | O89: =IFERROR(_xlfn.XLOOKUP(A89,$T$1:$T$13,$S$1:$S$13,,0),0) -> 0 | P89: =IFERROR(_xlfn.XLOOKUP(A89,$T$1:$T$13,$U$1:$U$13,,0),0) -> 0 | Q89: =IF(P89>1,P89,G89) -> 2640 | R89: =IFERROR(_xlfn.XLOOKUP(A89,$T$1:$T$13,$V$1:$V$13,,0),0) -> 0
A90: 1252 E Driggs Ave, Salt Lake City, UT 84106 | B90: Salt Lake City | C90: Salt Lake City | D90: https://www.zillow.com/homedetails/1252-E-Driggs-Ave-Salt-Lake-City-UT-84106/12775486_zpid/ | E90: 659900 | F90: 2439 | G90: 1980 | H90: 3 | I90: 164975 | J90: 324.45083 | K90: 236.46417 | L90: 18.028241 | M90: 409.87578 | N90: 318.58641 | O90: =IFERROR(_xlfn.XLOOKUP(A90,$T$1:$T$13,$S$1:$S$13,,0),0) -> 0 | P90: =IFERROR(_xlfn.XLOOKUP(A90,$T$1:$T$13,$U$1:$U$13,,0),0) -> 0 | Q90: =IF(P90>1,P90,G90) -> 1980 | R90: =IFERROR(_xlfn.XLOOKUP(A90,$T$1:$T$13,$V$1:$V$13,,0),0) -> 0
A91: 1752 E Water Pine Ct #107, Holladay, UT 84117 | B91: Millcreek | C91: Holladay | D91: https://www.zillow.com/homedetails/1752-E-Water-Pine-Ct-107-Holladay-UT-84117/457664204_zpid/ | E91: 774900 | F91: (blank) | G91: 1980 | H91: 3 | I91: 193725 | J91: 380.9925 | K91: 277.6725 | L91: 24.064201 | M91: 414.38503 | N91: 430.5 | O91: =IFERROR(_xlfn.XLOOKUP(A91,$T$1:$T$13,$S$1:$S$13,,0),0) -> 0 | P91: =IFERROR(_xlfn.XLOOKUP(A91,$T$1:$T$13,$U$1:$U$13,,0),0) -> 0 | Q91: =IF(P91>1,P91,G91) -> 1980 | R91: =IFERROR(_xlfn.XLOOKUP(A91,$T$1:$T$13,$V$1:$V$13,,0),0) -> 0
A92: 1756 E Water Pine Ct #106, Holladay, UT 84117 | B92: Millcreek | C92: Holladay | D92: https://www.zillow.com/homedetails/1756-E-Water-Pine-Ct-106-Holladay-UT-84117/457658909_zpid/ | E92: 774900 | F92: (blank) | G92: 1980 | H92: 3 | I92: 193725 | J92: 380.9925 | K92: 277.6725 | L92: 24.064201 | M92: 414.38503 | N92: 430.5 | O92: =IFERROR(_xlfn.XLOOKUP(A92,$T$1:$T$13,$S$1:$S$13,,0),0) -> 0 | P92: =IFERROR(_xlfn.XLOOKUP(A92,$T$1:$T$13,$U$1:$U$13,,0),0) -> 0 | Q92: =IF(P92>1,P92,G92) -> 1980 | R92: =IFERROR(_xlfn.XLOOKUP(A92,$T$1:$T$13,$V$1:$V$13,,0),0) -> 0
A93: 850 S Lake St, Salt Lake City, UT 84105 | B93: Salt Lake City | C93: Salt Lake City | D93: https://www.zillow.com/homedetails/850-S-Lake-St-Salt-Lake-City-UT-84105/305058187_zpid/ | E93: 1200000 | F93: 1678 | G93: 3960 | H93: 6 | I93: 300000 | J93: 590 | K93: 430 | L93: 27.063449 | M93: 420.16807 | N93: 524.2352 | O93: =IFERROR(_xlfn.XLOOKUP(A93,$T$1:$T$13,$S$1:$S$13,,0),0) -> 0 | P93: =IFERROR(_xlfn.XLOOKUP(A93,$T$1:$T$13,$U$1:$U$13,,0),0) -> 0 | Q93: =IF(P93>1,P93,G93) -> 3960 | R93: =IFERROR(_xlfn.XLOOKUP(A93,$T$1:$T$13,$V$1:$V$13,,0),0) -> 0
A94: 1712 S 900 E #2D74EC46B, Salt Lake City, UT 84105 | B94: Salt Lake City | C94: Salt Lake City | D94: https://www.zillow.com/homedetails/1712-S-900-E-2D74EC46B-Salt-Lake-City-UT-84105/450199489_zpid/ | E94: 10580000 | F94: (blank) | G94: 26400 | H94: 40 | I94: 2645000 | J94: 5201.8333 | K94: 3791.1667 | L94: 145.06572 | M94: 423.2 | N94: 440.83333 | O94: =IFERROR(_xlfn.XLOOKUP(A94,$T$1:$T$13,$S$1:$S$13,,0),0) -> 0 | P94: =IFERROR(_xlfn.XLOOKUP(A94,$T$1:$T$13,$U$1:$U$13,,0),0) -> 0 | Q94: =IF(P94>1,P94,G94) -> 26400 | R94: =IFERROR(_xlfn.XLOOKUP(A94,$T$1:$T$13,$V$1:$V$13,,0),0) -> 0
A95: 936 E 1700 S, Salt Lake City, UT 84105 | B95: Salt Lake City | C95: Salt Lake City | D95: https://www.zillow.com/homedetails/936-E-1700-S-Salt-Lake-City-UT-84105/296672784_zpid/ | E95: 1375000 | F95: 2152 | G95: 4620 | H95: 7 | I95: 343750 | J95: 676.04167 | K95: 492.70833 | L95: 374.06459 | M95: 442.12219 | N95: 483.16074 | O95: =IFERROR(_xlfn.XLOOKUP(A95,$T$1:$T$13,$S$1:$S$13,,0),0) -> 0 | P95: =IFERROR(_xlfn.XLOOKUP(A95,$T$1:$T$13,$U$1:$U$13,,0),0) -> 0 | Q95: =IF(P95>1,P95,G95) -> 4620 | R95: =IFERROR(_xlfn.XLOOKUP(A95,$T$1:$T$13,$V$1:$V$13,,0),0) -> 0
A96: 2689 S 500 E, Salt Lake City, UT 84106 | B96: Salt Lake City | C96: Salt Lake City | D96: https://www.zillow.com/homedetails/2689-S-500-E-Salt-Lake-City-UT-84106/456968277_zpid/ | E96: 6750000 | F96: (blank) | G96: 17820 | H96: 27 | I96: 1687500 | J96: 3318.75 | K96: 2418.75 | L96: 52.06544 | M96: 448.14766 | N96: 416.66667 | O96: =IFERROR(_xlfn.XLOOKUP(A96,$T$1:$T$13,$S$1:$S$13,,0),0) -> 0 | P96: =IFERROR(_xlfn.XLOOKUP(A96,$T$1:$T$13,$U$1:$U$13,,0),0) -> 0 | Q96: =IF(P96>1,P96,G96) -> 17820 | R96: =IFERROR(_xlfn.XLOOKUP(A96,$T$1:$T$13,$V$1:$V$13,,0),0) -> 0
A97: 458 E Lambourne Ave, Salt Lake City, UT 84115 | B97: Salt Lake City | C97: Salt Lake City | D97: https://www.zillow.com/homedetails/458-E-Lambourne-Ave-Salt-Lake-City-UT-84115/12788213_zpid/ | E97: 725000 | F97: 2067 | G97: 2640 | H97: 4 | I97: 181250 | J97: 356.45833 | K97: 259.79167 | L97: 281.06583 | M97: 450.87065 | N97: 326.41661 | O97: =IFERROR(_xlfn.XLOOKUP(A97,$T$1:$T$13,$S$1:$S$13,,0),0) -> 0 | P97: =IFERROR(_xlfn.XLOOKUP(A97,$T$1:$T$13,$U$1:$U$13,,0),0) -> 0 | Q97: =IF(P97>1,P97,G97) -> 2640 | R97: =IFERROR(_xlfn.XLOOKUP(A97,$T$1:$T$13,$V$1:$V$13,,0),0) -> 0
A98: 538 S 800 E, Salt Lake City, UT 84102 | B98: Salt Lake City | C98: Salt Lake City | D98: https://www.zillow.com/homedetails/538-S-800-E-Salt-Lake-City-UT-84102/12754309_zpid/ | E98: 950000 | F98: 2263 | G98: 2640 | H98: 4 | I98: 237500 | J98: 467.08333 | K98: 340.41667 | L98: 11.063414 | M98: 473.81546 | N98: 407.81503 | O98: =IFERROR(_xlfn.XLOOKUP(A98,$T$1:$T$13,$S$1:$S$13,,0),0) -> 0 | P98: =IFERROR(_xlfn.XLOOKUP(A98,$T$1:$T$13,$U$1:$U$13,,0),0) -> 0 | Q98: =IF(P98>1,P98,G98) -> 2640 | R98: =IFERROR(_xlfn.XLOOKUP(A98,$T$1:$T$13,$V$1:$V$13,,0),0) -> 0
A99: 2795 S Imperial St, Salt Lake City, UT 84106 | B99: Salt Lake City | C99: Salt Lake City | D99: https://www.zillow.com/homedetails/2795-S-Imperial-St-Salt-Lake-City-UT-84106/12784155_zpid/ | E99: 779900 | F99: 1877 | G99: 2640 | H99: 4 | I99: 194975 | J99: 383.45083 | K99: 279.46417 | L99: 37.065347 | M99: 474.10334 | N99: 370.2309 | O99: =IFERROR(_xlfn.XLOOKUP(A99,$T$1:$T$13,$S$1:$S$13,,0),0) -> 0 | P99: =IFERROR(_xlfn.XLOOKUP(A99,$T$1:$T$13,$U$1:$U$13,,0),0) -> 0 | Q99: =IF(P99>1,P99,G99) -> 2640 | R99: =IFERROR(_xlfn.XLOOKUP(A99,$T$1:$T$13,$V$1:$V$13,,0),0) -> 0
A100: 563 S Denver St, Salt Lake City, UT 84111 | B100: Salt Lake City | C100: Salt Lake City | D100: https://www.zillow.com/homedetails/563-S-Denver-St-Salt-Lake-City-UT-84111/305058059_zpid/ | E100: 1200000 | F100: 1529 | G100: 5280 | H100: 8 | I100: 300000 | J100: 590 | K100: 430 | L100: 1.1549653 | M100: 495.4583 | N100: 517.41334 | O100: =IFERROR(_xlfn.XLOOKUP(A100,$T$1:$T$13,$S$1:$S$13,,0),0) -> 0 | P100: =IFERROR(_xlfn.XLOOKUP(A100,$T$1:$T$13,$U$1:$U$13,,0),0) -> 0 | Q100: =IF(P100>1,P100,G100) -> 5280 | R100: =IFERROR(_xlfn.XLOOKUP(A100,$T$1:$T$13,$V$1:$V$13,,0),0) -> 0
A101: 803 E 6th Ave N, Salt Lake City, UT 84103 | B101: Avenues | C101: Salt Lake City | D101: https://www.zillow.com/homedetails/803-E-6th-Ave-N-Salt-Lake-City-UT-84103/457411105_zpid/ | E101: 750000 | F101: (blank) | G101: 2640 | H101: 4 | I101: 187500 | J101: 368.75 | K101: 268.75 | L101: 32.065081 | M101: 551.47059 | N101: 312.5 | O101: =IFERROR(_xlfn.XLOOKUP(A101,$T$1:$T$13,$S$1:$S$13,,0),0) -> 0 | P101: =IFERROR(_xlfn.XLOOKUP(A101,$T$1:$T$13,$U$1:$U$13,,0),0) -> 0 | Q101: =IF(P101>1,P101,G101) -> 2640 | R101: =IFERROR(_xlfn.XLOOKUP(A101,$T$1:$T$13,$V$1:$V$13,,0),0) -> 0
...

Sheet DATA>>

Sheet Inputs
A1: ASSUMPTIONS
L2: SLC Duplex
A3: MLS # | K3: Springville Duplex | L3: 1692304
B4: 1309 Hidden Ct | C4: =B5/4 -> #N/A | E4: 1309 Hidden Ct | F4: UofU 7-plex | G4: Sugarhouse triplex | H4: 1600 S 4 plex | I4: Texas 1 | J4: Texas 2 | M4: Millcreek fourplex | N4: UofU 4-plex | O4: Marmalade Duplex
A5: Monthly Rent Yr1 | B5: =_xlfn.XLOOKUP(1,Pivot!$O$10:$O$131,Pivot!$Q$10:$Q$131,,0) -> #N/A | C5: =XLOOKUP(1,Pivot!$O$10:$O$131,Pivot!$Q$10:$Q$131,,0) | E5: =_xlfn.XLOOKUP(1,Pivot!$O$10:$O$131,Pivot!$Q$10:$Q$131,,0) -> #N/A | F5: =1795+995+1195+1195+1495+1150 -> 7825 | G5: =2600+1400+1350 -> 5350 | H5: =1350+1200*3 -> 4950 | I5: =4*700 -> 2800 | J5: =700*4 -> 2800 | K5: =750+1250 -> 2000 | L5: =2500 -> 2500 | M5: =1925+1100+1800+1800 -> 6625 | N5: =1875+1200+1150+1500 -> 5725 | O5: 4900
A6: Annual Rent in Year 1 | B6: =B5*12 -> #N/A | E6: =E5*12 -> #N/A | F6: =F5*12 -> 93900 | G6: =G5*12 -> 64200 | H6: =H5*12 -> 59400 | I6: =I5*12 -> 33600 | J6: =J5*12 -> 33600 | K6: =K5*12 -> 24000 | L6: =L5*12 -> 30000 | ... O6: =O5*12 -> 58800
A7: Change in Rent | B7: 0.03 | E7: 0.03 | F7: 0.035 | G7: 0.035 | H7: 0.035 | I7: =I23 -> 0.025 | J7: =J23 -> 0.025 | K7: =K23 -> 0.025 | L7: =L23 -> 0.025 | M7: =M23 -> 0.025 | N7: =N23 -> 0.025 | O7: =O23 -> 0.025
A8: Vacancy & Bad Debts Losses | B8: 0.01 | E8: 0.01 | F8: 0.01 | G8: 0.01 | H8: 0.01 | I8: 0.03 | J8: 0.03 | K8: 0.03 | L8: 0.03 | M8: 0.03 | N8: 0.03 | O8: 0.03
A9: Operating Expenses in Year 1 | B9: =B42 -> #N/A | E9: =E42 -> #N/A | F9: =F42 -> 23845.549 | G9: =G42 -> 13558.744 | H9: =H42 -> 13513.289 | I9: =I42 -> 8743.7081 | J9: =J42 -> 9309.7608 | K9: =K42 -> 6577.3374 | L9: =L42 -> 11260.946 | ... O9: =O42 -> 12745.634
A10: Growth Rate in Operating Expenses | B10: =B23 -> 0.025 | C10: % per Year | E10: =E23 -> 0.025 | F10: =F23 -> 0.025 | G10: =G23 -> 0.025 | H10: =H23 -> 0.025 | I10: =I23 -> 0.025 | J10: =J23 -> 0.025 | K10: =K23 -> 0.025 | L10: =L23 -> 0.025 | ... O10: =O23 -> 0.025
A11: Purchase Price | B11: =_xlfn.XLOOKUP(1,Pivot!$O$10:$O$131,Pivot!$E$10:$E$131,,0)*(1-Pivot!$Q$2) -> #N/A | C11: =_xlfn.XLOOKUP(1,Pivot!$O$10:$O$131,Pivot!$E$10:$E$131,,0)*(1-Pivot!$Q$3-Pivot!$Q$2) -> #N/A | E11: =_xlfn.XLOOKUP(1,Pivot!$O$10:$O$131,Pivot!$E$10:$E$131,,0)*(1-Pivot!$Q$3-Pivot!$Q$2) -> #N/A | F11: =1899000*0.97 -> 1842030 | G11: 970000 | H11: =1000000*0.97 -> 970000 | I11: 330000 | J11: 420000 | K11: 310000 | L11: =(460000-10000)*101.75% -> 457875 | M11: 1195000 | N11: 1195000 | O11: 825000
A12: Loan-to-Value Ratio | B12: =1-B13/B11 -> #N/A | C12: % of Asking Price | E12: =1-E13/E11 -> #N/A | F12: 0.75 | G12: 0.75 | H12: 0.75 | I12: =(1-I13/I11) -> 0.95 | J12: =(1-J13/J11) -> 0.95 | K12: =(1-K13/K11) -> 0.9 | L12: =(1-L13/L11) -> 0.95 | M12: 0.8 | N12: 0.8 | O12: 0.8
A13: Down Payment | B13: =MIN(Pivot!H1,B11*0.25) -> #N/A | E13: =MIN(Pivot!K1,E11*0.25) -> #N/A | F13: =F11*(1-F12) -> 460507.5 | G13: =G11*(1-G12) -> 242500 | H13: =H11*(1-H12) -> 242500 | I13: =I11*0.05 -> 16500 | J13: =J11*0.05 -> 21000 | K13: =K11*0.1 -> 31000 | L13: =L11*0.05 -> 22893.75 | M13: =M11*(1-M12) -> 239000 | N13: =N11*(1-N12) -> 239000 | O13: =O11*(1-O12) -> 165000
A14: Mortgage Interest Rate | B14: 0.067 | C14: % Annual | E14: 0.067 | F14: 0.068 | G14: 0.07 | H14: 0.07 | I14: 0.03 | J14: 0.03 | K14: 0.025 | L14: 0.025 | M14: 0.06 | N14: 0.06 | O14: 0.06
A15: Mortgage Amortization Period | B15: 360 | C15: Months - Monthly Compounding | E15: 360 | F15: 360 | G15: 360 | H15: 360 | I15: 360 | J15: 360 | K15: 360 | L15: 360 | M15: 360 | N15: 360 | O15: 360
A16: Land-to-Value Ratio | B16: 0.5 | C16: % Non-depreciable for Tax | E16: 0.5 | F16: 0.5 | G16: 0.5 | H16: 0.5 | I16: 0.5 | J16: 0.5 | K16: 0.5 | L16: 0.5 | M16: 0.5 | N16: 0.5 | O16: 0.5
A17: Useful Life | B17: 27.5 | C17: Years of Tax Depreciable Life | E17: 27.5 | F17: 27.5 | G17: 27.5 | H17: 27.5 | I17: 27.5 | J17: 27.5 | K17: 27.5 | L17: 27.5 | M17: 27.5 | N17: 27.5 | O17: 27.5
A18: Ordinary Income Tax Rate | B18: 0.25 | C18: % Marginal Tax Rate | E18: 0.25 | F18: 0.25 | G18: 0.25 | H18: 0.25 | I18: 0.25 | J18: 0.25 | K18: 0.25 | L18: 0.25 | M18: 0.25 | N18: 0.25 | O18: 0.25
A19: Required Rate of Return--100% Equity | B19: 0.1 | C19: % per Year | E19: 0.1 | F19: 0.1 | G19: 0.1 | H19: 0.1 | I19: 0.1 | J19: 0.1 | K19: 0.1 | L19: 0.1 | M19: 0.1 | N19: 0.1 | O19: 0.1
A20: Required Equity for PMI To Drop Off | B20: 0.22 | C20: % | E20: 0.22 | F20: 0.22 | G20: 0.22 | H20: 0.22 | I20: 0.22 | J20: 0.22 | K20: 0.22 | L20: 0.22 | M20: 0.22 | N20: 0.22 | O20: 0.22
A22: Appreciation Rate | B22: 0.025 | C22: % per Year | E22: 0.025 | F22: 0.035 | G22: 0.035 | H22: 0.035 | I22: 0.01 | J22: 0.025 | K22: 0.025 | L22: 0.025 | M22: 0.025 | N22: 0.025 | O22: 0.025
A23: Inflation | B23: 0.025 | C23: % per Year | E23: 0.025 | F23: 0.025 | G23: 0.025 | H23: 0.025 | I23: 0.025 | J23: 0.025 | K23: 0.025 | L23: 0.025 | M23: 0.025 | N23: 0.025 | O23: 0.025
A24: Monthly Mortgage Payment | B24: =PMT(B14/12,B15,B11-B13) -> #N/A | C24: =B24*12 -> #N/A | E24: =PMT(E14/12,E15,E11-E13) -> #N/A | F24: =PMT(F14/12,F15,F11-F13) -> -9006.4932 | G24: =PMT(G14/12,G15,G11-G13) -> -4840.0757 | H24: =PMT(H14/12,H15,H11-H13) -> -4840.0757 | I24: =PMT(I14/12,I15,I11-I13) -> -1321.7286 | J24: =PMT(J14/12,J15,J11-J13) -> -1682.2001 | K24: =PMT(K14/12,K15,K11-K13) -> -1102.3873 | L24: =PMT(L14/12,L15,L11-L13) -> -1718.7018 | ... O24: =PMT(O14/12,O15,O11-O13) -> -3957.0335
A25: NPV Discount Rate | B25: N/A | C25: % per Year | E25: N/A | F25: N/A | G25: N/A | H25: N/A | I25: N/A | J25: N/A | K25: N/A | L25: N/A | M25: N/A | N25: N/A | O25: N/A
A27: Secondary Loan Amount | B27: 0 | E27: 0 | F27: 0 | G27: 0 | H27: 0 | I27: 0 | J27: 0 | K27: 0 | L27: 0 | M27: 0 | N27: 0 | O27: 0
A28: Secondary Loan Rate | B28: 0.08 | E28: 0.08 | F28: 0.08 | G28: 0.08 | H28: 0.08 | I28: 0.06625 | J28: 0.06625 | K28: 0.06625 | L28: 0.06625 | M28: 0.06625 | N28: 0.06625 | O28: 0.06625
A30: OPERATING EXPENSES
A32: Management Expense | B32: 0.01 | E32: 0.01 | F32: 0.01 | G32: 0.01 | H32: 0.01 | I32: 0 | J32: 0 | K32: 0 | L32: 0 | M32: 0 | N32: 0 | O32: 0
A33: Management Fees | B33: =7*300/2 -> 1050 | E33: =7*300/2 -> 1050 | F33: =7*300/2 -> 1050 | G33: =G5/660/2*300/2 -> 607.95455 | H33: =H5/660/2*300/2 -> 562.5 | I33: =I5/660/2*300/2 -> 318.18182 | J33: =J5/660/2*300/2 -> 318.18182 | K33: =K5/660/2*300/2 -> 227.27273 | L33: =L5/660/2*300/2 -> 284.09091 | M33: =M5/660/2*300/2 -> 752.84091 | N33: =N5/660/2*300/2 -> 650.56818 | O33: =O5/660/2*300/2 -> 556.81818
A34: Advertising/Agent Fees | B34: 0 | E34: 0 | F34: 0 | G34: 0 | H34: 0 | I34: 0 | J34: 0 | K34: 0 | L34: 0 | M34: 0 | N34: 0 | O34: 0
A35: PMI | B35: 0 | E35: 0 | F35: 0 | G35: 0 | H35: 0 | I35: =350*12 -> 4200 | J35: =350*12 -> 4200 | K35: =205/305*K11/1000*12 -> 2500.3279 | L35: =IF(L13/L11<0.05,0.0085,0.008)*L11 -> 3663 | M35: 0 | N35: 0 | O35: 0
A36: Maintenance / Misc | B36: =B11*0.005 -> #N/A | E36: =E11*0.005 -> #N/A | F36: =F11*0.005 -> 9210.15 | G36: =G11*0.005 -> 4850 | H36: =H11*0.005 -> 4850 | I36: =I11*0.005 -> 1650 | J36: =I36 -> 1650 | K36: 1000 | L36: =L11*0.0075 -> 3434.0625 | M36: 3000 | N36: 3000 | O36: 3000
A37: Utilities / HOA | B37: =1300/775000*B11+4200 -> #N/A | E37: =1300/775000*E11+4200 -> #N/A | F37: 2000 | G37: 2000 | H37: 2000 | I37: 500 | J37: 500 | K37: 900 | L37: 1000 | M37: 4000 | N37: 4000 | O37: 4000
A38: Hazard Insurance | B38: =_xlfn.XLOOKUP(1,Pivot!$O$10:$O$131,Pivot!$K$10:$K$131,,0)*12 -> #N/A | C38: =600*12 -> 7200 | E38: 3000 | F38: =0.45%*F11 -> 8289.135 | G38: =0.45%*G11 -> 4365 | H38: =0.45%*H11 -> 4365 | I38: =0.45%*I11 -> 1485 | J38: =0.45%*J11 -> 1890 | K38: =0.45%*K11 -> 1395 | L38: =0.45%*L11 -> 2060.4375 | M38: =0.45%*M11 -> 5377.5 | ... O38: =0.45%*O11 -> 3712.5
A39: Property Taxes | B39: =_xlfn.XLOOKUP(1,Pivot!$O$10:$O$131,Pivot!$J$10:$J$131,,0)*12 -> #N/A | C39: =_xlfn.XLOOKUP(1,Pivot!$O$10:$O$131,Pivot!$J$10:$J$131,,0)*12 -> #N/A | E39: 5534 | F39: =1700/950000*F11 -> 3296.2642 | G39: =1700/950000*G11 -> 1735.7895 | H39: =1700/950000*H11 -> 1735.7895 | I39: =1700/950000*I11 -> 590.52632 | J39: =1700/950000*J11 -> 751.57895 | K39: =1700/950000*K11 -> 554.73684 | L39: =1700/950000*L11 -> 819.35526 | M39: =1700/950000*M11 -> 2138.4211 | ... O39: =1700/950000*O11 -> 1476.3158
A40: Interest Expense (Secondary Loan) | B40: =B28*B27 -> 0 | E40: =E28*E27 -> 0 | F40: =F28*F27 -> 0 | G40: =G28*G27 -> 0 | H40: =H28*H27 -> 0 | I40: =I28*I27 -> 0 | J40: =J28*J27 -> 0 | K40: =K28*K27 -> 0 | L40: =L28*L27 -> 0 | ... O40: =O28*O27 -> 0
C41: =B39/12 -> #N/A
A42: TOTAL | B42: =SUM(B33:B40) -> #N/A | E42: =SUM(E33:E40) -> #N/A | F42: =SUM(F33:F40) -> 23845.549 | G42: =SUM(G33:G40) -> 13558.744 | H42: =SUM(H33:H40) -> 13513.289 | I42: =SUM(I33:I40) -> 8743.7081 | J42: =SUM(J33:J40) -> 9309.7608 | K42: =SUM(K33:K40) -> 6577.3374 | L42: =SUM(L33:L40) -> 11260.946 | ... O42: =SUM(O33:O40) -> 12745.634
A44: CALCULATIONS
A46: Monthly Depreciation | B46: =(B11*(1-B16))/(B17*12) -> #N/A | E46: =(E11*(1-E16))/(E17*12) -> #N/A | F46: =(F11*(1-F16))/(F17*12) -> 2790.9545 | G46: =(G11*(1-G16))/(G17*12) -> 1469.697 | H46: =(H11*(1-H16))/(H17*12) -> 1469.697 | I46: =(I11*(1-I16))/(I17*12) -> 500 | J46: =(J11*(1-J16))/(J17*12) -> 636.36364 | K46: =(K11*(1-K16))/(K17*12) -> 469.69697 | L46: =(L11*(1-L16))/(L17*12) -> 693.75 | ... O46: =(O11*(1-O16))/(O17*12) -> 1250
A47: Cap Rate | B47: =(B6-(SUM(B36:B39)))/B11 -> #N/A | E47: =(E6-(SUM(E36:E39)))/E11 -> #N/A | F47: =(F6-(SUM(F36:F39)))/F11 -> 0.038601136 | G47: =(G6-(SUM(G36:G39)))/G11 -> 0.052834238 | H47: =(H6-(SUM(H36:H39)))/H11 -> 0.047885784 | I47: =(I6-(SUM(I36:I39)))/I11 -> 0.089013557 | J47: =(J6-(SUM(J36:J39)))/J11 -> 0.068591479 | K47: =(K6-(SUM(K36:K39)))/K11 -> 0.065000849 | L47: =(L6-(SUM(L36:L39)))/L11 -> 0.04954659 | ... O47: =(O6-(SUM(O36:O39)))/O11 -> 0.056498405
A48: Rent Multiplier | B48: =B11/(B6/12) -> #N/A | E48: =E11/(E6/12) -> #N/A | F48: =F11/(F6/12) -> 235.40319 | G48: =G11/(G6/12) -> 181.30841 | H48: =H11/(H6/12) -> 195.9596 | I48: =I11/(I6/12) -> 117.85714 | J48: =J11/(J6/12) -> 150 | K48: =K11/(K6/12) -> 155 | L48: =L11/(L6/12) -> 183.15 | ... O48: =O11/(O6/12) -> 168.36735
A49: Closing Costs | B49: =13000/700000*(B11*B12) -> #N/A | E49: =13000/700000*(E11*E12) -> #N/A | F49: =13000/700000*(F11*F12) -> 25656.846 | G49: =13000/700000*(G11*G12) -> 13510.714 | H49: =13000/700000*(H11*H12) -> 13510.714 | I49: =13000/700000*(I11*I12) -> 5822.1429 | J49: =13000/700000*(J11*J12) -> 7410 | K49: =13000/700000*(K11*K12) -> 5181.4286 | L49: =13000/700000*(L11*L12) -> 8078.2232 | ... O49: =13000/700000*(O11*O12) -> 12257.143
A50: CoC Return | B50: =(B6-SUM(B36:B39)+B24*12)/(B13+B49) -> #N/A | E50: =(E6-SUM(E36:E39)+E24*12)/(E13+E49) -> #N/A | F50: =(F6-SUM(F36:F39)+F24*12)/(F13+F49) -> -0.076051375 | G50: =(G6-SUM(G36:G39)+G24*12)/(G13+G49) -> -0.026685201 | H50: =(H6-SUM(H36:H39)+H24*12)/(H13+H49) -> -0.045434416 | I50: =(I6-SUM(I36:I39)+I24*12)/(I13+I49) -> 0.60539573 | J50: =(J6-SUM(J36:J39)+J24*12)/(J13+J49) -> 0.30348539 | K50: =(K6-SUM(K36:K39)+K24*12)/(K13+K49) -> 0.19130299 | L50: =(L6-SUM(L36:L39)+L24*12)/(L13+L49) -> 0.066567371 | ... O50: =(O6-SUM(O36:O39)+O24*12)/(O13+O49) -> -0.0049262747
A51: NOI | B51: =(B6-SUM(B36:B39)) -> #N/A | E51: =(E6-SUM(E36:E39)) -> #N/A | F51: =(F6-SUM(F36:F39)) -> 71104.451 | G51: =(G6-SUM(G36:G39)) -> 51249.211 | H51: =(H6-SUM(H36:H39)) -> 46449.211 | I51: =(I6-SUM(I36:I39)) -> 29374.474 | J51: =(J6-SUM(J36:J39)) -> 28808.421 | K51: =(K6-SUM(K36:K39)) -> 20150.263 | L51: =(L6-SUM(L36:L39)) -> 22686.145 | ... O51: =(O6-SUM(O36:O39)) -> 46611.184
L52: occupy 60 days after closing
A55: * Total positive cashflows (rents minus deductible expenses) are taxed at 'ordinary income tax rate'
A56: * Net positive cashflows after taxes are applied to balance of the secondary loan
A59: Assumptions to consider including in the model:
A61: Selling Expenses | C61: % of Sale Price
A62: Mortgage Financing Costs | C62: % of Loan Amount
A63: Mortgage Prepayment Penalty | C63: % of Mortgage Balance
A64: Acquisition Costs | C64: % of Asking Price
A65: Capital Gains Tax Rate
A66: Depreciation Recapture Tax Rate
A68: 1039
A70: CONTRACT INPUTS
A71: Earnest Money | B71: =B74*0.02 -> #N/A | E71: =E74*0.02 -> #N/A
A72: New Loan | B72: =B12*B11 -> #N/A | E72: =E12*E11 -> #N/A
A73: Balance of PP | B73: =B74-B72-B71 -> #N/A | E73: =E74-E72-E71 -> #N/A
A74: PP | B74: =B11 -> #N/A | E74: =E11 -> #N/A
D75: Days
A76: Deadlines | B76: Date | C76: Weeks | E76: Date
A77: Today | C77: 45914 | D77: =C78*7 -> 7
A78: Seller Disclosure | B78: =$C$77+C78*7 -> 45921 | C78: 1 | D78: =C79*7 -> 28 | E78: =$C$77+F78*7 -> 45914
A79: Due Dilligence | B79: =$C$77+C79*7 -> 45942 | C79: =C78+3 -> 4 | D79: =C80*7 -> 28 | E79: =$C$77+F79*7 -> 45914
A80: Financing Deadline | B80: =$C$77+C80*7 -> 45942 | C80: =C79 -> 4 | D80: =C81*7 -> 35 | E80: =$C$77+F80*7 -> 45914
A81: Settlement Deadline | B81: =$C$77+C81*7 -> 45949 | C81: =C80+1 -> 5 | E81: =$C$77+F81*7 -> 45914
B82: TOTAL | C82: =MAX(C78:C81)*7 -> 35 | E82: TOTAL

Sheet Financials
B1: 45658 | C1: =EDATE(B1,1) -> 45689 | D1: =EDATE(C1,1) -> 45717 | E1: =EDATE(D1,1) -> 45748 | F1: =EDATE(E1,1) -> 45778 | G1: =EDATE(F1,1) -> 45809 | H1: =EDATE(G1,1) -> 45839 | I1: =EDATE(H1,1) -> 45870 | J1: =EDATE(I1,1) -> 45901 | ... M1: =EDATE(L1,1) -> 45992 | N1: =YEAR(M1)&" Total" -> 2025 Total | O1: =EDATE(M1,1) -> 46023 | P1: =EDATE(O1,1) -> 46054 | Q1: =EDATE(P1,1) -> 46082 | R1: =EDATE(Q1,1) -> 46113 | S1: =EDATE(R1,1) -> 46143 | T1: =EDATE(S1,1) -> 46174 | U1: =EDATE(T1,1) -> 46204 | V1: =EDATE(U1,1) -> 46235 | W1: =EDATE(V1,1) -> 46266 | ... Z1: =EDATE(Y1,1) -> 46357 | AA1: =YEAR(Z1)&" Total" -> 2026 Total | AB1: =EDATE(Z1,1) -> 46388 | AC1: =EDATE(AB1,1) -> 46419 | AD1: =EDATE(AC1,1) -> 46447 | AE1: =EDATE(AD1,1) -> 46478 | AF1: =EDATE(AE1,1) -> 46508 | AG1: =EDATE(AF1,1) -> 46539 | AH1: =EDATE(AG1,1) -> 46569 | AI1: =EDATE(AH1,1) -> 46600 | AJ1: =EDATE(AI1,1) -> 46631 | ... AM1: =EDATE(AL1,1) -> 46722 | AN1: =YEAR(AM1)&" Total" -> 2027 Total | AO1: =EDATE(AM1,1) -> 46753 | AP1: =EDATE(AO1,1) -> 46784 | AQ1: =EDATE(AP1,1) -> 46813 | AR1: =EDATE(AQ1,1) -> 46844 | AS1: =EDATE(AR1,1) -> 46874 | AT1: =EDATE(AS1,1) -> 46905 | AU1: =EDATE(AT1,1) -> 46935 | AV1: =EDATE(AU1,1) -> 46966 | AW1: =EDATE(AV1,1) -> 46997 | ... AZ1: =EDATE(AY1,1) -> 47088 | BA1: =YEAR(AZ1)&" Total" -> 2028 Total | BB1: =EDATE(AZ1,1) -> 47119 | BC1: =EDATE(BB1,1) -> 47150 | BD1: =EDATE(BC1,1) -> 47178 | BE1: =EDATE(BD1,1) -> 47209 | BF1: =EDATE(BE1,1) -> 47239 | BG1: =EDATE(BF1,1) -> 47270 | BH1: =EDATE(BG1,1) -> 47300 | BI1: =EDATE(BH1,1) -> 47331 | BJ1: =EDATE(BI1,1) -> 47362 | ... BM1: =EDATE(BL1,1) -> 47453 | BN1: =YEAR(BM1)&" Total" -> 2029 Total | BO1: =EDATE(BM1,1) -> 47484 | BP1: =EDATE(BO1,1) -> 47515 | BQ1: =EDATE(BP1,1) -> 47543 | BR1: =EDATE(BQ1,1) -> 47574 | BS1: =EDATE(BR1,1) -> 47604 | BT1: =EDATE(BS1,1) -> 47635 | BU1: =EDATE(BT1,1) -> 47665 | BV1: =EDATE(BU1,1) -> 47696 | BW1: =EDATE(BV1,1) -> 47727 | ... BZ1: =EDATE(BY1,1) -> 47818 | CA1: =YEAR(BZ1)&" Total" -> 2030 Total | CB1: =EDATE(BZ1,1) -> 47849 | CC1: =EDATE(CB1,1) -> 47880 | CD1: =EDATE(CC1,1) -> 47908 | CE1: =EDATE(CD1,1) -> 47939 | CF1: =EDATE(CE1,1) -> 47969 | CG1: =EDATE(CF1,1) -> 48000 | CH1: =EDATE(CG1,1) -> 48030 | CI1: =EDATE(CH1,1) -> 48061 | CJ1: =EDATE(CI1,1) -> 48092 | ... CM1: =EDATE(CL1,1) -> 48183 | CN1: =YEAR(CM1)&" Total" -> 2031 Total | CO1: =EDATE(CM1,1) -> 48214 | CP1: =EDATE(CO1,1) -> 48245 | CQ1: =EDATE(CP1,1) -> 48274 | CR1: =EDATE(CQ1,1) -> 48305 | CS1: =EDATE(CR1,1) -> 48335 | CT1: =EDATE(CS1,1) -> 48366 | CU1: =EDATE(CT1,1) -> 48396 | CV1: =EDATE(CU1,1) -> 48427 | CW1: =EDATE(CV1,1) -> 48458 | ... CZ1: =EDATE(CY1,1) -> 48549 | DA1: =YEAR(CZ1)&" Total" -> 2032 Total | DB1: =EDATE(CZ1,1) -> 48580 | DC1: =EDATE(DB1,1) -> 48611 | DD1: =EDATE(DC1,1) -> 48639 | DE1: =EDATE(DD1,1) -> 48670 | DF1: =EDATE(DE1,1) -> 48700 | DG1: =EDATE(DF1,1) -> 48731 | DH1: =EDATE(DG1,1) -> 48761 | DI1: =EDATE(DH1,1) -> 48792 | DJ1: =EDATE(DI1,1) -> 48823 | ... DM1: =EDATE(DL1,1) -> 48914 | DN1: =YEAR(DM1)&" Total" -> 2033 Total | DO1: =EDATE(DM1,1) -> 48945 | DP1: =EDATE(DO1,1) -> 48976 | DQ1: =EDATE(DP1,1) -> 49004 | DR1: =EDATE(DQ1,1) -> 49035 | DS1: =EDATE(DR1,1) -> 49065 | DT1: =EDATE(DS1,1) -> 49096 | DU1: =EDATE(DT1,1) -> 49126 | DV1: =EDATE(DU1,1) -> 49157 | DW1: =EDATE(DV1,1) -> 49188 | ... DZ1: =EDATE(DY1,1) -> 49279 | EA1: =YEAR(DZ1)&" Total" -> 2034 Total | EB1: =EDATE(DZ1,1) -> 49310 | EC1: =EDATE(EB1,1) -> 49341 | ED1: =EDATE(EC1,1) -> 49369 | EE1: =EDATE(ED1,1) -> 49400 | EF1: =EDATE(EE1,1) -> 49430 | EG1: =EDATE(EF1,1) -> 49461 | EH1: =EDATE(EG1,1) -> 49491 | EI1: =EDATE(EH1,1) -> 49522 | EJ1: =EDATE(EI1,1) -> 49553 | ... EM1: =EDATE(EL1,1) -> 49644 | EN1: =YEAR(EM1)&" Total" -> 2035 Total | EO1: =EDATE(EM1,1) -> 49675 | EP1: =EDATE(EO1,1) -> 49706 | EQ1: =EDATE(EP1,1) -> 49735 | ER1: =EDATE(EQ1,1) -> 49766 | ES1: =EDATE(ER1,1) -> 49796 | ET1: =EDATE(ES1,1) -> 49827 | EU1: =EDATE(ET1,1) -> 49857 | EV1: =EDATE(EU1,1) -> 49888 | EW1: =EDATE(EV1,1) -> 49919 | ... EZ1: =EDATE(EY1,1) -> 50010 | FA1: =YEAR(EZ1)&" Total" -> 2036 Total | FB1: =EDATE(EZ1,1) -> 50041 | FC1: =EDATE(FB1,1) -> 50072 | FD1: =EDATE(FC1,1) -> 50100 | FE1: =EDATE(FD1,1) -> 50131 | FF1: =EDATE(FE1,1) -> 50161 | FG1: =EDATE(FF1,1) -> 50192 | FH1: =EDATE(FG1,1) -> 50222 | FI1: =EDATE(FH1,1) -> 50253 | FJ1: =EDATE(FI1,1) -> 50284 | ... FM1: =EDATE(FL1,1) -> 50375 | FN1: =YEAR(FM1)&" Total" -> 2037 Total | FO1: =EDATE(FM1,1) -> 50406 | FP1: =EDATE(FO1,1) -> 50437 | FQ1: =EDATE(FP1,1) -> 50465 | FR1: =EDATE(FQ1,1) -> 50496 | FS1: =EDATE(FR1,1) -> 50526 | FT1: =EDATE(FS1,1) -> 50557 | FU1: =EDATE(FT1,1) -> 50587 | FV1: =EDATE(FU1,1) -> 50618 | FW1: =EDATE(FV1,1) -> 50649 | ... FZ1: =EDATE(FY1,1) -> 50740 | GA1: =YEAR(FZ1)&" Total" -> 2038 Total | GB1: =EDATE(FZ1,1) -> 50771 | GC1: =EDATE(GB1,1) -> 50802 | GD1: =EDATE(GC1,1) -> 50830 | GE1: =EDATE(GD1,1) -> 50861 | GF1: =EDATE(GE1,1) -> 50891 | GG1: =EDATE(GF1,1) -> 50922 | GH1: =EDATE(GG1,1) -> 50952 | GI1: =EDATE(GH1,1) -> 50983 | GJ1: =EDATE(GI1,1) -> 51014 | ... GM1: =EDATE(GL1,1) -> 51105 | GN1: =YEAR(GM1)&" Total" -> 2039 Total | GO1: =EDATE(GM1,1) -> 51136 | GP1: =EDATE(GO1,1) -> 51167 | GQ1: =EDATE(GP1,1) -> 51196 | GR1: =EDATE(GQ1,1) -> 51227 | GS1: =EDATE(GR1,1) -> 51257 | GT1: =EDATE(GS1,1) -> 51288 | GU1: =EDATE(GT1,1) -> 51318 | GV1: =EDATE(GU1,1) -> 51349 | GW1: =EDATE(GV1,1) -> 51380 | ... GZ1: =EDATE(GY1,1) -> 51471 | HA1: =YEAR(GZ1)&" Total" -> 2040 Total | HB1: =EDATE(GZ1,1) -> 51502 | HC1: =EDATE(HB1,1) -> 51533 | HD1: =EDATE(HC1,1) -> 51561 | HE1: =EDATE(HD1,1) -> 51592 | HF1: =EDATE(HE1,1) -> 51622 | HG1: =EDATE(HF1,1) -> 51653 | HH1: =EDATE(HG1,1) -> 51683 | HI1: =EDATE(HH1,1) -> 51714 | HJ1: =EDATE(HI1,1) -> 51745 | ... HM1: =EDATE(HL1,1) -> 51836 | HN1: =YEAR(HM1)&" Total" -> 2041 Total | HO1: =EDATE(HM1,1) -> 51867 | HP1: =EDATE(HO1,1) -> 51898 | HQ1: =EDATE(HP1,1) -> 51926 | HR1: =EDATE(HQ1,1) -> 51957 | HS1: =EDATE(HR1,1) -> 51987 | HT1: =EDATE(HS1,1) -> 52018 | HU1: =EDATE(HT1,1) -> 52048 | HV1: =EDATE(HU1,1) -> 52079 | HW1: =EDATE(HV1,1) -> 52110 | ... HZ1: =EDATE(HY1,1) -> 52201 | IA1: =YEAR(HZ1)&" Total" -> 2042 Total | IB1: =EDATE(HZ1,1) -> 52232 | IC1: =EDATE(IB1,1) -> 52263 | ID1: =EDATE(IC1,1) -> 52291 | IE1: =EDATE(ID1,1) -> 52322 | IF1: =EDATE(IE1,1) -> 52352 | IG1: =EDATE(IF1,1) -> 52383 | IH1: =EDATE(IG1,1) -> 52413 | II1: =EDATE(IH1,1) -> 52444 | IJ1: =EDATE(II1,1) -> 52475 | ... IM1: =EDATE(IL1,1) -> 52566 | IN1: =YEAR(IM1)&" Total" -> 2043 Total | IO1: =EDATE(IM1,1) -> 52597 | IP1: =EDATE(IO1,1) -> 52628 | IQ1: =EDATE(IP1,1) -> 52657 | IR1: =EDATE(IQ1,1) -> 52688 | IS1: =EDATE(IR1,1) -> 52718 | IT1: =EDATE(IS1,1) -> 52749 | IU1: =EDATE(IT1,1) -> 52779 | IV1: =EDATE(IU1,1) -> 52810 | IW1: =EDATE(IV1,1) -> 52841 | ... IZ1: =EDATE(IY1,1) -> 52932 | JA1: =YEAR(IZ1)&" Total" -> 2044 Total | JB1: =EDATE(IZ1,1) -> 52963 | JC1: =EDATE(JB1,1) -> 52994 | JD1: =EDATE(JC1,1) -> 53022 | JE1: =EDATE(JD1,1) -> 53053 | JF1: =EDATE(JE1,1) -> 53083 | JG1: =EDATE(JF1,1) -> 53114 | JH1: =EDATE(JG1,1) -> 53144 | JI1: =EDATE(JH1,1) -> 53175 | JJ1: =EDATE(JI1,1) -> 53206 | ... JM1: =EDATE(JL1,1) -> 53297 | JN1: =YEAR(JM1)&" Total" -> 2045 Total | JO1: =EDATE(JM1,1) -> 53328 | JP1: =EDATE(JO1,1) -> 53359 | JQ1: =EDATE(JP1,1) -> 53387 | JR1: =EDATE(JQ1,1) -> 53418 | JS1: =EDATE(JR1,1) -> 53448 | JT1: =EDATE(JS1,1) -> 53479 | JU1: =EDATE(JT1,1) -> 53509 | JV1: =EDATE(JU1,1) -> 53540 | JW1: =EDATE(JV1,1) -> 53571 | ... JZ1: =EDATE(JY1,1) -> 53662 | KA1: =YEAR(JZ1)&" Total" -> 2046 Total | KB1: =EDATE(JZ1,1) -> 53693 | KC1: =EDATE(KB1,1) -> 53724 | KD1: =EDATE(KC1,1) -> 53752 | KE1: =EDATE(KD1,1) -> 53783 | KF1: =EDATE(KE1,1) -> 53813 | KG1: =EDATE(KF1,1) -> 53844 | KH1: =EDATE(KG1,1) -> 53874 | KI1: =EDATE(KH1,1) -> 53905 | KJ1: =EDATE(KI1,1) -> 53936 | ... KM1: =EDATE(KL1,1) -> 54027 | KN1: =YEAR(KM1)&" Total" -> 2047 Total | KO1: =EDATE(KM1,1) -> 54058 | KP1: =EDATE(KO1,1) -> 54089 | KQ1: =EDATE(KP1,1) -> 54118 | KR1: =EDATE(KQ1,1) -> 54149 | KS1: =EDATE(KR1,1) -> 54179 | KT1: =EDATE(KS1,1) -> 54210 | KU1: =EDATE(KT1,1) -> 54240 | KV1: =EDATE(KU1,1) -> 54271 | KW1: =EDATE(KV1,1) -> 54302 | ... KZ1: =EDATE(KY1,1) -> 54393 | LA1: =YEAR(KZ1)&" Total" -> 2048 Total | LB1: =EDATE(KZ1,1) -> 54424 | LC1: =EDATE(LB1,1) -> 54455 | LD1: =EDATE(LC1,1) -> 54483 | LE1: =EDATE(LD1,1) -> 54514 | LF1: =EDATE(LE1,1) -> 54544 | LG1: =EDATE(LF1,1) -> 54575 | LH1: =EDATE(LG1,1) -> 54605 | LI1: =EDATE(LH1,1) -> 54636 | LJ1: =EDATE(LI1,1) -> 54667 | ... LM1: =EDATE(LL1,1) -> 54758 | LN1: =YEAR(LM1)&" Total" -> 2049 Total | LO1: =EDATE(LM1,1) -> 54789 | LP1: =EDATE(LO1,1) -> 54820 | LQ1: =EDATE(LP1,1) -> 54848 | LR1: =EDATE(LQ1,1) -> 54879 | LS1: =EDATE(LR1,1) -> 54909 | LT1: =EDATE(LS1,1) -> 54940 | LU1: =EDATE(LT1,1) -> 54970 | LV1: =EDATE(LU1,1) -> 55001 | LW1: =EDATE(LV1,1) -> 55032 | ... LZ1: =EDATE(LY1,1) -> 55123 | MA1: =YEAR(LZ1)&" Total" -> 2050 Total | MB1: =EDATE(LZ1,1) -> 55154 | MC1: =EDATE(MB1,1) -> 55185 | MD1: =EDATE(MC1,1) -> 55213 | ME1: =EDATE(MD1,1) -> 55244 | MF1: =EDATE(ME1,1) -> 55274 | MG1: =EDATE(MF1,1) -> 55305 | MH1: =EDATE(MG1,1) -> 55335 | MI1: =EDATE(MH1,1) -> 55366 | MJ1: =EDATE(MI1,1) -> 55397 | ... MM1: =EDATE(ML1,1) -> 55488 | MN1: =YEAR(MM1)&" Total" -> 2051 Total | MO1: =EDATE(MM1,1) -> 55519 | MP1: =EDATE(MO1,1) -> 55550 | MQ1: =EDATE(MP1,1) -> 55579 | MR1: =EDATE(MQ1,1) -> 55610 | MS1: =EDATE(MR1,1) -> 55640 | MT1: =EDATE(MS1,1) -> 55671 | MU1: =EDATE(MT1,1) -> 55701 | MV1: =EDATE(MU1,1) -> 55732 | MW1: =EDATE(MV1,1) -> 55763 | ... MZ1: =EDATE(MY1,1) -> 55854 | NA1: =YEAR(MZ1)&" Total" -> 2052 Total | NB1: =EDATE(MZ1,1) -> 55885 | NC1: =EDATE(NB1,1) -> 55916 | ND1: =EDATE(NC1,1) -> 55944 | NE1: =EDATE(ND1,1) -> 55975 | NF1: =EDATE(NE1,1) -> 56005 | NG1: =EDATE(NF1,1) -> 56036 | NH1: =EDATE(NG1,1) -> 56066 | NI1: =EDATE(NH1,1) -> 56097 | NJ1: =EDATE(NI1,1) -> 56128 | ... NM1: =EDATE(NL1,1) -> 56219 | NN1: =YEAR(NM1)&" Total" -> 2053 Total | NO1: =EDATE(NM1,1) -> 56250 | NP1: =EDATE(NO1,1) -> 56281 | NQ1: =EDATE(NP1,1) -> 56309 | NR1: =EDATE(NQ1,1) -> 56340 | NS1: =EDATE(NR1,1) -> 56370 | NT1: =EDATE(NS1,1) -> 56401 | NU1: =EDATE(NT1,1) -> 56431 | NV1: =EDATE(NU1,1) -> 56462 | NW1: =EDATE(NV1,1) -> 56493 | ... NZ1: =EDATE(NY1,1) -> 56584 | OA1: =YEAR(NZ1)&" Total" -> 2054 Total | OB1: =EDATE(NZ1,1) -> 56615 | OC1: =EDATE(OB1,1) -> 56646 | OD1: =EDATE(OC1,1) -> 56674 | OE1: =EDATE(OD1,1) -> 56705 | OF1: =EDATE(OE1,1) -> 56735 | OG1: =EDATE(OF1,1) -> 56766 | OH1: =EDATE(OG1,1) -> 56796 | OI1: =EDATE(OH1,1) -> 56827 | OJ1: =EDATE(OI1,1) -> 56858 | ... OM1: =EDATE(OL1,1) -> 56949 | ON1: =YEAR(OM1)&" Total" -> 2055 Total | OO1: =EDATE(OM1,1) -> 56980 | OP1: =EDATE(OO1,1) -> 57011 | OQ1: =EDATE(OP1,1) -> 57040 | OR1: =EDATE(OQ1,1) -> 57071 | OS1: =EDATE(OR1,1) -> 57101 | OT1: =EDATE(OS1,1) -> 57132 | OU1: =EDATE(OT1,1) -> 57162 | OV1: =EDATE(OU1,1) -> 57193 | OW1: =EDATE(OV1,1) -> 57224 | ... OZ1: =EDATE(OY1,1) -> 57315 | PA1: =YEAR(OZ1)&" Total" -> 2056 Total | PB1: =EDATE(OZ1,1) -> 57346 | PC1: =EDATE(PB1,1) -> 57377 | PD1: =EDATE(PC1,1) -> 57405 | PE1: =EDATE(PD1,1) -> 57436 | PF1: =EDATE(PE1,1) -> 57466 | PG1: =EDATE(PF1,1) -> 57497 | PH1: =EDATE(PG1,1) -> 57527 | PI1: =EDATE(PH1,1) -> 57558 | PJ1: =EDATE(PI1,1) -> 57589 | ... PM1: =EDATE(PL1,1) -> 57680 | PN1: =YEAR(PM1)&" Total" -> 2057 Total | PO1: =EDATE(PM1,1) -> 57711 | PP1: =EDATE(PO1,1) -> 57742 | PQ1: =EDATE(PP1,1) -> 57770 | PR1: =EDATE(PQ1,1) -> 57801 | PS1: =EDATE(PR1,1) -> 57831 | PT1: =EDATE(PS1,1) -> 57862 | PU1: =EDATE(PT1,1) -> 57892 | PV1: =EDATE(PU1,1) -> 57923 | PW1: =EDATE(PV1,1) -> 57954 | ... PZ1: =EDATE(PY1,1) -> 58045 | QA1: =YEAR(PZ1)&" Total" -> 2058 Total | QB1: =EDATE(PZ1,1) -> 58076 | QC1: =EDATE(QB1,1) -> 58107 | QD1: =EDATE(QC1,1) -> 58135 | QE1: =EDATE(QD1,1) -> 58166 | QF1: =EDATE(QE1,1) -> 58196 | QG1: =EDATE(QF1,1) -> 58227 | QH1: =EDATE(QG1,1) -> 58257 | QI1: =EDATE(QH1,1) -> 58288 | QJ1: =EDATE(QI1,1) -> 58319 | ... QM1: =EDATE(QL1,1) -> 58410 | QN1: =YEAR(QM1)&" Total" -> 2059 Total | QO1: =EDATE(QM1,1) -> 58441 | QP1: =EDATE(QO1,1) -> 58472 | QQ1: =EDATE(QP1,1) -> 58501 | QR1: =EDATE(QQ1,1) -> 58532 | QS1: =EDATE(QR1,1) -> 58562 | QT1: =EDATE(QS1,1) -> 58593 | QU1: =EDATE(QT1,1) -> 58623 | QV1: =EDATE(QU1,1) -> 58654 | QW1: =EDATE(QV1,1) -> 58685 | ... QZ1: =EDATE(QY1,1) -> 58776 | RA1: =YEAR(QZ1)&" Total" -> 2060 Total | RB1: =EDATE(QZ1,1) -> 58807 | RC1: =EDATE(RB1,1) -> 58838 | RD1: =EDATE(RC1,1) -> 58866 | RE1: =EDATE(RD1,1) -> 58897 | RF1: =EDATE(RE1,1) -> 58927 | RG1: =EDATE(RF1,1) -> 58958 | RH1: =EDATE(RG1,1) -> 58988 | RI1: =EDATE(RH1,1) -> 59019 | RJ1: =EDATE(RI1,1) -> 59050 | ... RM1: =EDATE(RL1,1) -> 59141 | RN1: =YEAR(RM1)&" Total" -> 2061 Total
C2: =(YEAR(D1)-YEAR(B1))/12 -> 0
A3: KEY METRICS
A4: Cash Flow | B4: =B52 -> #N/A | C4: =C52 -> #N/A | D4: =D52 -> #N/A | E4: =E52 -> #N/A | F4: =F52 -> #N/A | G4: =G52 -> #N/A | H4: =H52 -> #N/A | I4: =I52 -> #N/A | ... M4: =M52 -> #N/A | N4: =SUM(B4:M4) -> #N/A | O4: =O52 -> #N/A | P4: =P52 -> #N/A | Q4: =Q52 -> #N/A | R4: =R52 -> #N/A | S4: =S52 -> #N/A | T4: =T52 -> #N/A | U4: =U52 -> #N/A | V4: =V52 -> #N/A | ... Z4: =Z52 -> #N/A | AA4: =SUM(O4:Z4) -> #N/A | AB4: =AB52 -> #N/A | AC4: =AC52 -> #N/A | AD4: =AD52 -> #N/A | AE4: =AE52 -> #N/A | AF4: =AF52 -> #N/A | AG4: =AG52 -> #N/A | AH4: =AH52 -> #N/A | AI4: =AI52 -> #N/A | ... AM4: =AM52 -> #N/A | AN4: =SUM(AB4:AM4) -> #N/A | AO4: =AO52 -> #N/A | AP4: =AP52 -> #N/A | AQ4: =AQ52 -> #N/A | AR4: =AR52 -> #N/A | AS4: =AS52 -> #N/A | AT4: =AT52 -> #N/A | AU4: =AU52 -> #N/A | AV4: =AV52 -> #N/A | ... AZ4: =AZ52 -> #N/A | BA4: =SUM(AO4:AZ4) -> #N/A | BB4: =BB52 -> #N/A | BC4: =BC52 -> #N/A | BD4: =BD52 -> #N/A | BE4: =BE52 -> #N/A | BF4: =BF52 -> #N/A | BG4: =BG52 -> #N/A | BH4: =BH52 -> #N/A | BI4: =BI52 -> #N/A | ... BM4: =BM52 -> #N/A | BN4: =SUM(BB4:BM4) -> #N/A | BO4: =BO52 -> #N/A | BP4: =BP52 -> #N/A | BQ4: =BQ52 -> #N/A | BR4: =BR52 -> #N/A | BS4: =BS52 -> #N/A | BT4: =BT52 -> #N/A | BU4: =BU52 -> #N/A | BV4: =BV52 -> #N/A | ... BZ4: =BZ52 -> #N/A | CA4: =SUM(BO4:BZ4) -> #N/A | CB4: =CB52 -> #N/A | CC4: =CC52 -> #N/A | CD4: =CD52 -> #N/A | CE4: =CE52 -> #N/A | CF4: =CF52 -> #N/A | CG4: =CG52 -> #N/A | CH4: =CH52 -> #N/A | CI4: =CI52 -> #N/A | ... CM4: =CM52 -> #N/A | CN4: =SUM(CB4:CM4) -> #N/A | CO4: =CO52 -> #N/A | CP4: =CP52 -> #N/A | CQ4: =CQ52 -> #N/A | CR4: =CR52 -> #N/A | CS4: =CS52 -> #N/A | CT4: =CT52 -> #N/A | CU4: =CU52 -> #N/A | CV4: =CV52 -> #N/A | ... CZ4: =CZ52 -> #N/A | DA4: =SUM(CO4:CZ4) -> #N/A | DB4: =DB52 -> #N/A | DC4: =DC52 -> #N/A | DD4: =DD52 -> #N/A | DE4: =DE52 -> #N/A | DF4: =DF52 -> #N/A | DG4: =DG52 -> #N/A | DH4: =DH52 -> #N/A | DI4: =DI52 -> #N/A | ... DM4: =DM52 -> #N/A | DN4: =SUM(DB4:DM4) -> #N/A | DO4: =DO52 -> #N/A | DP4: =DP52 -> #N/A | DQ4: =DQ52 -> #N/A | DR4: =DR52 -> #N/A | DS4: =DS52 -> #N/A | DT4: =DT52 -> #N/A | DU4: =DU52 -> #N/A | DV4: =DV52 -> #N/A | ... DZ4: =DZ52 -> #N/A | EA4: =SUM(DO4:DZ4) -> #N/A | EB4: =EB52 -> #N/A | EC4: =EC52 -> #N/A | ED4: =ED52 -> #N/A | EE4: =EE52 -> #N/A | EF4: =EF52 -> #N/A | EG4: =EG52 -> #N/A | EH4: =EH52 -> #N/A | EI4: =EI52 -> #N/A | ... EM4: =EM52 -> #N/A | EN4: =SUM(EB4:EM4) -> #N/A | EO4: =EO52 -> #N/A | EP4: =EP52 -> #N/A | EQ4: =EQ52 -> #N/A | ER4: =ER52 -> #N/A | ES4: =ES52 -> #N/A | ET4: =ET52 -> #N/A | EU4: =EU52 -> #N/A | EV4: =EV52 -> #N/A | ... EZ4: =EZ52 -> #N/A | FA4: =SUM(EO4:EZ4) -> #N/A | FB4: =FB52 -> #N/A | FC4: =FC52 -> #N/A | FD4: =FD52 -> #N/A | FE4: =FE52 -> #N/A | FF4: =FF52 -> #N/A | FG4: =FG52 -> #N/A | FH4: =FH52 -> #N/A | FI4: =FI52 -> #N/A | ... FM4: =FM52 -> #N/A | FN4: =SUM(FB4:FM4) -> #N/A | FO4: =FO52 -> #N/A | FP4: =FP52 -> #N/A | FQ4: =FQ52 -> #N/A | FR4: =FR52 -> #N/A | FS4: =FS52 -> #N/A | FT4: =FT52 -> #N/A | FU4: =FU52 -> #N/A | FV4: =FV52 -> #N/A | ... FZ4: =FZ52 -> #N/A | GA4: =SUM(FO4:FZ4) -> #N/A | GB4: =GB52 -> #N/A | GC4: =GC52 -> #N/A | GD4: =GD52 -> #N/A | GE4: =GE52 -> #N/A | GF4: =GF52 -> #N/A | GG4: =GG52 -> #N/A | GH4: =GH52 -> #N/A | GI4: =GI52 -> #N/A | ... GM4: =GM52 -> #N/A | GN4: =SUM(GB4:GM4) -> #N/A | GO4: =GO52 -> #N/A | GP4: =GP52 -> #N/A | GQ4: =GQ52 -> #N/A | GR4: =GR52 -> #N/A | GS4: =GS52 -> #N/A | GT4: =GT52 -> #N/A | GU4: =GU52 -> #N/A | GV4: =GV52 -> #N/A | ... GZ4: =GZ52 -> #N/A | HA4: =SUM(GO4:GZ4) -> #N/A | HB4: =HB52 -> #N/A | HC4: =HC52 -> #N/A | HD4: =HD52 -> #N/A | HE4: =HE52 -> #N/A | HF4: =HF52 -> #N/A | HG4: =HG52 -> #N/A | HH4: =HH52 -> #N/A | HI4: =HI52 -> #N/A | ... HM4: =HM52 -> #N/A | HN4: =SUM(HB4:HM4) -> #N/A | HO4: =HO52 -> #N/A | HP4: =HP52 -> #N/A | HQ4: =HQ52 -> #N/A | HR4: =HR52 -> #N/A | HS4: =HS52 -> #N/A | HT4: =HT52 -> #N/A | HU4: =HU52 -> #N/A | HV4: =HV52 -> #N/A | ... HZ4: =HZ52 -> #N/A | IA4: =SUM(HO4:HZ4) -> #N/A | IB4: =IB52 -> #N/A | IC4: =IC52 -> #N/A | ID4: =ID52 -> #N/A | IE4: =IE52 -> #N/A | IF4: =IF52 -> #N/A | IG4: =IG52 -> #N/A | IH4: =IH52 -> #N/A | II4: =II52 -> #N/A | ... IM4: =IM52 -> #N/A | IN4: =SUM(IB4:IM4) -> #N/A | IO4: =IO52 -> #N/A | IP4: =IP52 -> #N/A | IQ4: =IQ52 -> #N/A | IR4: =IR52 -> #N/A | IS4: =IS52 -> #N/A | IT4: =IT52 -> #N/A | IU4: =IU52 -> #N/A | IV4: =IV52 -> #N/A | ... IZ4: =IZ52 -> #N/A | JA4: =SUM(IO4:IZ4) -> #N/A | JB4: =JB52 -> #N/A | JC4: =JC52 -> #N/A | JD4: =JD52 -> #N/A | JE4: =JE52 -> #N/A | JF4: =JF52 -> #N/A | JG4: =JG52 -> #N/A | JH4: =JH52 -> #N/A | JI4: =JI52 -> #N/A | ... JM4: =JM52 -> #N/A | JN4: =SUM(JB4:JM4) -> #N/A | JO4: =JO52 -> #N/A | JP4: =JP52 -> #N/A | JQ4: =JQ52 -> #N/A | JR4: =JR52 -> #N/A | JS4: =JS52 -> #N/A | JT4: =JT52 -> #N/A | JU4: =JU52 -> #N/A | JV4: =JV52 -> #N/A | ... JZ4: =JZ52 -> #N/A | KA4: =SUM(JO4:JZ4) -> #N/A | KB4: =KB52 -> #N/A | KC4: =KC52 -> #N/A | KD4: =KD52 -> #N/A | KE4: =KE52 -> #N/A | KF4: =KF52 -> #N/A | KG4: =KG52 -> #N/A | KH4: =KH52 -> #N/A | KI4: =KI52 -> #N/A | ... KM4: =KM52 -> #N/A | KN4: =SUM(KB4:KM4) -> #N/A | KO4: =KO52 -> #N/A | KP4: =KP52 -> #N/A | KQ4: =KQ52 -> #N/A | KR4: =KR52 -> #N/A | KS4: =KS52 -> #N/A | KT4: =KT52 -> #N/A | KU4: =KU52 -> #N/A | KV4: =KV52 -> #N/A | ... KZ4: =KZ52 -> #N/A | LA4: =SUM(KO4:KZ4) -> #N/A | LB4: =LB52 -> #N/A | LC4: =LC52 -> #N/A | LD4: =LD52 -> #N/A | LE4: =LE52 -> #N/A | LF4: =LF52 -> #N/A | LG4: =LG52 -> #N/A | LH4: =LH52 -> #N/A | LI4: =LI52 -> #N/A | ... LM4: =LM52 -> #N/A | LN4: =SUM(LB4:LM4) -> #N/A | LO4: =LO52 -> #N/A | LP4: =LP52 -> #N/A | LQ4: =LQ52 -> #N/A | LR4: =LR52 -> #N/A | LS4: =LS52 -> #N/A | LT4: =LT52 -> #N/A | LU4: =LU52 -> #N/A | LV4: =LV52 -> #N/A | ... LZ4: =LZ52 -> #N/A | MA4: =SUM(LO4:LZ4) -> #N/A | MB4: =MB52 -> #N/A | MC4: =MC52 -> #N/A | MD4: =MD52 -> #N/A | ME4: =ME52 -> #N/A | MF4: =MF52 -> #N/A | MG4: =MG52 -> #N/A | MH4: =MH52 -> #N/A | MI4: =MI52 -> #N/A | ... MM4: =MM52 -> #N/A | MN4: =SUM(MB4:MM4) -> #N/A | MO4: =MO52 -> #N/A | MP4: =MP52 -> #N/A | MQ4: =MQ52 -> #N/A | MR4: =MR52 -> #N/A | MS4: =MS52 -> #N/A | MT4: =MT52 -> #N/A | MU4: =MU52 -> #N/A | MV4: =MV52 -> #N/A | ... MZ4: =MZ52 -> #N/A | NA4: =SUM(MO4:MZ4) -> #N/A | NB4: =NB52 -> #N/A | NC4: =NC52 -> #N/A | ND4: =ND52 -> #N/A | NE4: =NE52 -> #N/A | NF4: =NF52 -> #N/A | NG4: =NG52 -> #N/A | NH4: =NH52 -> #N/A | NI4: =NI52 -> #N/A | ... NM4: =NM52 -> #N/A | NN4: =SUM(NB4:NM4) -> #N/A | NO4: =NO52 -> #N/A | NP4: =NP52 -> #N/A | NQ4: =NQ52 -> #N/A | NR4: =NR52 -> #N/A | NS4: =NS52 -> #N/A | NT4: =NT52 -> #N/A | NU4: =NU52 -> #N/A | NV4: =NV52 -> #N/A | ... NZ4: =NZ52 -> #N/A | OA4: =SUM(NO4:NZ4) -> #N/A | OB4: =OB52 -> #N/A | OC4: =OC52 -> #N/A | OD4: =OD52 -> #N/A | OE4: =OE52 -> #N/A | OF4: =OF52 -> #N/A | OG4: =OG52 -> #N/A | OH4: =OH52 -> #N/A | OI4: =OI52 -> #N/A | ... OM4: =OM52 -> #N/A | ON4: =SUM(OB4:OM4) -> #N/A | OO4: =OO52 -> #N/A | OP4: =OP52 -> #N/A | OQ4: =OQ52 -> #N/A | OR4: =OR52 -> #N/A | OS4: =OS52 -> #N/A | OT4: =OT52 -> #N/A | OU4: =OU52 -> #N/A | OV4: =OV52 -> #N/A | ... OZ4: =OZ52 -> #N/A | PA4: =SUM(OO4:OZ4) -> #N/A | PB4: =PB52 -> #N/A | PC4: =PC52 -> #N/A | PD4: =PD52 -> #N/A | PE4: =PE52 -> #N/A | PF4: =PF52 -> #N/A | PG4: =PG52 -> #N/A | PH4: =PH52 -> #N/A | PI4: =PI52 -> #N/A | ... PM4: =PM52 -> #N/A | PN4: =SUM(PB4:PM4) -> #N/A | PO4: =PO52 -> #N/A | PP4: =PP52 -> #N/A | PQ4: =PQ52 -> #N/A | PR4: =PR52 -> #N/A | PS4: =PS52 -> #N/A | PT4: =PT52 -> #N/A | PU4: =PU52 -> #N/A | PV4: =PV52 -> #N/A | ... PZ4: =PZ52 -> #N/A | QA4: =SUM(PO4:PZ4) -> #N/A | QB4: =QB52 -> #N/A | QC4: =QC52 -> #N/A | QD4: =QD52 -> #N/A | QE4: =QE52 -> #N/A | QF4: =QF52 -> #N/A | QG4: =QG52 -> #N/A | QH4: =QH52 -> #N/A | QI4: =QI52 -> #N/A | ... QM4: =QM52 -> #N/A | QN4: =SUM(QB4:QM4) -> #N/A | QO4: =QO52 -> #N/A | QP4: =QP52 -> #N/A | QQ4: =QQ52 -> #N/A | QR4: =QR52 -> #N/A | QS4: =QS52 -> #N/A | QT4: =QT52 -> #N/A | QU4: =QU52 -> #N/A | QV4: =QV52 -> #N/A | ... QZ4: =QZ52 -> #N/A | RA4: =SUM(QO4:QZ4) -> #N/A | RB4: =RB52 -> #N/A | RC4: =RC52 -> #N/A | RD4: =RD52 -> #N/A | RE4: =RE52 -> #N/A | RF4: =RF52 -> #N/A | RG4: =RG52 -> #N/A | RH4: =RH52 -> #N/A | RI4: =RI52 -> #N/A | ... RM4: =RM52 -> #N/A | RN4: =SUM(RB4:RM4) -> #N/A
A5: Cash Flow (pre-tax) | B5: =B52+B42 -> #N/A | C5: =C52+C42 -> #N/A | D5: =D52+D42 -> #N/A | E5: =E52+E42 -> #N/A | F5: =F52+F42 -> #N/A | G5: =G52+G42 -> #N/A | H5: =H52+H42 -> #N/A | I5: =I52+I42 -> #N/A | ... M5: =M52+M42 -> #N/A | N5: =SUM(B5:M5) -> #N/A | O5: =O52+O42 -> #N/A | P5: =P52+P42 -> #N/A | Q5: =Q52+Q42 -> #N/A | R5: =R52+R42 -> #N/A | S5: =S52+S42 -> #N/A | T5: =T52+T42 -> #N/A | U5: =U52+U42 -> #N/A | V5: =V52+V42 -> #N/A | ... Z5: =Z52+Z42 -> #N/A | AA5: =SUM(O5:Z5) -> #N/A | AB5: =AB52+AB42 -> #N/A | AC5: =AC52+AC42 -> #N/A | AD5: =AD52+AD42 -> #N/A | AE5: =AE52+AE42 -> #N/A | AF5: =AF52+AF42 -> #N/A | AG5: =AG52+AG42 -> #N/A | AH5: =AH52+AH42 -> #N/A | AI5: =AI52+AI42 -> #N/A | ... AM5: =AM52+AM42 -> #N/A | AN5: =SUM(AB5:AM5) -> #N/A | AO5: =AO52+AO42 -> #N/A | AP5: =AP52+AP42 -> #N/A | AQ5: =AQ52+AQ42 -> #N/A | AR5: =AR52+AR42 -> #N/A | AS5: =AS52+AS42 -> #N/A | AT5: =AT52+AT42 -> #N/A | AU5: =AU52+AU42 -> #N/A | AV5: =AV52+AV42 -> #N/A | ... AZ5: =AZ52+AZ42 -> #N/A | BA5: =SUM(AO5:AZ5) -> #N/A | BB5: =BB52+BB42 -> #N/A | BC5: =BC52+BC42 -> #N/A | BD5: =BD52+BD42 -> #N/A | BE5: =BE52+BE42 -> #N/A | BF5: =BF52+BF42 -> #N/A | BG5: =BG52+BG42 -> #N/A | BH5: =BH52+BH42 -> #N/A | BI5: =BI52+BI42 -> #N/A | ... BM5: =BM52+BM42 -> #N/A | BN5: =SUM(BB5:BM5) -> #N/A | BO5: =BO52+BO42 -> #N/A | BP5: =BP52+BP42 -> #N/A | BQ5: =BQ52+BQ42 -> #N/A | BR5: =BR52+BR42 -> #N/A | BS5: =BS52+BS42 -> #N/A | BT5: =BT52+BT42 -> #N/A | BU5: =BU52+BU42 -> #N/A | BV5: =BV52+BV42 -> #N/A | ... BZ5: =BZ52+BZ42 -> #N/A | CA5: =SUM(BO5:BZ5) -> #N/A | CB5: =CB52+CB42 -> #N/A | CC5: =CC52+CC42 -> #N/A | CD5: =CD52+CD42 -> #N/A | CE5: =CE52+CE42 -> #N/A | CF5: =CF52+CF42 -> #N/A | CG5: =CG52+CG42 -> #N/A | CH5: =CH52+CH42 -> #N/A | CI5: =CI52+CI42 -> #N/A | ... CM5: =CM52+CM42 -> #N/A | CN5: =SUM(CB5:CM5) -> #N/A | CO5: =CO52+CO42 -> #N/A | CP5: =CP52+CP42 -> #N/A | CQ5: =CQ52+CQ42 -> #N/A | CR5: =CR52+CR42 -> #N/A | CS5: =CS52+CS42 -> #N/A | CT5: =CT52+CT42 -> #N/A | CU5: =CU52+CU42 -> #N/A | CV5: =CV52+CV42 -> #N/A | ... CZ5: =CZ52+CZ42 -> #N/A | DA5: =SUM(CO5:CZ5) -> #N/A | DB5: =DB52+DB42 -> #N/A | DC5: =DC52+DC42 -> #N/A | DD5: =DD52+DD42 -> #N/A | DE5: =DE52+DE42 -> #N/A | DF5: =DF52+DF42 -> #N/A | DG5: =DG52+DG42 -> #N/A | DH5: =DH52+DH42 -> #N/A | DI5: =DI52+DI42 -> #N/A | ... DM5: =DM52+DM42 -> #N/A | DN5: =SUM(DB5:DM5) -> #N/A | DO5: =DO52+DO42 -> #N/A | DP5: =DP52+DP42 -> #N/A | DQ5: =DQ52+DQ42 -> #N/A | DR5: =DR52+DR42 -> #N/A | DS5: =DS52+DS42 -> #N/A | DT5: =DT52+DT42 -> #N/A | DU5: =DU52+DU42 -> #N/A | DV5: =DV52+DV42 -> #N/A | ... DZ5: =DZ52+DZ42 -> #N/A | EA5: =SUM(DO5:DZ5) -> #N/A | EB5: =EB52+EB42 -> #N/A | EC5: =EC52+EC42 -> #N/A | ED5: =ED52+ED42 -> #N/A | EE5: =EE52+EE42 -> #N/A | EF5: =EF52+EF42 -> #N/A | EG5: =EG52+EG42 -> #N/A | EH5: =EH52+EH42 -> #N/A | EI5: =EI52+EI42 -> #N/A | ... EM5: =EM52+EM42 -> #N/A | EN5: =SUM(EB5:EM5) -> #N/A | EO5: =EO52+EO42 -> #N/A | EP5: =EP52+EP42 -> #N/A | EQ5: =EQ52+EQ42 -> #N/A | ER5: =ER52+ER42 -> #N/A | ES5: =ES52+ES42 -> #N/A | ET5: =ET52+ET42 -> #N/A | EU5: =EU52+EU42 -> #N/A | EV5: =EV52+EV42 -> #N/A | ... EZ5: =EZ52+EZ42 -> #N/A | FA5: =SUM(EO5:EZ5) -> #N/A | FB5: =FB52+FB42 -> #N/A | FC5: =FC52+FC42 -> #N/A | FD5: =FD52+FD42 -> #N/A | FE5: =FE52+FE42 -> #N/A | FF5: =FF52+FF42 -> #N/A | FG5: =FG52+FG42 -> #N/A | FH5: =FH52+FH42 -> #N/A | FI5: =FI52+FI42 -> #N/A | ... FM5: =FM52+FM42 -> #N/A | FN5: =SUM(FB5:FM5) -> #N/A | FO5: =FO52+FO42 -> #N/A | FP5: =FP52+FP42 -> #N/A | FQ5: =FQ52+FQ42 -> #N/A | FR5: =FR52+FR42 -> #N/A | FS5: =FS52+FS42 -> #N/A | FT5: =FT52+FT42 -> #N/A | FU5: =FU52+FU42 -> #N/A | FV5: =FV52+FV42 -> #N/A | ... FZ5: =FZ52+FZ42 -> #N/A | GA5: =SUM(FO5:FZ5) -> #N/A | GB5: =GB52+GB42 -> #N/A | GC5: =GC52+GC42 -> #N/A | GD5: =GD52+GD42 -> #N/A | GE5: =GE52+GE42 -> #N/A | GF5: =GF52+GF42 -> #N/A | GG5: =GG52+GG42 -> #N/A | GH5: =GH52+GH42 -> #N/A | GI5: =GI52+GI42 -> #N/A | ... GM5: =GM52+GM42 -> #N/A | GN5: =SUM(GB5:GM5) -> #N/A | GO5: =GO52+GO42 -> #N/A | GP5: =GP52+GP42 -> #N/A | GQ5: =GQ52+GQ42 -> #N/A | GR5: =GR52+GR42 -> #N/A | GS5: =GS52+GS42 -> #N/A | GT5: =GT52+GT42 -> #N/A | GU5: =GU52+GU42 -> #N/A | GV5: =GV52+GV42 -> #N/A | ... GZ5: =GZ52+GZ42 -> #N/A | HA5: =SUM(GO5:GZ5) -> #N/A | HB5: =HB52+HB42 -> #N/A | HC5: =HC52+HC42 -> #N/A | HD5: =HD52+HD42 -> #N/A | HE5: =HE52+HE42 -> #N/A | HF5: =HF52+HF42 -> #N/A | HG5: =HG52+HG42 -> #N/A | HH5: =HH52+HH42 -> #N/A | HI5: =HI52+HI42 -> #N/A | ... HM5: =HM52+HM42 -> #N/A | HN5: =SUM(HB5:HM5) -> #N/A | HO5: =HO52+HO42 -> #N/A | HP5: =HP52+HP42 -> #N/A | HQ5: =HQ52+HQ42 -> #N/A | HR5: =HR52+HR42 -> #N/A | HS5: =HS52+HS42 -> #N/A | HT5: =HT52+HT42 -> #N/A | HU5: =HU52+HU42 -> #N/A | HV5: =HV52+HV42 -> #N/A | ... HZ5: =HZ52+HZ42 -> #N/A | IA5: =SUM(HO5:HZ5) -> #N/A | IB5: =IB52+IB42 -> #N/A | IC5: =IC52+IC42 -> #N/A | ID5: =ID52+ID42 -> #N/A | IE5: =IE52+IE42 -> #N/A | IF5: =IF52+IF42 -> #N/A | IG5: =IG52+IG42 -> #N/A | IH5: =IH52+IH42 -> #N/A | II5: =II52+II42 -> #N/A | ... IM5: =IM52+IM42 -> #N/A | IN5: =SUM(IB5:IM5) -> #N/A | IO5: =IO52+IO42 -> #N/A | IP5: =IP52+IP42 -> #N/A | IQ5: =IQ52+IQ42 -> #N/A | IR5: =IR52+IR42 -> #N/A | IS5: =IS52+IS42 -> #N/A | IT5: =IT52+IT42 -> #N/A | IU5: =IU52+IU42 -> #N/A | IV5: =IV52+IV42 -> #N/A | ... IZ5: =IZ52+IZ42 -> #N/A | JA5: =SUM(IO5:IZ5) -> #N/A | JB5: =JB52+JB42 -> #N/A | JC5: =JC52+JC42 -> #N/A | JD5: =JD52+JD42 -> #N/A | JE5: =JE52+JE42 -> #N/A | JF5: =JF52+JF42 -> #N/A | JG5: =JG52+JG42 -> #N/A | JH5: =JH52+JH42 -> #N/A | JI5: =JI52+JI42 -> #N/A | ... JM5: =JM52+JM42 -> #N/A | JN5: =SUM(JB5:JM5) -> #N/A | JO5: =JO52+JO42 -> #N/A | JP5: =JP52+JP42 -> #N/A | JQ5: =JQ52+JQ42 -> #N/A | JR5: =JR52+JR42 -> #N/A | JS5: =JS52+JS42 -> #N/A | JT5: =JT52+JT42 -> #N/A | JU5: =JU52+JU42 -> #N/A | JV5: =JV52+JV42 -> #N/A | ... JZ5: =JZ52+JZ42 -> #N/A | KA5: =SUM(JO5:JZ5) -> #N/A | KB5: =KB52+KB42 -> #N/A | KC5: =KC52+KC42 -> #N/A | KD5: =KD52+KD42 -> #N/A | KE5: =KE52+KE42 -> #N/A | KF5: =KF52+KF42 -> #N/A | KG5: =KG52+KG42 -> #N/A | KH5: =KH52+KH42 -> #N/A | KI5: =KI52+KI42 -> #N/A | ... KM5: =KM52+KM42 -> #N/A | KN5: =SUM(KB5:KM5) -> #N/A | KO5: =KO52+KO42 -> #N/A | KP5: =KP52+KP42 -> #N/A | KQ5: =KQ52+KQ42 -> #N/A | KR5: =KR52+KR42 -> #N/A | KS5: =KS52+KS42 -> #N/A | KT5: =KT52+KT42 -> #N/A | KU5: =KU52+KU42 -> #N/A | KV5: =KV52+KV42 -> #N/A | ... KZ5: =KZ52+KZ42 -> #N/A | LA5: =SUM(KO5:KZ5) -> #N/A | LB5: =LB52+LB42 -> #N/A | LC5: =LC52+LC42 -> #N/A | LD5: =LD52+LD42 -> #N/A | LE5: =LE52+LE42 -> #N/A | LF5: =LF52+LF42 -> #N/A | LG5: =LG52+LG42 -> #N/A | LH5: =LH52+LH42 -> #N/A | LI5: =LI52+LI42 -> #N/A | ... LM5: =LM52+LM42 -> #N/A | LN5: =SUM(LB5:LM5) -> #N/A | LO5: =LO52+LO42 -> #N/A | LP5: =LP52+LP42 -> #N/A | LQ5: =LQ52+LQ42 -> #N/A | LR5: =LR52+LR42 -> #N/A | LS5: =LS52+LS42 -> #N/A | LT5: =LT52+LT42 -> #N/A | LU5: =LU52+LU42 -> #N/A | LV5: =LV52+LV42 -> #N/A | ... LZ5: =LZ52+LZ42 -> #N/A | MA5: =SUM(LO5:LZ5) -> #N/A | MB5: =MB52+MB42 -> #N/A | MC5: =MC52+MC42 -> #N/A | MD5: =MD52+MD42 -> #N/A | ME5: =ME52+ME42 -> #N/A | MF5: =MF52+MF42 -> #N/A | MG5: =MG52+MG42 -> #N/A | MH5: =MH52+MH42 -> #N/A | MI5: =MI52+MI42 -> #N/A | ... MM5: =MM52+MM42 -> #N/A | MN5: =SUM(MB5:MM5) -> #N/A | MO5: =MO52+MO42 -> #N/A | MP5: =MP52+MP42 -> #N/A | MQ5: =MQ52+MQ42 -> #N/A | MR5: =MR52+MR42 -> #N/A | MS5: =MS52+MS42 -> #N/A | MT5: =MT52+MT42 -> #N/A | MU5: =MU52+MU42 -> #N/A | MV5: =MV52+MV42 -> #N/A | ... MZ5: =MZ52+MZ42 -> #N/A | NA5: =SUM(MO5:MZ5) -> #N/A | NB5: =NB52+NB42 -> #N/A | NC5: =NC52+NC42 -> #N/A | ND5: =ND52+ND42 -> #N/A | NE5: =NE52+NE42 -> #N/A | NF5: =NF52+NF42 -> #N/A | NG5: =NG52+NG42 -> #N/A | NH5: =NH52+NH42 -> #N/A | NI5: =NI52+NI42 -> #N/A | ... NM5: =NM52+NM42 -> #N/A | NN5: =SUM(NB5:NM5) -> #N/A | NO5: =NO52+NO42 -> #N/A | NP5: =NP52+NP42 -> #N/A | NQ5: =NQ52+NQ42 -> #N/A | NR5: =NR52+NR42 -> #N/A | NS5: =NS52+NS42 -> #N/A | NT5: =NT52+NT42 -> #N/A | NU5: =NU52+NU42 -> #N/A | NV5: =NV52+NV42 -> #N/A | ... NZ5: =NZ52+NZ42 -> #N/A | OA5: =SUM(NO5:NZ5) -> #N/A | OB5: =OB52+OB42 -> #N/A | OC5: =OC52+OC42 -> #N/A | OD5: =OD52+OD42 -> #N/A | OE5: =OE52+OE42 -> #N/A | OF5: =OF52+OF42 -> #N/A | OG5: =OG52+OG42 -> #N/A | OH5: =OH52+OH42 -> #N/A | OI5: =OI52+OI42 -> #N/A | ... OM5: =OM52+OM42 -> #N/A | ON5: =SUM(OB5:OM5) -> #N/A | OO5: =OO52+OO42 -> #N/A | OP5: =OP52+OP42 -> #N/A | OQ5: =OQ52+OQ42 -> #N/A | OR5: =OR52+OR42 -> #N/A | OS5: =OS52+OS42 -> #N/A | OT5: =OT52+OT42 -> #N/A | OU5: =OU52+OU42 -> #N/A | OV5: =OV52+OV42 -> #N/A | ... OZ5: =OZ52+OZ42 -> #N/A | PA5: =SUM(OO5:OZ5) -> #N/A | PB5: =PB52+PB42 -> #N/A | PC5: =PC52+PC42 -> #N/A | PD5: =PD52+PD42 -> #N/A | PE5: =PE52+PE42 -> #N/A | PF5: =PF52+PF42 -> #N/A | PG5: =PG52+PG42 -> #N/A | PH5: =PH52+PH42 -> #N/A | PI5: =PI52+PI42 -> #N/A | ... PM5: =PM52+PM42 -> #N/A | PN5: =SUM(PB5:PM5) -> #N/A | PO5: =PO52+PO42 -> #N/A | PP5: =PP52+PP42 -> #N/A | PQ5: =PQ52+PQ42 -> #N/A | PR5: =PR52+PR42 -> #N/A | PS5: =PS52+PS42 -> #N/A | PT5: =PT52+PT42 -> #N/A | PU5: =PU52+PU42 -> #N/A | PV5: =PV52+PV42 -> #N/A | ... PZ5: =PZ52+PZ42 -> #N/A | QA5: =SUM(PO5:PZ5) -> #N/A | QB5: =QB52+QB42 -> #N/A | QC5: =QC52+QC42 -> #N/A | QD5: =QD52+QD42 -> #N/A | QE5: =QE52+QE42 -> #N/A | QF5: =QF52+QF42 -> #N/A | QG5: =QG52+QG42 -> #N/A | QH5: =QH52+QH42 -> #N/A | QI5: =QI52+QI42 -> #N/A | ... QM5: =QM52+QM42 -> #N/A | QN5: =SUM(QB5:QM5) -> #N/A | QO5: =QO52+QO42 -> #N/A | QP5: =QP52+QP42 -> #N/A | QQ5: =QQ52+QQ42 -> #N/A | QR5: =QR52+QR42 -> #N/A | QS5: =QS52+QS42 -> #N/A | QT5: =QT52+QT42 -> #N/A | QU5: =QU52+QU42 -> #N/A | QV5: =QV52+QV42 -> #N/A | ... QZ5: =QZ52+QZ42 -> #N/A | RA5: =SUM(QO5:QZ5) -> #N/A | RB5: =RB52+RB42 -> #N/A | RC5: =RC52+RC42 -> #N/A | RD5: =RD52+RD42 -> #N/A | RE5: =RE52+RE42 -> #N/A | RF5: =RF52+RF42 -> #N/A | RG5: =RG52+RG42 -> #N/A | RH5: =RH52+RH42 -> #N/A | RI5: =RI52+RI42 -> #N/A | ... RM5: =RM52+RM42 -> #N/A | RN5: =SUM(RB5:RM5) -> #N/A
A6: Cash | B6: =B56 -> #N/A | C6: =C56 -> #N/A | D6: =D56 -> #N/A | E6: =E56 -> #N/A | F6: =F56 -> #N/A | G6: =G56 -> #N/A | H6: =H56 -> #N/A | I6: =I56 -> #N/A | ... RN6: =RN56 -> #N/A
A7: Cash (pre-tax) | B7: =B56+B42 -> #N/A | C7: =B7+C5 -> #N/A | D7: =C7+D5 -> #N/A | E7: =D7+E5 -> #N/A | F7: =E7+F5 -> #N/A | G7: =F7+G5 -> #N/A | H7: =G7+H5 -> #N/A | I7: =H7+I5 -> #N/A | J7: =I7+J5 -> #N/A | ... M7: =L7+M5 -> #N/A | N7: =M7 -> #N/A | O7: =M7+O5 -> #N/A | P7: =O7+P5 -> #N/A | Q7: =P7+Q5 -> #N/A | R7: =Q7+R5 -> #N/A | S7: =R7+S5 -> #N/A | T7: =S7+T5 -> #N/A | U7: =T7+U5 -> #N/A | V7: =U7+V5 -> #N/A | W7: =V7+W5 -> #N/A | ... Z7: =Y7+Z5 -> #N/A | AA7: =Z7 -> #N/A | AB7: =Z7+AB5 -> #N/A | AC7: =AB7+AC5 -> #N/A | AD7: =AC7+AD5 -> #N/A | AE7: =AD7+AE5 -> #N/A | AF7: =AE7+AF5 -> #N/A | AG7: =AF7+AG5 -> #N/A | AH7: =AG7+AH5 -> #N/A | AI7: =AH7+AI5 -> #N/A | AJ7: =AI7+AJ5 -> #N/A | ... AM7: =AL7+AM5 -> #N/A | AN7: =AM7 -> #N/A | AO7: =AM7+AO5 -> #N/A | AP7: =AO7+AP5 -> #N/A | AQ7: =AP7+AQ5 -> #N/A | AR7: =AQ7+AR5 -> #N/A | AS7: =AR7+AS5 -> #N/A | AT7: =AS7+AT5 -> #N/A | AU7: =AT7+AU5 -> #N/A | AV7: =AU7+AV5 -> #N/A | AW7: =AV7+AW5 -> #N/A | ... AZ7: =AY7+AZ5 -> #N/A | BA7: =AZ7 -> #N/A | BB7: =AZ7+BB5 -> #N/A | BC7: =BB7+BC5 -> #N/A | BD7: =BC7+BD5 -> #N/A | BE7: =BD7+BE5 -> #N/A | BF7: =BE7+BF5 -> #N/A | BG7: =BF7+BG5 -> #N/A | BH7: =BG7+BH5 -> #N/A | BI7: =BH7+BI5 -> #N/A | BJ7: =BI7+BJ5 -> #N/A | ... BM7: =BL7+BM5 -> #N/A | BN7: =BM7 -> #N/A | BO7: =BM7+BO5 -> #N/A | BP7: =BO7+BP5 -> #N/A | BQ7: =BP7+BQ5 -> #N/A | BR7: =BQ7+BR5 -> #N/A | BS7: =BR7+BS5 -> #N/A | BT7: =BS7+BT5 -> #N/A | BU7: =BT7+BU5 -> #N/A | BV7: =BU7+BV5 -> #N/A | BW7: =BV7+BW5 -> #N/A | ... BZ7: =BY7+BZ5 -> #N/A | CA7: =BZ7 -> #N/A | CB7: =BZ7+CB5 -> #N/A | CC7: =CB7+CC5 -> #N/A | CD7: =CC7+CD5 -> #N/A | CE7: =CD7+CE5 -> #N/A | CF7: =CE7+CF5 -> #N/A | CG7: =CF7+CG5 -> #N/A | CH7: =CG7+CH5 -> #N/A | CI7: =CH7+CI5 -> #N/A | CJ7: =CI7+CJ5 -> #N/A | ... CM7: =CL7+CM5 -> #N/A | CN7: =CM7 -> #N/A | CO7: =CM7+CO5 -> #N/A | CP7: =CO7+CP5 -> #N/A | CQ7: =CP7+CQ5 -> #N/A | CR7: =CQ7+CR5 -> #N/A | CS7: =CR7+CS5 -> #N/A | CT7: =CS7+CT5 -> #N/A | CU7: =CT7+CU5 -> #N/A | CV7: =CU7+CV5 -> #N/A | CW7: =CV7+CW5 -> #N/A | ... CZ7: =CY7+CZ5 -> #N/A | DA7: =CZ7 -> #N/A | DB7: =CZ7+DB5 -> #N/A | DC7: =DB7+DC5 -> #N/A | DD7: =DC7+DD5 -> #N/A | DE7: =DD7+DE5 -> #N/A | DF7: =DE7+DF5 -> #N/A | DG7: =DF7+DG5 -> #N/A | DH7: =DG7+DH5 -> #N/A | DI7: =DH7+DI5 -> #N/A | DJ7: =DI7+DJ5 -> #N/A | ... DM7: =DL7+DM5 -> #N/A | DN7: =DM7 -> #N/A | DO7: =DM7+DO5 -> #N/A | DP7: =DO7+DP5 -> #N/A | DQ7: =DP7+DQ5 -> #N/A | DR7: =DQ7+DR5 -> #N/A | DS7: =DR7+DS5 -> #N/A | DT7: =DS7+DT5 -> #N/A | DU7: =DT7+DU5 -> #N/A | DV7: =DU7+DV5 -> #N/A | DW7: =DV7+DW5 -> #N/A | ... DZ7: =DY7+DZ5 -> #N/A | EA7: =DZ7 -> #N/A | EB7: =DZ7+EB5 -> #N/A | EC7: =EB7+EC5 -> #N/A | ED7: =EC7+ED5 -> #N/A | EE7: =ED7+EE5 -> #N/A | EF7: =EE7+EF5 -> #N/A | EG7: =EF7+EG5 -> #N/A | EH7: =EG7+EH5 -> #N/A | EI7: =EH7+EI5 -> #N/A | EJ7: =EI7+EJ5 -> #N/A | ... EM7: =EL7+EM5 -> #N/A | EN7: =EM7 -> #N/A | EO7: =EM7+EO5 -> #N/A | EP7: =EO7+EP5 -> #N/A | EQ7: =EP7+EQ5 -> #N/A | ER7: =EQ7+ER5 -> #N/A | ES7: =ER7+ES5 -> #N/A | ET7: =ES7+ET5 -> #N/A | EU7: =ET7+EU5 -> #N/A | EV7: =EU7+EV5 -> #N/A | EW7: =EV7+EW5 -> #N/A | ... EZ7: =EY7+EZ5 -> #N/A | FA7: =EZ7 -> #N/A | FB7: =EZ7+FB5 -> #N/A | FC7: =FB7+FC5 -> #N/A | FD7: =FC7+FD5 -> #N/A | FE7: =FD7+FE5 -> #N/A | FF7: =FE7+FF5 -> #N/A | FG7: =FF7+FG5 -> #N/A | FH7: =FG7+FH5 -> #N/A | FI7: =FH7+FI5 -> #N/A | FJ7: =FI7+FJ5 -> #N/A | ... FM7: =FL7+FM5 -> #N/A | FN7: =FM7 -> #N/A | FO7: =FM7+FO5 -> #N/A | FP7: =FO7+FP5 -> #N/A | FQ7: =FP7+FQ5 -> #N/A | FR7: =FQ7+FR5 -> #N/A | FS7: =FR7+FS5 -> #N/A | FT7: =FS7+FT5 -> #N/A | FU7: =FT7+FU5 -> #N/A | FV7: =FU7+FV5 -> #N/A | FW7: =FV7+FW5 -> #N/A | ... FZ7: =FY7+FZ5 -> #N/A | GA7: =FZ7 -> #N/A | GB7: =FZ7+GB5 -> #N/A | GC7: =GB7+GC5 -> #N/A | GD7: =GC7+GD5 -> #N/A | GE7: =GD7+GE5 -> #N/A | GF7: =GE7+GF5 -> #N/A | GG7: =GF7+GG5 -> #N/A | GH7: =GG7+GH5 -> #N/A | GI7: =GH7+GI5 -> #N/A | GJ7: =GI7+GJ5 -> #N/A | ... GM7: =GL7+GM5 -> #N/A | GN7: =GM7 -> #N/A | GO7: =GM7+GO5 -> #N/A | GP7: =GO7+GP5 -> #N/A | GQ7: =GP7+GQ5 -> #N/A | GR7: =GQ7+GR5 -> #N/A | GS7: =GR7+GS5 -> #N/A | GT7: =GS7+GT5 -> #N/A | GU7: =GT7+GU5 -> #N/A | GV7: =GU7+GV5 -> #N/A | GW7: =GV7+GW5 -> #N/A | ... GZ7: =GY7+GZ5 -> #N/A | HA7: =GZ7 -> #N/A | HB7: =GZ7+HB5 -> #N/A | HC7: =HB7+HC5 -> #N/A | HD7: =HC7+HD5 -> #N/A | HE7: =HD7+HE5 -> #N/A | HF7: =HE7+HF5 -> #N/A | HG7: =HF7+HG5 -> #N/A | HH7: =HG7+HH5 -> #N/A | HI7: =HH7+HI5 -> #N/A | HJ7: =HI7+HJ5 -> #N/A | ... HM7: =HL7+HM5 -> #N/A | HN7: =HM7 -> #N/A | HO7: =HM7+HO5 -> #N/A | HP7: =HO7+HP5 -> #N/A | HQ7: =HP7+HQ5 -> #N/A | HR7: =HQ7+HR5 -> #N/A | HS7: =HR7+HS5 -> #N/A | HT7: =HS7+HT5 -> #N/A | HU7: =HT7+HU5 -> #N/A | HV7: =HU7+HV5 -> #N/A | HW7: =HV7+HW5 -> #N/A | ... HZ7: =HY7+HZ5 -> #N/A | IA7: =HZ7 -> #N/A | IB7: =HZ7+IB5 -> #N/A | IC7: =IB7+IC5 -> #N/A | ID7: =IC7+ID5 -> #N/A | IE7: =ID7+IE5 -> #N/A | IF7: =IE7+IF5 -> #N/A | IG7: =IF7+IG5 -> #N/A | IH7: =IG7+IH5 -> #N/A | II7: =IH7+II5 -> #N/A | IJ7: =II7+IJ5 -> #N/A | ... IM7: =IL7+IM5 -> #N/A | IN7: =IM7 -> #N/A | IO7: =IM7+IO5 -> #N/A | IP7: =IO7+IP5 -> #N/A | IQ7: =IP7+IQ5 -> #N/A | IR7: =IQ7+IR5 -> #N/A | IS7: =IR7+IS5 -> #N/A | IT7: =IS7+IT5 -> #N/A | IU7: =IT7+IU5 -> #N/A | IV7: =IU7+IV5 -> #N/A | IW7: =IV7+IW5 -> #N/A | ... IZ7: =IY7+IZ5 -> #N/A | JA7: =IZ7 -> #N/A | JB7: =IZ7+JB5 -> #N/A | JC7: =JB7+JC5 -> #N/A | JD7: =JC7+JD5 -> #N/A | JE7: =JD7+JE5 -> #N/A | JF7: =JE7+JF5 -> #N/A | JG7: =JF7+JG5 -> #N/A | JH7: =JG7+JH5 -> #N/A | JI7: =JH7+JI5 -> #N/A | JJ7: =JI7+JJ5 -> #N/A | ... JM7: =JL7+JM5 -> #N/A | JN7: =JM7 -> #N/A | JO7: =JM7+JO5 -> #N/A | JP7: =JO7+JP5 -> #N/A | JQ7: =JP7+JQ5 -> #N/A | JR7: =JQ7+JR5 -> #N/A | JS7: =JR7+JS5 -> #N/A | JT7: =JS7+JT5 -> #N/A | JU7: =JT7+JU5 -> #N/A | JV7: =JU7+JV5 -> #N/A | JW7: =JV7+JW5 -> #N/A | ... JZ7: =JY7+JZ5 -> #N/A | KA7: =JZ7 -> #N/A | KB7: =JZ7+KB5 -> #N/A | KC7: =KB7+KC5 -> #N/A | KD7: =KC7+KD5 -> #N/A | KE7: =KD7+KE5 -> #N/A | KF7: =KE7+KF5 -> #N/A | KG7: =KF7+KG5 -> #N/A | KH7: =KG7+KH5 -> #N/A | KI7: =KH7+KI5 -> #N/A | KJ7: =KI7+KJ5 -> #N/A | ... KM7: =KL7+KM5 -> #N/A | KN7: =KM7 -> #N/A | KO7: =KM7+KO5 -> #N/A | KP7: =KO7+KP5 -> #N/A | KQ7: =KP7+KQ5 -> #N/A | KR7: =KQ7+KR5 -> #N/A | KS7: =KR7+KS5 -> #N/A | KT7: =KS7+KT5 -> #N/A | KU7: =KT7+KU5 -> #N/A | KV7: =KU7+KV5 -> #N/A | KW7: =KV7+KW5 -> #N/A | ... KZ7: =KY7+KZ5 -> #N/A | LA7: =KZ7 -> #N/A | LB7: =KZ7+LB5 -> #N/A | LC7: =LB7+LC5 -> #N/A | LD7: =LC7+LD5 -> #N/A | LE7: =LD7+LE5 -> #N/A | LF7: =LE7+LF5 -> #N/A | LG7: =LF7+LG5 -> #N/A | LH7: =LG7+LH5 -> #N/A | LI7: =LH7+LI5 -> #N/A | LJ7: =LI7+LJ5 -> #N/A | ... LM7: =LL7+LM5 -> #N/A | LN7: =LM7 -> #N/A | LO7: =LM7+LO5 -> #N/A | LP7: =LO7+LP5 -> #N/A | LQ7: =LP7+LQ5 -> #N/A | LR7: =LQ7+LR5 -> #N/A | LS7: =LR7+LS5 -> #N/A | LT7: =LS7+LT5 -> #N/A | LU7: =LT7+LU5 -> #N/A | LV7: =LU7+LV5 -> #N/A | LW7: =LV7+LW5 -> #N/A | ... LZ7: =LY7+LZ5 -> #N/A | MA7: =LZ7 -> #N/A | MB7: =LZ7+MB5 -> #N/A | MC7: =MB7+MC5 -> #N/A | MD7: =MC7+MD5 -> #N/A | ME7: =MD7+ME5 -> #N/A | MF7: =ME7+MF5 -> #N/A | MG7: =MF7+MG5 -> #N/A | MH7: =MG7+MH5 -> #N/A | MI7: =MH7+MI5 -> #N/A | MJ7: =MI7+MJ5 -> #N/A | ... MM7: =ML7+MM5 -> #N/A | MN7: =MM7 -> #N/A | MO7: =MM7+MO5 -> #N/A | MP7: =MO7+MP5 -> #N/A | MQ7: =MP7+MQ5 -> #N/A | MR7: =MQ7+MR5 -> #N/A | MS7: =MR7+MS5 -> #N/A | MT7: =MS7+MT5 -> #N/A | MU7: =MT7+MU5 -> #N/A | MV7: =MU7+MV5 -> #N/A | MW7: =MV7+MW5 -> #N/A | ... MZ7: =MY7+MZ5 -> #N/A | NA7: =MZ7 -> #N/A | NB7: =MZ7+NB5 -> #N/A | NC7: =NB7+NC5 -> #N/A | ND7: =NC7+ND5 -> #N/A | NE7: =ND7+NE5 -> #N/A | NF7: =NE7+NF5 -> #N/A | NG7: =NF7+NG5 -> #N/A | NH7: =NG7+NH5 -> #N/A | NI7: =NH7+NI5 -> #N/A | NJ7: =NI7+NJ5 -> #N/A | ... NM7: =NL7+NM5 -> #N/A | NN7: =NM7 -> #N/A | NO7: =NM7+NO5 -> #N/A | NP7: =NO7+NP5 -> #N/A | NQ7: =NP7+NQ5 -> #N/A | NR7: =NQ7+NR5 -> #N/A | NS7: =NR7+NS5 -> #N/A | NT7: =NS7+NT5 -> #N/A | NU7: =NT7+NU5 -> #N/A | NV7: =NU7+NV5 -> #N/A | NW7: =NV7+NW5 -> #N/A | ... NZ7: =NY7+NZ5 -> #N/A | OA7: =NZ7 -> #N/A | OB7: =NZ7+OB5 -> #N/A | OC7: =OB7+OC5 -> #N/A | OD7: =OC7+OD5 -> #N/A | OE7: =OD7+OE5 -> #N/A | OF7: =OE7+OF5 -> #N/A | OG7: =OF7+OG5 -> #N/A | OH7: =OG7+OH5 -> #N/A | OI7: =OH7+OI5 -> #N/A | OJ7: =OI7+OJ5 -> #N/A | ... OM7: =OL7+OM5 -> #N/A | ON7: =OM7 -> #N/A | OO7: =OM7+OO5 -> #N/A | OP7: =OO7+OP5 -> #N/A | OQ7: =OP7+OQ5 -> #N/A | OR7: =OQ7+OR5 -> #N/A | OS7: =OR7+OS5 -> #N/A | OT7: =OS7+OT5 -> #N/A | OU7: =OT7+OU5 -> #N/A | OV7: =OU7+OV5 -> #N/A | OW7: =OV7+OW5 -> #N/A | ... OZ7: =OY7+OZ5 -> #N/A | PA7: =OZ7 -> #N/A | PB7: =OZ7+PB5 -> #N/A | PC7: =PB7+PC5 -> #N/A | PD7: =PC7+PD5 -> #N/A | PE7: =PD7+PE5 -> #N/A | PF7: =PE7+PF5 -> #N/A | PG7: =PF7+PG5 -> #N/A | PH7: =PG7+PH5 -> #N/A | PI7: =PH7+PI5 -> #N/A | PJ7: =PI7+PJ5 -> #N/A | ... PM7: =PL7+PM5 -> #N/A | PN7: =PM7 -> #N/A | PO7: =PM7+PO5 -> #N/A | PP7: =PO7+PP5 -> #N/A | PQ7: =PP7+PQ5 -> #N/A | PR7: =PQ7+PR5 -> #N/A | PS7: =PR7+PS5 -> #N/A | PT7: =PS7+PT5 -> #N/A | PU7: =PT7+PU5 -> #N/A | PV7: =PU7+PV5 -> #N/A | PW7: =PV7+PW5 -> #N/A | ... PZ7: =PY7+PZ5 -> #N/A | QA7: =PZ7 -> #N/A | QB7: =PZ7+QB5 -> #N/A | QC7: =QB7+QC5 -> #N/A | QD7: =QC7+QD5 -> #N/A | QE7: =QD7+QE5 -> #N/A | QF7: =QE7+QF5 -> #N/A | QG7: =QF7+QG5 -> #N/A | QH7: =QG7+QH5 -> #N/A | QI7: =QH7+QI5 -> #N/A | QJ7: =QI7+QJ5 -> #N/A | ... QM7: =QL7+QM5 -> #N/A | QN7: =QM7 -> #N/A | QO7: =QM7+QO5 -> #N/A | QP7: =QO7+QP5 -> #N/A | QQ7: =QP7+QQ5 -> #N/A | QR7: =QQ7+QR5 -> #N/A | QS7: =QR7+QS5 -> #N/A | QT7: =QS7+QT5 -> #N/A | QU7: =QT7+QU5 -> #N/A | QV7: =QU7+QV5 -> #N/A | QW7: =QV7+QW5 -> #N/A | ... QZ7: =QY7+QZ5 -> #N/A | RA7: =QZ7 -> #N/A | RB7: =QZ7+RB5 -> #N/A | RC7: =RB7+RC5 -> #N/A | RD7: =RC7+RD5 -> #N/A | RE7: =RD7+RE5 -> #N/A | RF7: =RE7+RF5 -> #N/A | RG7: =RF7+RG5 -> #N/A | RH7: =RG7+RH5 -> #N/A | RI7: =RH7+RI5 -> #N/A | RJ7: =RI7+RJ5 -> #N/A | ... RM7: =RL7+RM5 -> #N/A | RN7: =RM7 -> #N/A
A8: Net Income | B8: =B43 -> #N/A | C8: =C43 -> #N/A | D8: =D43 -> #N/A | E8: =E43 -> #N/A | F8: =F43 -> #N/A | G8: =G43 -> #N/A | H8: =H43 -> #N/A | I8: =I43 -> #N/A | ... M8: =M43 -> #N/A | N8: =SUM(B8:M8) -> #N/A | O8: =O43 -> #N/A | P8: =P43 -> #N/A | Q8: =Q43 -> #N/A | R8: =R43 -> #N/A | S8: =S43 -> #N/A | T8: =T43 -> #N/A | U8: =U43 -> #N/A | V8: =V43 -> #N/A | ... Z8: =Z43 -> #N/A | AA8: =SUM(O8:Z8) -> #N/A | AB8: =AB43 -> #N/A | AC8: =AC43 -> #N/A | AD8: =AD43 -> #N/A | AE8: =AE43 -> #N/A | AF8: =AF43 -> #N/A | AG8: =AG43 -> #N/A | AH8: =AH43 -> #N/A | AI8: =AI43 -> #N/A | ... AM8: =AM43 -> #N/A | AN8: =SUM(AB8:AM8) -> #N/A | AO8: =AO43 -> #N/A | AP8: =AP43 -> #N/A | AQ8: =AQ43 -> #N/A | AR8: =AR43 -> #N/A | AS8: =AS43 -> #N/A | AT8: =AT43 -> #N/A | AU8: =AU43 -> #N/A | AV8: =AV43 -> #N/A | ... AZ8: =AZ43 -> #N/A | BA8: =SUM(AO8:AZ8) -> #N/A | BB8: =BB43 -> #N/A | BC8: =BC43 -> #N/A | BD8: =BD43 -> #N/A | BE8: =BE43 -> #N/A | BF8: =BF43 -> #N/A | BG8: =BG43 -> #N/A | BH8: =BH43 -> #N/A | BI8: =BI43 -> #N/A | ... BM8: =BM43 -> #N/A | BN8: =SUM(BB8:BM8) -> #N/A | BO8: =BO43 -> #N/A | BP8: =BP43 -> #N/A | BQ8: =BQ43 -> #N/A | BR8: =BR43 -> #N/A | BS8: =BS43 -> #N/A | BT8: =BT43 -> #N/A | BU8: =BU43 -> #N/A | BV8: =BV43 -> #N/A | ... BZ8: =BZ43 -> #N/A | CA8: =SUM(BO8:BZ8) -> #N/A | CB8: =CB43 -> #N/A | CC8: =CC43 -> #N/A | CD8: =CD43 -> #N/A | CE8: =CE43 -> #N/A | CF8: =CF43 -> #N/A | CG8: =CG43 -> #N/A | CH8: =CH43 -> #N/A | CI8: =CI43 -> #N/A | ... CM8: =CM43 -> #N/A | CN8: =SUM(CB8:CM8) -> #N/A | CO8: =CO43 -> #N/A | CP8: =CP43 -> #N/A | CQ8: =CQ43 -> #N/A | CR8: =CR43 -> #N/A | CS8: =CS43 -> #N/A | CT8: =CT43 -> #N/A | CU8: =CU43 -> #N/A | CV8: =CV43 -> #N/A | ... CZ8: =CZ43 -> #N/A | DA8: =SUM(CO8:CZ8) -> #N/A | DB8: =DB43 -> #N/A | DC8: =DC43 -> #N/A | DD8: =DD43 -> #N/A | DE8: =DE43 -> #N/A | DF8: =DF43 -> #N/A | DG8: =DG43 -> #N/A | DH8: =DH43 -> #N/A | DI8: =DI43 -> #N/A | ... DM8: =DM43 -> #N/A | DN8: =SUM(DB8:DM8) -> #N/A | DO8: =DO43 -> #N/A | DP8: =DP43 -> #N/A | DQ8: =DQ43 -> #N/A | DR8: =DR43 -> #N/A | DS8: =DS43 -> #N/A | DT8: =DT43 -> #N/A | DU8: =DU43 -> #N/A | DV8: =DV43 -> #N/A | ... DZ8: =DZ43 -> #N/A | EA8: =SUM(DO8:DZ8) -> #N/A | EB8: =EB43 -> #N/A | EC8: =EC43 -> #N/A | ED8: =ED43 -> #N/A | EE8: =EE43 -> #N/A | EF8: =EF43 -> #N/A | EG8: =EG43 -> #N/A | EH8: =EH43 -> #N/A | EI8: =EI43 -> #N/A | ... EM8: =EM43 -> #N/A | EN8: =SUM(EB8:EM8) -> #N/A | EO8: =EO43 -> #N/A | EP8: =EP43 -> #N/A | EQ8: =EQ43 -> #N/A | ER8: =ER43 -> #N/A | ES8: =ES43 -> #N/A | ET8: =ET43 -> #N/A | EU8: =EU43 -> #N/A | EV8: =EV43 -> #N/A | ... EZ8: =EZ43 -> #N/A | FA8: =SUM(EO8:EZ8) -> #N/A | FB8: =FB43 -> #N/A | FC8: =FC43 -> #N/A | FD8: =FD43 -> #N/A | FE8: =FE43 -> #N/A | FF8: =FF43 -> #N/A | FG8: =FG43 -> #N/A | FH8: =FH43 -> #N/A | FI8: =FI43 -> #N/A | ... FM8: =FM43 -> #N/A | FN8: =SUM(FB8:FM8) -> #N/A | FO8: =FO43 -> #N/A | FP8: =FP43 -> #N/A | FQ8: =FQ43 -> #N/A | FR8: =FR43 -> #N/A | FS8: =FS43 -> #N/A | FT8: =FT43 -> #N/A | FU8: =FU43 -> #N/A | FV8: =FV43 -> #N/A | ... FZ8: =FZ43 -> #N/A | GA8: =SUM(FO8:FZ8) -> #N/A | GB8: =GB43 -> #N/A | GC8: =GC43 -> #N/A | GD8: =GD43 -> #N/A | GE8: =GE43 -> #N/A | GF8: =GF43 -> #N/A | GG8: =GG43 -> #N/A | GH8: =GH43 -> #N/A | GI8: =GI43 -> #N/A | ... GM8: =GM43 -> #N/A | GN8: =SUM(GB8:GM8) -> #N/A | GO8: =GO43 -> #N/A | GP8: =GP43 -> #N/A | GQ8: =GQ43 -> #N/A | GR8: =GR43 -> #N/A | GS8: =GS43 -> #N/A | GT8: =GT43 -> #N/A | GU8: =GU43 -> #N/A | GV8: =GV43 -> #N/A | ... GZ8: =GZ43 -> #N/A | HA8: =SUM(GO8:GZ8) -> #N/A | HB8: =HB43 -> #N/A | HC8: =HC43 -> #N/A | HD8: =HD43 -> #N/A | HE8: =HE43 -> #N/A | HF8: =HF43 -> #N/A | HG8: =HG43 -> #N/A | HH8: =HH43 -> #N/A | HI8: =HI43 -> #N/A | ... HM8: =HM43 -> #N/A | HN8: =SUM(HB8:HM8) -> #N/A | HO8: =HO43 -> #N/A | HP8: =HP43 -> #N/A | HQ8: =HQ43 -> #N/A | HR8: =HR43 -> #N/A | HS8: =HS43 -> #N/A | HT8: =HT43 -> #N/A | HU8: =HU43 -> #N/A | HV8: =HV43 -> #N/A | ... HZ8: =HZ43 -> #N/A | IA8: =SUM(HO8:HZ8) -> #N/A | IB8: =IB43 -> #N/A | IC8: =IC43 -> #N/A | ID8: =ID43 -> #N/A | IE8: =IE43 -> #N/A | IF8: =IF43 -> #N/A | IG8: =IG43 -> #N/A | IH8: =IH43 -> #N/A | II8: =II43 -> #N/A | ... IM8: =IM43 -> #N/A | IN8: =SUM(IB8:IM8) -> #N/A | IO8: =IO43 -> #N/A | IP8: =IP43 -> #N/A | IQ8: =IQ43 -> #N/A | IR8: =IR43 -> #N/A | IS8: =IS43 -> #N/A | IT8: =IT43 -> #N/A | IU8: =IU43 -> #N/A | IV8: =IV43 -> #N/A | ... IZ8: =IZ43 -> #N/A | JA8: =SUM(IO8:IZ8) -> #N/A | JB8: =JB43 -> #N/A | JC8: =JC43 -> #N/A | JD8: =JD43 -> #N/A | JE8: =JE43 -> #N/A | JF8: =JF43 -> #N/A | JG8: =JG43 -> #N/A | JH8: =JH43 -> #N/A | JI8: =JI43 -> #N/A | ... JM8: =JM43 -> #N/A | JN8: =SUM(JB8:JM8) -> #N/A | JO8: =JO43 -> #N/A | JP8: =JP43 -> #N/A | JQ8: =JQ43 -> #N/A | JR8: =JR43 -> #N/A | JS8: =JS43 -> #N/A | JT8: =JT43 -> #N/A | JU8: =JU43 -> #N/A | JV8: =JV43 -> #N/A | ... JZ8: =JZ43 -> #N/A | KA8: =SUM(JO8:JZ8) -> #N/A | KB8: =KB43 -> #N/A | KC8: =KC43 -> #N/A | KD8: =KD43 -> #N/A | KE8: =KE43 -> #N/A | KF8: =KF43 -> #N/A | KG8: =KG43 -> #N/A | KH8: =KH43 -> #N/A | KI8: =KI43 -> #N/A | ... KM8: =KM43 -> #N/A | KN8: =SUM(KB8:KM8) -> #N/A | KO8: =KO43 -> #N/A | KP8: =KP43 -> #N/A | KQ8: =KQ43 -> #N/A | KR8: =KR43 -> #N/A | KS8: =KS43 -> #N/A | KT8: =KT43 -> #N/A | KU8: =KU43 -> #N/A | KV8: =KV43 -> #N/A | ... KZ8: =KZ43 -> #N/A | LA8: =SUM(KO8:KZ8) -> #N/A | LB8: =LB43 -> #N/A | LC8: =LC43 -> #N/A | LD8: =LD43 -> #N/A | LE8: =LE43 -> #N/A | LF8: =LF43 -> #N/A | LG8: =LG43 -> #N/A | LH8: =LH43 -> #N/A | LI8: =LI43 -> #N/A | ... LM8: =LM43 -> #N/A | LN8: =SUM(LB8:LM8) -> #N/A | LO8: =LO43 -> #N/A | LP8: =LP43 -> #N/A | LQ8: =LQ43 -> #N/A | LR8: =LR43 -> #N/A | LS8: =LS43 -> #N/A | LT8: =LT43 -> #N/A | LU8: =LU43 -> #N/A | LV8: =LV43 -> #N/A | ... LZ8: =LZ43 -> #N/A | MA8: =SUM(LO8:LZ8) -> #N/A | MB8: =MB43 -> #N/A | MC8: =MC43 -> #N/A | MD8: =MD43 -> #N/A | ME8: =ME43 -> #N/A | MF8: =MF43 -> #N/A | MG8: =MG43 -> #N/A | MH8: =MH43 -> #N/A | MI8: =MI43 -> #N/A | ... MM8: =MM43 -> #N/A | MN8: =SUM(MB8:MM8) -> #N/A | MO8: =MO43 -> #N/A | MP8: =MP43 -> #N/A | MQ8: =MQ43 -> #N/A | MR8: =MR43 -> #N/A | MS8: =MS43 -> #N/A | MT8: =MT43 -> #N/A | MU8: =MU43 -> #N/A | MV8: =MV43 -> #N/A | ... MZ8: =MZ43 -> #N/A | NA8: =SUM(MO8:MZ8) -> #N/A | NB8: =NB43 -> #N/A | NC8: =NC43 -> #N/A | ND8: =ND43 -> #N/A | NE8: =NE43 -> #N/A | NF8: =NF43 -> #N/A | NG8: =NG43 -> #N/A | NH8: =NH43 -> #N/A | NI8: =NI43 -> #N/A | ... NM8: =NM43 -> #N/A | NN8: =SUM(NB8:NM8) -> #N/A | NO8: =NO43 -> #N/A | NP8: =NP43 -> #N/A | NQ8: =NQ43 -> #N/A | NR8: =NR43 -> #N/A | NS8: =NS43 -> #N/A | NT8: =NT43 -> #N/A | NU8: =NU43 -> #N/A | NV8: =NV43 -> #N/A | ... NZ8: =NZ43 -> #N/A | OA8: =SUM(NO8:NZ8) -> #N/A | OB8: =OB43 -> #N/A | OC8: =OC43 -> #N/A | OD8: =OD43 -> #N/A | OE8: =OE43 -> #N/A | OF8: =OF43 -> #N/A | OG8: =OG43 -> #N/A | OH8: =OH43 -> #N/A | OI8: =OI43 -> #N/A | ... OM8: =OM43 -> #N/A | ON8: =SUM(OB8:OM8) -> #N/A | OO8: =OO43 -> #N/A | OP8: =OP43 -> #N/A | OQ8: =OQ43 -> #N/A | OR8: =OR43 -> #N/A | OS8: =OS43 -> #N/A | OT8: =OT43 -> #N/A | OU8: =OU43 -> #N/A | OV8: =OV43 -> #N/A | ... OZ8: =OZ43 -> #N/A | PA8: =SUM(OO8:OZ8) -> #N/A | PB8: =PB43 -> #N/A | PC8: =PC43 -> #N/A | PD8: =PD43 -> #N/A | PE8: =PE43 -> #N/A | PF8: =PF43 -> #N/A | PG8: =PG43 -> #N/A | PH8: =PH43 -> #N/A | PI8: =PI43 -> #N/A | ... PM8: =PM43 -> #N/A | PN8: =SUM(PB8:PM8) -> #N/A | PO8: =PO43 -> #N/A | PP8: =PP43 -> #N/A | PQ8: =PQ43 -> #N/A | PR8: =PR43 -> #N/A | PS8: =PS43 -> #N/A | PT8: =PT43 -> #N/A | PU8: =PU43 -> #N/A | PV8: =PV43 -> #N/A | ... PZ8: =PZ43 -> #N/A | QA8: =SUM(PO8:PZ8) -> #N/A | QB8: =QB43 -> #N/A | QC8: =QC43 -> #N/A | QD8: =QD43 -> #N/A | QE8: =QE43 -> #N/A | QF8: =QF43 -> #N/A | QG8: =QG43 -> #N/A | QH8: =QH43 -> #N/A | QI8: =QI43 -> #N/A | ... QM8: =QM43 -> #N/A | QN8: =SUM(QB8:QM8) -> #N/A | QO8: =QO43 -> #N/A | QP8: =QP43 -> #N/A | QQ8: =QQ43 -> #N/A | QR8: =QR43 -> #N/A | QS8: =QS43 -> #N/A | QT8: =QT43 -> #N/A | QU8: =QU43 -> #N/A | QV8: =QV43 -> #N/A | ... QZ8: =QZ43 -> #N/A | RA8: =SUM(QO8:QZ8) -> #N/A | RB8: =RB43 -> #N/A | RC8: =RC43 -> #N/A | RD8: =RD43 -> #N/A | RE8: =RE43 -> #N/A | RF8: =RF43 -> #N/A | RG8: =RG43 -> #N/A | RH8: =RH43 -> #N/A | RI8: =RI43 -> #N/A | ... RM8: =RM43 -> #N/A | RN8: =SUM(RB8:RM8) -> #N/A
A9: Net Income (w/ Appreciation) | B9: =B8 -> #N/A | C9: =C8+(C10-B10) -> #N/A | D9: =D8+(D10-C10) -> #N/A | E9: =E8+(E10-D10) -> #N/A | F9: =F8+(F10-E10) -> #N/A | G9: =G8+(G10-F10) -> #N/A | H9: =H8+(H10-G10) -> #N/A | I9: =I8+(I10-H10) -> #N/A | J9: =J8+(J10-I10) -> #N/A | ... M9: =M8+(M10-L10) -> #N/A | N9: =SUM(B9:M9) -> #N/A | O9: =O8+(O10-M10) -> #N/A | P9: =P8+(P10-O10) -> #N/A | Q9: =Q8+(Q10-P10) -> #N/A | R9: =R8+(R10-Q10) -> #N/A | S9: =S8+(S10-R10) -> #N/A | T9: =T8+(T10-S10) -> #N/A | U9: =U8+(U10-T10) -> #N/A | V9: =V8+(V10-U10) -> #N/A | W9: =W8+(W10-V10) -> #N/A | ... Z9: =Z8+(Z10-Y10) -> #N/A | AA9: =SUM(O9:Z9) -> #N/A | AB9: =AB8+(AB10-Z10) -> #N/A | AC9: =AC8+(AC10-AB10) -> #N/A | AD9: =AD8+(AD10-AC10) -> #N/A | AE9: =AE8+(AE10-AD10) -> #N/A | AF9: =AF8+(AF10-AE10) -> #N/A | AG9: =AG8+(AG10-AF10) -> #N/A | AH9: =AH8+(AH10-AG10) -> #N/A | AI9: =AI8+(AI10-AH10) -> #N/A | AJ9: =AJ8+(AJ10-AI10) -> #N/A | ... AM9: =AM8+(AM10-AL10) -> #N/A | AN9: =SUM(AB9:AM9) -> #N/A | AO9: =AO8+(AO10-AM10) -> #N/A | AP9: =AP8+(AP10-AO10) -> #N/A | AQ9: =AQ8+(AQ10-AP10) -> #N/A | AR9: =AR8+(AR10-AQ10) -> #N/A | AS9: =AS8+(AS10-AR10) -> #N/A | AT9: =AT8+(AT10-AS10) -> #N/A | AU9: =AU8+(AU10-AT10) -> #N/A | AV9: =AV8+(AV10-AU10) -> #N/A | AW9: =AW8+(AW10-AV10) -> #N/A | ... AZ9: =AZ8+(AZ10-AY10) -> #N/A | BA9: =SUM(AO9:AZ9) -> #N/A | BB9: =BB8+(BB10-AZ10) -> #N/A | BC9: =BC8+(BC10-BB10) -> #N/A | BD9: =BD8+(BD10-BC10) -> #N/A | BE9: =BE8+(BE10-BD10) -> #N/A | BF9: =BF8+(BF10-BE10) -> #N/A | BG9: =BG8+(BG10-BF10) -> #N/A | BH9: =BH8+(BH10-BG10) -> #N/A | BI9: =BI8+(BI10-BH10) -> #N/A | BJ9: =BJ8+(BJ10-BI10) -> #N/A | ... BM9: =BM8+(BM10-BL10) -> #N/A | BN9: =SUM(BB9:BM9) -> #N/A | BO9: =BO8+(BO10-BM10) -> #N/A | BP9: =BP8+(BP10-BO10) -> #N/A | BQ9: =BQ8+(BQ10-BP10) -> #N/A | BR9: =BR8+(BR10-BQ10) -> #N/A | BS9: =BS8+(BS10-BR10) -> #N/A | BT9: =BT8+(BT10-BS10) -> #N/A | BU9: =BU8+(BU10-BT10) -> #N/A | BV9: =BV8+(BV10-BU10) -> #N/A | BW9: =BW8+(BW10-BV10) -> #N/A | ... BZ9: =BZ8+(BZ10-BY10) -> #N/A | CA9: =SUM(BO9:BZ9) -> #N/A | CB9: =CB8+(CB10-BZ10) -> #N/A | CC9: =CC8+(CC10-CB10) -> #N/A | CD9: =CD8+(CD10-CC10) -> #N/A | CE9: =CE8+(CE10-CD10) -> #N/A | CF9: =CF8+(CF10-CE10) -> #N/A | CG9: =CG8+(CG10-CF10) -> #N/A | CH9: =CH8+(CH10-CG10) -> #N/A | CI9: =CI8+(CI10-CH10) -> #N/A | CJ9: =CJ8+(CJ10-CI10) -> #N/A | ... CM9: =CM8+(CM10-CL10) -> #N/A | CN9: =SUM(CB9:CM9) -> #N/A | CO9: =CO8+(CO10-CM10) -> #N/A | CP9: =CP8+(CP10-CO10) -> #N/A | CQ9: =CQ8+(CQ10-CP10) -> #N/A | CR9: =CR8+(CR10-CQ10) -> #N/A | CS9: =CS8+(CS10-CR10) -> #N/A | CT9: =CT8+(CT10-CS10) -> #N/A | CU9: =CU8+(CU10-CT10) -> #N/A | CV9: =CV8+(CV10-CU10) -> #N/A | CW9: =CW8+(CW10-CV10) -> #N/A | ... CZ9: =CZ8+(CZ10-CY10) -> #N/A | DA9: =SUM(CO9:CZ9) -> #N/A | DB9: =DB8+(DB10-CZ10) -> #N/A | DC9: =DC8+(DC10-DB10) -> #N/A | DD9: =DD8+(DD10-DC10) -> #N/A | DE9: =DE8+(DE10-DD10) -> #N/A | DF9: =DF8+(DF10-DE10) -> #N/A | DG9: =DG8+(DG10-DF10) -> #N/A | DH9: =DH8+(DH10-DG10) -> #N/A | DI9: =DI8+(DI10-DH10) -> #N/A | DJ9: =DJ8+(DJ10-DI10) -> #N/A | ... DM9: =DM8+(DM10-DL10) -> #N/A | DN9: =SUM(DB9:DM9) -> #N/A | DO9: =DO8+(DO10-DM10) -> #N/A | DP9: =DP8+(DP10-DO10) -> #N/A | DQ9: =DQ8+(DQ10-DP10) -> #N/A | DR9: =DR8+(DR10-DQ10) -> #N/A | DS9: =DS8+(DS10-DR10) -> #N/A | DT9: =DT8+(DT10-DS10) -> #N/A | DU9: =DU8+(DU10-DT10) -> #N/A | DV9: =DV8+(DV10-DU10) -> #N/A | DW9: =DW8+(DW10-DV10) -> #N/A | ... DZ9: =DZ8+(DZ10-DY10) -> #N/A | EA9: =SUM(DO9:DZ9) -> #N/A | EB9: =EB8+(EB10-DZ10) -> #N/A | EC9: =EC8+(EC10-EB10) -> #N/A | ED9: =ED8+(ED10-EC10) -> #N/A | EE9: =EE8+(EE10-ED10) -> #N/A | EF9: =EF8+(EF10-EE10) -> #N/A | EG9: =EG8+(EG10-EF10) -> #N/A | EH9: =EH8+(EH10-EG10) -> #N/A | EI9: =EI8+(EI10-EH10) -> #N/A | EJ9: =EJ8+(EJ10-EI10) -> #N/A | ... EM9: =EM8+(EM10-EL10) -> #N/A | EN9: =SUM(EB9:EM9) -> #N/A | EO9: =EO8+(EO10-EM10) -> #N/A | EP9: =EP8+(EP10-EO10) -> #N/A | EQ9: =EQ8+(EQ10-EP10) -> #N/A | ER9: =ER8+(ER10-EQ10) -> #N/A | ES9: =ES8+(ES10-ER10) -> #N/A | ET9: =ET8+(ET10-ES10) -> #N/A | EU9: =EU8+(EU10-ET10) -> #N/A | EV9: =EV8+(EV10-EU10) -> #N/A | EW9: =EW8+(EW10-EV10) -> #N/A | ... EZ9: =EZ8+(EZ10-EY10) -> #N/A | FA9: =SUM(EO9:EZ9) -> #N/A | FB9: =FB8+(FB10-EZ10) -> #N/A | FC9: =FC8+(FC10-FB10) -> #N/A | FD9: =FD8+(FD10-FC10) -> #N/A | FE9: =FE8+(FE10-FD10) -> #N/A | FF9: =FF8+(FF10-FE10) -> #N/A | FG9: =FG8+(FG10-FF10) -> #N/A | FH9: =FH8+(FH10-FG10) -> #N/A | FI9: =FI8+(FI10-FH10) -> #N/A | FJ9: =FJ8+(FJ10-FI10) -> #N/A | ... FM9: =FM8+(FM10-FL10) -> #N/A | FN9: =SUM(FB9:FM9) -> #N/A | FO9: =FO8+(FO10-FM10) -> #N/A | FP9: =FP8+(FP10-FO10) -> #N/A | FQ9: =FQ8+(FQ10-FP10) -> #N/A | FR9: =FR8+(FR10-FQ10) -> #N/A | FS9: =FS8+(FS10-FR10) -> #N/A | FT9: =FT8+(FT10-FS10) -> #N/A | FU9: =FU8+(FU10-FT10) -> #N/A | FV9: =FV8+(FV10-FU10) -> #N/A | FW9: =FW8+(FW10-FV10) -> #N/A | ... FZ9: =FZ8+(FZ10-FY10) -> #N/A | GA9: =SUM(FO9:FZ9) -> #N/A | GB9: =GB8+(GB10-FZ10) -> #N/A | GC9: =GC8+(GC10-GB10) -> #N/A | GD9: =GD8+(GD10-GC10) -> #N/A | GE9: =GE8+(GE10-GD10) -> #N/A | GF9: =GF8+(GF10-GE10) -> #N/A | GG9: =GG8+(GG10-GF10) -> #N/A | GH9: =GH8+(GH10-GG10) -> #N/A | GI9: =GI8+(GI10-GH10) -> #N/A | GJ9: =GJ8+(GJ10-GI10) -> #N/A | ... GM9: =GM8+(GM10-GL10) -> #N/A | GN9: =SUM(GB9:GM9) -> #N/A | GO9: =GO8+(GO10-GM10) -> #N/A | GP9: =GP8+(GP10-GO10) -> #N/A | GQ9: =GQ8+(GQ10-GP10) -> #N/A | GR9: =GR8+(GR10-GQ10) -> #N/A | GS9: =GS8+(GS10-GR10) -> #N/A | GT9: =GT8+(GT10-GS10) -> #N/A | GU9: =GU8+(GU10-GT10) -> #N/A | GV9: =GV8+(GV10-GU10) -> #N/A | GW9: =GW8+(GW10-GV10) -> #N/A | ... GZ9: =GZ8+(GZ10-GY10) -> #N/A | HA9: =SUM(GO9:GZ9) -> #N/A | HB9: =HB8+(HB10-GZ10) -> #N/A | HC9: =HC8+(HC10-HB10) -> #N/A | HD9: =HD8+(HD10-HC10) -> #N/A | HE9: =HE8+(HE10-HD10) -> #N/A | HF9: =HF8+(HF10-HE10) -> #N/A | HG9: =HG8+(HG10-HF10) -> #N/A | HH9: =HH8+(HH10-HG10) -> #N/A | HI9: =HI8+(HI10-HH10) -> #N/A | HJ9: =HJ8+(HJ10-HI10) -> #N/A | ... HM9: =HM8+(HM10-HL10) -> #N/A | HN9: =SUM(HB9:HM9) -> #N/A | HO9: =HO8+(HO10-HM10) -> #N/A | HP9: =HP8+(HP10-HO10) -> #N/A | HQ9: =HQ8+(HQ10-HP10) -> #N/A | HR9: =HR8+(HR10-HQ10) -> #N/A | HS9: =HS8+(HS10-HR10) -> #N/A | HT9: =HT8+(HT10-HS10) -> #N/A | HU9: =HU8+(HU10-HT10) -> #N/A | HV9: =HV8+(HV10-HU10) -> #N/A | HW9: =HW8+(HW10-HV10) -> #N/A | ... HZ9: =HZ8+(HZ10-HY10) -> #N/A | IA9: =SUM(HO9:HZ9) -> #N/A | IB9: =IB8+(IB10-HZ10) -> #N/A | IC9: =IC8+(IC10-IB10) -> #N/A | ID9: =ID8+(ID10-IC10) -> #N/A | IE9: =IE8+(IE10-ID10) -> #N/A | IF9: =IF8+(IF10-IE10) -> #N/A | IG9: =IG8+(IG10-IF10) -> #N/A | IH9: =IH8+(IH10-IG10) -> #N/A | II9: =II8+(II10-IH10) -> #N/A | IJ9: =IJ8+(IJ10-II10) -> #N/A | ... IM9: =IM8+(IM10-IL10) -> #N/A | IN9: =SUM(IB9:IM9) -> #N/A | IO9: =IO8+(IO10-IM10) -> #N/A | IP9: =IP8+(IP10-IO10) -> #N/A | IQ9: =IQ8+(IQ10-IP10) -> #N/A | IR9: =IR8+(IR10-IQ10) -> #N/A | IS9: =IS8+(IS10-IR10) -> #N/A | IT9: =IT8+(IT10-IS10) -> #N/A | IU9: =IU8+(IU10-IT10) -> #N/A | IV9: =IV8+(IV10-IU10) -> #N/A | IW9: =IW8+(IW10-IV10) -> #N/A | ... IZ9: =IZ8+(IZ10-IY10) -> #N/A | JA9: =SUM(IO9:IZ9) -> #N/A | JB9: =JB8+(JB10-IZ10) -> #N/A | JC9: =JC8+(JC10-JB10) -> #N/A | JD9: =JD8+(JD10-JC10) -> #N/A | JE9: =JE8+(JE10-JD10) -> #N/A | JF9: =JF8+(JF10-JE10) -> #N/A | JG9: =JG8+(JG10-JF10) -> #N/A | JH9: =JH8+(JH10-JG10) -> #N/A | JI9: =JI8+(JI10-JH10) -> #N/A | JJ9: =JJ8+(JJ10-JI10) -> #N/A | ... JM9: =JM8+(JM10-JL10) -> #N/A | JN9: =SUM(JB9:JM9) -> #N/A | JO9: =JO8+(JO10-JM10) -> #N/A | JP9: =JP8+(JP10-JO10) -> #N/A | JQ9: =JQ8+(JQ10-JP10) -> #N/A | JR9: =JR8+(JR10-JQ10) -> #N/A | JS9: =JS8+(JS10-JR10) -> #N/A | JT9: =JT8+(JT10-JS10) -> #N/A | JU9: =JU8+(JU10-JT10) -> #N/A | JV9: =JV8+(JV10-JU10) -> #N/A | JW9: =JW8+(JW10-JV10) -> #N/A | ... JZ9: =JZ8+(JZ10-JY10) -> #N/A | KA9: =SUM(JO9:JZ9) -> #N/A | KB9: =KB8+(KB10-JZ10) -> #N/A | KC9: =KC8+(KC10-KB10) -> #N/A | KD9: =KD8+(KD10-KC10) -> #N/A | KE9: =KE8+(KE10-KD10) -> #N/A | KF9: =KF8+(KF10-KE10) -> #N/A | KG9: =KG8+(KG10-KF10) -> #N/A | KH9: =KH8+(KH10-KG10) -> #N/A | KI9: =KI8+(KI10-KH10) -> #N/A | KJ9: =KJ8+(KJ10-KI10) -> #N/A | ... KM9: =KM8+(KM10-KL10) -> #N/A | KN9: =SUM(KB9:KM9) -> #N/A | KO9: =KO8+(KO10-KM10) -> #N/A | KP9: =KP8+(KP10-KO10) -> #N/A | KQ9: =KQ8+(KQ10-KP10) -> #N/A | KR9: =KR8+(KR10-KQ10) -> #N/A | KS9: =KS8+(KS10-KR10) -> #N/A | KT9: =KT8+(KT10-KS10) -> #N/A | KU9: =KU8+(KU10-KT10) -> #N/A | KV9: =KV8+(KV10-KU10) -> #N/A | KW9: =KW8+(KW10-KV10) -> #N/A | ... KZ9: =KZ8+(KZ10-KY10) -> #N/A | LA9: =SUM(KO9:KZ9) -> #N/A | LB9: =LB8+(LB10-KZ10) -> #N/A | LC9: =LC8+(LC10-LB10) -> #N/A | LD9: =LD8+(LD10-LC10) -> #N/A | LE9: =LE8+(LE10-LD10) -> #N/A | LF9: =LF8+(LF10-LE10) -> #N/A | LG9: =LG8+(LG10-LF10) -> #N/A | LH9: =LH8+(LH10-LG10) -> #N/A | LI9: =LI8+(LI10-LH10) -> #N/A | LJ9: =LJ8+(LJ10-LI10) -> #N/A | ... LM9: =LM8+(LM10-LL10) -> #N/A | LN9: =SUM(LB9:LM9) -> #N/A | LO9: =LO8+(LO10-LM10) -> #N/A | LP9: =LP8+(LP10-LO10) -> #N/A | LQ9: =LQ8+(LQ10-LP10) -> #N/A | LR9: =LR8+(LR10-LQ10) -> #N/A | LS9: =LS8+(LS10-LR10) -> #N/A | LT9: =LT8+(LT10-LS10) -> #N/A | LU9: =LU8+(LU10-LT10) -> #N/A | LV9: =LV8+(LV10-LU10) -> #N/A | LW9: =LW8+(LW10-LV10) -> #N/A | ... LZ9: =LZ8+(LZ10-LY10) -> #N/A | MA9: =SUM(LO9:LZ9) -> #N/A | MB9: =MB8+(MB10-LZ10) -> #N/A | MC9: =MC8+(MC10-MB10) -> #N/A | MD9: =MD8+(MD10-MC10) -> #N/A | ME9: =ME8+(ME10-MD10) -> #N/A | MF9: =MF8+(MF10-ME10) -> #N/A | MG9: =MG8+(MG10-MF10) -> #N/A | MH9: =MH8+(MH10-MG10) -> #N/A | MI9: =MI8+(MI10-MH10) -> #N/A | MJ9: =MJ8+(MJ10-MI10) -> #N/A | ... MM9: =MM8+(MM10-ML10) -> #N/A | MN9: =SUM(MB9:MM9) -> #N/A | MO9: =MO8+(MO10-MM10) -> #N/A | MP9: =MP8+(MP10-MO10) -> #N/A | MQ9: =MQ8+(MQ10-MP10) -> #N/A | MR9: =MR8+(MR10-MQ10) -> #N/A | MS9: =MS8+(MS10-MR10) -> #N/A | MT9: =MT8+(MT10-MS10) -> #N/A | MU9: =MU8+(MU10-MT10) -> #N/A | MV9: =MV8+(MV10-MU10) -> #N/A | MW9: =MW8+(MW10-MV10) -> #N/A | ... MZ9: =MZ8+(MZ10-MY10) -> #N/A | NA9: =SUM(MO9:MZ9) -> #N/A | NB9: =NB8+(NB10-MZ10) -> #N/A | NC9: =NC8+(NC10-NB10) -> #N/A | ND9: =ND8+(ND10-NC10) -> #N/A | NE9: =NE8+(NE10-ND10) -> #N/A | NF9: =NF8+(NF10-NE10) -> #N/A | NG9: =NG8+(NG10-NF10) -> #N/A | NH9: =NH8+(NH10-NG10) -> #N/A | NI9: =NI8+(NI10-NH10) -> #N/A | NJ9: =NJ8+(NJ10-NI10) -> #N/A | ... NM9: =NM8+(NM10-NL10) -> #N/A | NN9: =SUM(NB9:NM9) -> #N/A | NO9: =NO8+(NO10-NM10) -> #N/A | NP9: =NP8+(NP10-NO10) -> #N/A | NQ9: =NQ8+(NQ10-NP10) -> #N/A | NR9: =NR8+(NR10-NQ10) -> #N/A | NS9: =NS8+(NS10-NR10) -> #N/A | NT9: =NT8+(NT10-NS10) -> #N/A | NU9: =NU8+(NU10-NT10) -> #N/A | NV9: =NV8+(NV10-NU10) -> #N/A | NW9: =NW8+(NW10-NV10) -> #N/A | ... NZ9: =NZ8+(NZ10-NY10) -> #N/A | OA9: =SUM(NO9:NZ9) -> #N/A | OB9: =OB8+(OB10-NZ10) -> #N/A | OC9: =OC8+(OC10-OB10) -> #N/A | OD9: =OD8+(OD10-OC10) -> #N/A | OE9: =OE8+(OE10-OD10) -> #N/A | OF9: =OF8+(OF10-OE10) -> #N/A | OG9: =OG8+(OG10-OF10) -> #N/A | OH9: =OH8+(OH10-OG10) -> #N/A | OI9: =OI8+(OI10-OH10) -> #N/A | OJ9: =OJ8+(OJ10-OI10) -> #N/A | ... OM9: =OM8+(OM10-OL10) -> #N/A | ON9: =SUM(OB9:OM9) -> #N/A | OO9: =OO8+(OO10-OM10) -> #N/A | OP9: =OP8+(OP10-OO10) -> #N/A | OQ9: =OQ8+(OQ10-OP10) -> #N/A | OR9: =OR8+(OR10-OQ10) -> #N/A | OS9: =OS8+(OS10-OR10) -> #N/A | OT9: =OT8+(OT10-OS10) -> #N/A | OU9: =OU8+(OU10-OT10) -> #N/A | OV9: =OV8+(OV10-OU10) -> #N/A | OW9: =OW8+(OW10-OV10) -> #N/A | ... OZ9: =OZ8+(OZ10-OY10) -> #N/A | PA9: =SUM(OO9:OZ9) -> #N/A | PB9: =PB8+(PB10-OZ10) -> #N/A | PC9: =PC8+(PC10-PB10) -> #N/A | PD9: =PD8+(PD10-PC10) -> #N/A | PE9: =PE8+(PE10-PD10) -> #N/A | PF9: =PF8+(PF10-PE10) -> #N/A | PG9: =PG8+(PG10-PF10) -> #N/A | PH9: =PH8+(PH10-PG10) -> #N/A | PI9: =PI8+(PI10-PH10) -> #N/A | PJ9: =PJ8+(PJ10-PI10) -> #N/A | ... PM9: =PM8+(PM10-PL10) -> #N/A | PN9: =SUM(PB9:PM9) -> #N/A | PO9: =PO8+(PO10-PM10) -> #N/A | PP9: =PP8+(PP10-PO10) -> #N/A | PQ9: =PQ8+(PQ10-PP10) -> #N/A | PR9: =PR8+(PR10-PQ10) -> #N/A | PS9: =PS8+(PS10-PR10) -> #N/A | PT9: =PT8+(PT10-PS10) -> #N/A | PU9: =PU8+(PU10-PT10) -> #N/A | PV9: =PV8+(PV10-PU10) -> #N/A | PW9: =PW8+(PW10-PV10) -> #N/A | ... PZ9: =PZ8+(PZ10-PY10) -> #N/A | QA9: =SUM(PO9:PZ9) -> #N/A | QB9: =QB8+(QB10-PZ10) -> #N/A | QC9: =QC8+(QC10-QB10) -> #N/A | QD9: =QD8+(QD10-QC10) -> #N/A | QE9: =QE8+(QE10-QD10) -> #N/A | QF9: =QF8+(QF10-QE10) -> #N/A | QG9: =QG8+(QG10-QF10) -> #N/A | QH9: =QH8+(QH10-QG10) -> #N/A | QI9: =QI8+(QI10-QH10) -> #N/A | QJ9: =QJ8+(QJ10-QI10) -> #N/A | ... QM9: =QM8+(QM10-QL10) -> #N/A | QN9: =SUM(QB9:QM9) -> #N/A | QO9: =QO8+(QO10-QM10) -> #N/A | QP9: =QP8+(QP10-QO10) -> #N/A | QQ9: =QQ8+(QQ10-QP10) -> #N/A | QR9: =QR8+(QR10-QQ10) -> #N/A | QS9: =QS8+(QS10-QR10) -> #N/A | QT9: =QT8+(QT10-QS10) -> #N/A | QU9: =QU8+(QU10-QT10) -> #N/A | QV9: =QV8+(QV10-QU10) -> #N/A | QW9: =QW8+(QW10-QV10) -> #N/A | ... QZ9: =QZ8+(QZ10-QY10) -> #N/A | RA9: =SUM(QO9:QZ9) -> #N/A | RB9: =RB8+(RB10-QZ10) -> #N/A | RC9: =RC8+(RC10-RB10) -> #N/A | RD9: =RD8+(RD10-RC10) -> #N/A | RE9: =RE8+(RE10-RD10) -> #N/A | RF9: =RF8+(RF10-RE10) -> #N/A | RG9: =RG8+(RG10-RF10) -> #N/A | RH9: =RH8+(RH10-RG10) -> #N/A | RI9: =RI8+(RI10-RH10) -> #N/A | RJ9: =RJ8+(RJ10-RI10) -> #N/A | ... RM9: =RM8+(RM10-RL10) -> #N/A | RN9: =SUM(RB9:RM9) -> #N/A
A10: Market Value | B10: =B55 -> #N/A | C10: =C55 -> #N/A | D10: =D55 -> #N/A | E10: =E55 -> #N/A | F10: =F55 -> #N/A | G10: =G55 -> #N/A | H10: =H55 -> #N/A | I10: =I55 -> #N/A | ... M10: =M55 -> #N/A | N10: =M10 -> #N/A | O10: =O55 -> #N/A | P10: =P55 -> #N/A | Q10: =Q55 -> #N/A | R10: =R55 -> #N/A | S10: =S55 -> #N/A | T10: =T55 -> #N/A | U10: =U55 -> #N/A | V10: =V55 -> #N/A | ... Z10: =Z55 -> #N/A | AA10: =Z10 -> #N/A | AB10: =AB55 -> #N/A | AC10: =AC55 -> #N/A | AD10: =AD55 -> #N/A | AE10: =AE55 -> #N/A | AF10: =AF55 -> #N/A | AG10: =AG55 -> #N/A | AH10: =AH55 -> #N/A | AI10: =AI55 -> #N/A | ... AM10: =AM55 -> #N/A | AN10: =AM10 -> #N/A | AO10: =AO55 -> #N/A | AP10: =AP55 -> #N/A | AQ10: =AQ55 -> #N/A | AR10: =AR55 -> #N/A | AS10: =AS55 -> #N/A | AT10: =AT55 -> #N/A | AU10: =AU55 -> #N/A | AV10: =AV55 -> #N/A | ... AZ10: =AZ55 -> #N/A | BA10: =AZ10 -> #N/A | BB10: =BB55 -> #N/A | BC10: =BC55 -> #N/A | BD10: =BD55 -> #N/A | BE10: =BE55 -> #N/A | BF10: =BF55 -> #N/A | BG10: =BG55 -> #N/A | BH10: =BH55 -> #N/A | BI10: =BI55 -> #N/A | ... BM10: =BM55 -> #N/A | BN10: =BM10 -> #N/A | BO10: =BO55 -> #N/A | BP10: =BP55 -> #N/A | BQ10: =BQ55 -> #N/A | BR10: =BR55 -> #N/A | BS10: =BS55 -> #N/A | BT10: =BT55 -> #N/A | BU10: =BU55 -> #N/A | BV10: =BV55 -> #N/A | ... BZ10: =BZ55 -> #N/A | CA10: =BZ10 -> #N/A | CB10: =CB55 -> #N/A | CC10: =CC55 -> #N/A | CD10: =CD55 -> #N/A | CE10: =CE55 -> #N/A | CF10: =CF55 -> #N/A | CG10: =CG55 -> #N/A | CH10: =CH55 -> #N/A | CI10: =CI55 -> #N/A | ... CM10: =CM55 -> #N/A | CN10: =CM10 -> #N/A | CO10: =CO55 -> #N/A | CP10: =CP55 -> #N/A | CQ10: =CQ55 -> #N/A | CR10: =CR55 -> #N/A | CS10: =CS55 -> #N/A | CT10: =CT55 -> #N/A | CU10: =CU55 -> #N/A | CV10: =CV55 -> #N/A | ... CZ10: =CZ55 -> #N/A | DA10: =CZ10 -> #N/A | DB10: =DB55 -> #N/A | DC10: =DC55 -> #N/A | DD10: =DD55 -> #N/A | DE10: =DE55 -> #N/A | DF10: =DF55 -> #N/A | DG10: =DG55 -> #N/A | DH10: =DH55 -> #N/A | DI10: =DI55 -> #N/A | ... DM10: =DM55 -> #N/A | DN10: =DM10 -> #N/A | DO10: =DO55 -> #N/A | DP10: =DP55 -> #N/A | DQ10: =DQ55 -> #N/A | DR10: =DR55 -> #N/A | DS10: =DS55 -> #N/A | DT10: =DT55 -> #N/A | DU10: =DU55 -> #N/A | DV10: =DV55 -> #N/A | ... DZ10: =DZ55 -> #N/A | EA10: =DZ10 -> #N/A | EB10: =EB55 -> #N/A | EC10: =EC55 -> #N/A | ED10: =ED55 -> #N/A | EE10: =EE55 -> #N/A | EF10: =EF55 -> #N/A | EG10: =EG55 -> #N/A | EH10: =EH55 -> #N/A | EI10: =EI55 -> #N/A | ... EM10: =EM55 -> #N/A | EN10: =EM10 -> #N/A | EO10: =EO55 -> #N/A | EP10: =EP55 -> #N/A | EQ10: =EQ55 -> #N/A | ER10: =ER55 -> #N/A | ES10: =ES55 -> #N/A | ET10: =ET55 -> #N/A | EU10: =EU55 -> #N/A | EV10: =EV55 -> #N/A | ... EZ10: =EZ55 -> #N/A | FA10: =EZ10 -> #N/A | FB10: =FB55 -> #N/A | FC10: =FC55 -> #N/A | FD10: =FD55 -> #N/A | FE10: =FE55 -> #N/A | FF10: =FF55 -> #N/A | FG10: =FG55 -> #N/A | FH10: =FH55 -> #N/A | FI10: =FI55 -> #N/A | ... FM10: =FM55 -> #N/A | FN10: =FM10 -> #N/A | FO10: =FO55 -> #N/A | FP10: =FP55 -> #N/A | FQ10: =FQ55 -> #N/A | FR10: =FR55 -> #N/A | FS10: =FS55 -> #N/A | FT10: =FT55 -> #N/A | FU10: =FU55 -> #N/A | FV10: =FV55 -> #N/A | ... FZ10: =FZ55 -> #N/A | GA10: =FZ10 -> #N/A | GB10: =GB55 -> #N/A | GC10: =GC55 -> #N/A | GD10: =GD55 -> #N/A | GE10: =GE55 -> #N/A | GF10: =GF55 -> #N/A | GG10: =GG55 -> #N/A | GH10: =GH55 -> #N/A | GI10: =GI55 -> #N/A | ... GM10: =GM55 -> #N/A | GN10: =GM10 -> #N/A | GO10: =GO55 -> #N/A | GP10: =GP55 -> #N/A | GQ10: =GQ55 -> #N/A | GR10: =GR55 -> #N/A | GS10: =GS55 -> #N/A | GT10: =GT55 -> #N/A | GU10: =GU55 -> #N/A | GV10: =GV55 -> #N/A | ... GZ10: =GZ55 -> #N/A | HA10: =GZ10 -> #N/A | HB10: =HB55 -> #N/A | HC10: =HC55 -> #N/A | HD10: =HD55 -> #N/A | HE10: =HE55 -> #N/A | HF10: =HF55 -> #N/A | HG10: =HG55 -> #N/A | HH10: =HH55 -> #N/A | HI10: =HI55 -> #N/A | ... HM10: =HM55 -> #N/A | HN10: =HM10 -> #N/A | HO10: =HO55 -> #N/A | HP10: =HP55 -> #N/A | HQ10: =HQ55 -> #N/A | HR10: =HR55 -> #N/A | HS10: =HS55 -> #N/A | HT10: =HT55 -> #N/A | HU10: =HU55 -> #N/A | HV10: =HV55 -> #N/A | ... HZ10: =HZ55 -> #N/A | IA10: =HZ10 -> #N/A | IB10: =IB55 -> #N/A | IC10: =IC55 -> #N/A | ID10: =ID55 -> #N/A | IE10: =IE55 -> #N/A | IF10: =IF55 -> #N/A | IG10: =IG55 -> #N/A | IH10: =IH55 -> #N/A | II10: =II55 -> #N/A | ... IM10: =IM55 -> #N/A | IN10: =IM10 -> #N/A | IO10: =IO55 -> #N/A | IP10: =IP55 -> #N/A | IQ10: =IQ55 -> #N/A | IR10: =IR55 -> #N/A | IS10: =IS55 -> #N/A | IT10: =IT55 -> #N/A | IU10: =IU55 -> #N/A | IV10: =IV55 -> #N/A | ... IZ10: =IZ55 -> #N/A | JA10: =IZ10 -> #N/A | JB10: =JB55 -> #N/A | JC10: =JC55 -> #N/A | JD10: =JD55 -> #N/A | JE10: =JE55 -> #N/A | JF10: =JF55 -> #N/A | JG10: =JG55 -> #N/A | JH10: =JH55 -> #N/A | JI10: =JI55 -> #N/A | ... JM10: =JM55 -> #N/A | JN10: =JM10 -> #N/A | JO10: =JO55 -> #N/A | JP10: =JP55 -> #N/A | JQ10: =JQ55 -> #N/A | JR10: =JR55 -> #N/A | JS10: =JS55 -> #N/A | JT10: =JT55 -> #N/A | JU10: =JU55 -> #N/A | JV10: =JV55 -> #N/A | ... JZ10: =JZ55 -> #N/A | KA10: =JZ10 -> #N/A | KB10: =KB55 -> #N/A | KC10: =KC55 -> #N/A | KD10: =KD55 -> #N/A | KE10: =KE55 -> #N/A | KF10: =KF55 -> #N/A | KG10: =KG55 -> #N/A | KH10: =KH55 -> #N/A | KI10: =KI55 -> #N/A | ... KM10: =KM55 -> #N/A | KN10: =KM10 -> #N/A | KO10: =KO55 -> #N/A | KP10: =KP55 -> #N/A | KQ10: =KQ55 -> #N/A | KR10: =KR55 -> #N/A | KS10: =KS55 -> #N/A | KT10: =KT55 -> #N/A | KU10: =KU55 -> #N/A | KV10: =KV55 -> #N/A | ... KZ10: =KZ55 -> #N/A | LA10: =KZ10 -> #N/A | LB10: =LB55 -> #N/A | LC10: =LC55 -> #N/A | LD10: =LD55 -> #N/A | LE10: =LE55 -> #N/A | LF10: =LF55 -> #N/A | LG10: =LG55 -> #N/A | LH10: =LH55 -> #N/A | LI10: =LI55 -> #N/A | ... LM10: =LM55 -> #N/A | LN10: =LM10 -> #N/A | LO10: =LO55 -> #N/A | LP10: =LP55 -> #N/A | LQ10: =LQ55 -> #N/A | LR10: =LR55 -> #N/A | LS10: =LS55 -> #N/A | LT10: =LT55 -> #N/A | LU10: =LU55 -> #N/A | LV10: =LV55 -> #N/A | ... LZ10: =LZ55 -> #N/A | MA10: =LZ10 -> #N/A | MB10: =MB55 -> #N/A | MC10: =MC55 -> #N/A | MD10: =MD55 -> #N/A | ME10: =ME55 -> #N/A | MF10: =MF55 -> #N/A | MG10: =MG55 -> #N/A | MH10: =MH55 -> #N/A | MI10: =MI55 -> #N/A | ... MM10: =MM55 -> #N/A | MN10: =MM10 -> #N/A | MO10: =MO55 -> #N/A | MP10: =MP55 -> #N/A | MQ10: =MQ55 -> #N/A | MR10: =MR55 -> #N/A | MS10: =MS55 -> #N/A | MT10: =MT55 -> #N/A | MU10: =MU55 -> #N/A | MV10: =MV55 -> #N/A | ... MZ10: =MZ55 -> #N/A | NA10: =MZ10 -> #N/A | NB10: =NB55 -> #N/A | NC10: =NC55 -> #N/A | ND10: =ND55 -> #N/A | NE10: =NE55 -> #N/A | NF10: =NF55 -> #N/A | NG10: =NG55 -> #N/A | NH10: =NH55 -> #N/A | NI10: =NI55 -> #N/A | ... NM10: =NM55 -> #N/A | NN10: =NM10 -> #N/A | NO10: =NO55 -> #N/A | NP10: =NP55 -> #N/A | NQ10: =NQ55 -> #N/A | NR10: =NR55 -> #N/A | NS10: =NS55 -> #N/A | NT10: =NT55 -> #N/A | NU10: =NU55 -> #N/A | NV10: =NV55 -> #N/A | ... NZ10: =NZ55 -> #N/A | OA10: =NZ10 -> #N/A | OB10: =OB55 -> #N/A | OC10: =OC55 -> #N/A | OD10: =OD55 -> #N/A | OE10: =OE55 -> #N/A | OF10: =OF55 -> #N/A | OG10: =OG55 -> #N/A | OH10: =OH55 -> #N/A | OI10: =OI55 -> #N/A | ... OM10: =OM55 -> #N/A | ON10: =OM10 -> #N/A | OO10: =OO55 -> #N/A | OP10: =OP55 -> #N/A | OQ10: =OQ55 -> #N/A | OR10: =OR55 -> #N/A | OS10: =OS55 -> #N/A | OT10: =OT55 -> #N/A | OU10: =OU55 -> #N/A | OV10: =OV55 -> #N/A | ... OZ10: =OZ55 -> #N/A | PA10: =OZ10 -> #N/A | PB10: =PB55 -> #N/A | PC10: =PC55 -> #N/A | PD10: =PD55 -> #N/A | PE10: =PE55 -> #N/A | PF10: =PF55 -> #N/A | PG10: =PG55 -> #N/A | PH10: =PH55 -> #N/A | PI10: =PI55 -> #N/A | ... PM10: =PM55 -> #N/A | PN10: =PM10 -> #N/A | PO10: =PO55 -> #N/A | PP10: =PP55 -> #N/A | PQ10: =PQ55 -> #N/A | PR10: =PR55 -> #N/A | PS10: =PS55 -> #N/A | PT10: =PT55 -> #N/A | PU10: =PU55 -> #N/A | PV10: =PV55 -> #N/A | ... PZ10: =PZ55 -> #N/A | QA10: =PZ10 -> #N/A | QB10: =QB55 -> #N/A | QC10: =QC55 -> #N/A | QD10: =QD55 -> #N/A | QE10: =QE55 -> #N/A | QF10: =QF55 -> #N/A | QG10: =QG55 -> #N/A | QH10: =QH55 -> #N/A | QI10: =QI55 -> #N/A | ... QM10: =QM55 -> #N/A | QN10: =QM10 -> #N/A | QO10: =QO55 -> #N/A | QP10: =QP55 -> #N/A | QQ10: =QQ55 -> #N/A | QR10: =QR55 -> #N/A | QS10: =QS55 -> #N/A | QT10: =QT55 -> #N/A | QU10: =QU55 -> #N/A | QV10: =QV55 -> #N/A | ... QZ10: =QZ55 -> #N/A | RA10: =QZ10 -> #N/A | RB10: =RB55 -> #N/A | RC10: =RC55 -> #N/A | RD10: =RD55 -> #N/A | RE10: =RE55 -> #N/A | RF10: =RF55 -> #N/A | RG10: =RG55 -> #N/A | RH10: =RH55 -> #N/A | RI10: =RI55 -> #N/A | ... RM10: =RM55 -> #N/A | RN10: =RM10 -> #N/A
A11: Equity | B11: =B61 -> #N/A | C11: =C61 -> #N/A | D11: =D61 -> #N/A | E11: =E61 -> #N/A | F11: =F61 -> #N/A | G11: =G61 -> #N/A | H11: =H61 -> #N/A | I11: =I61 -> #N/A | ... RN11: =RN61 -> #N/A
A12: Return on Equity | N12: =IFERROR(N11/(Inputs!$B$11*(1-Inputs!$B$12)-Inputs!$B$27)-1,"") | AA12: =AA11/N11-1 -> #N/A | AN12: =AN11/AA11-1 -> #N/A | BA12: =BA11/AN11-1 -> #N/A | BN12: =BN11/BA11-1 -> #N/A | CA12: =CA11/BN11-1 -> #N/A | CN12: =CN11/CA11-1 -> #N/A | DA12: =DA11/CN11-1 -> #N/A | DN12: =DN11/DA11-1 -> #N/A | EA12: =EA11/DN11-1 -> #N/A | EN12: =EN11/EA11-1 -> #N/A | FA12: =FA11/EN11-1 -> #N/A | FN12: =FN11/FA11-1 -> #N/A | GA12: =GA11/FN11-1 -> #N/A | GN12: =GN11/GA11-1 -> #N/A | HA12: =HA11/GN11-1 -> #N/A | HN12: =HN11/HA11-1 -> #N/A | IA12: =IA11/HN11-1 -> #N/A | IN12: =IN11/IA11-1 -> #N/A | JA12: =JA11/IN11-1 -> #N/A | JN12: =JN11/JA11-1 -> #N/A | KA12: =KA11/JN11-1 -> #N/A | KN12: =KN11/KA11-1 -> #N/A | LA12: =LA11/KN11-1 -> #N/A | LN12: =LN11/LA11-1 -> #N/A | MA12: =MA11/LN11-1 -> #N/A | MN12: =MN11/MA11-1 -> #N/A | NA12: =NA11/MN11-1 -> #N/A | NN12: =NN11/NA11-1 -> #N/A | OA12: =OA11/NN11-1 -> #N/A | ON12: =ON11/OA11-1 -> #N/A | PA12: =PA11/ON11-1 -> #N/A | PN12: =PN11/PA11-1 -> #N/A | QA12: =QA11/PN11-1 -> #N/A | QN12: =QN11/QA11-1 -> #N/A | RA12: =RA11/QN11-1 -> #N/A | RN12: =RN11/RA11-1 -> #N/A
A13: Cash on Cash Return | N13: =IFERROR(IF((Inputs!$B$11*(1-Inputs!$B$12)-Inputs!$B$27+N7)>0,N$5/(Inputs!$B$11*(1-Inputs!$B$12)-Inputs!$B$27+N7),""),"") | AA13: =IFERROR(IF((Inputs!$B$11*(1-Inputs!$B$12)-Inputs!$B$27+AA7)>0,AA$5/(Inputs!$B$11*(1-Inputs!$B$12)-Inputs!$B$27+AA7),""),"") | AN13: =IFERROR(IF((Inputs!$B$11*(1-Inputs!$B$12)-Inputs!$B$27+AN7)>0,AN$5/(Inputs!$B$11*(1-Inputs!$B$12)-Inputs!$B$27+AN7),""),"") | BA13: =IFERROR(IF((Inputs!$B$11*(1-Inputs!$B$12)-Inputs!$B$27+BA7)>0,BA$5/(Inputs!$B$11*(1-Inputs!$B$12)-Inputs!$B$27+BA7),""),"") | BN13: =IFERROR(IF((Inputs!$B$11*(1-Inputs!$B$12)-Inputs!$B$27+BN7)>0,BN$5/(Inputs!$B$11*(1-Inputs!$B$12)-Inputs!$B$27+BN7),""),"") | CA13: =IFERROR(IF((Inputs!$B$11*(1-Inputs!$B$12)-Inputs!$B$27+CA7)>0,CA$5/(Inputs!$B$11*(1-Inputs!$B$12)-Inputs!$B$27+CA7),""),"") | CN13: =IFERROR(IF((Inputs!$B$11*(1-Inputs!$B$12)-Inputs!$B$27+CN7)>0,CN$5/(Inputs!$B$11*(1-Inputs!$B$12)-Inputs!$B$27+CN7),""),"") | DA13: =IFERROR(IF((Inputs!$B$11*(1-Inputs!$B$12)-Inputs!$B$27+DA7)>0,DA$5/(Inputs!$B$11*(1-Inputs!$B$12)-Inputs!$B$27+DA7),""),"") | DN13: =IFERROR(IF((Inputs!$B$11*(1-Inputs!$B$12)-Inputs!$B$27+DN7)>0,DN$5/(Inputs!$B$11*(1-Inputs!$B$12)-Inputs!$B$27+DN7),""),"") | EA13: =IFERROR(IF((Inputs!$B$11*(1-Inputs!$B$12)-Inputs!$B$27+EA7)>0,EA$5/(Inputs!$B$11*(1-Inputs!$B$12)-Inputs!$B$27+EA7),""),"") | EN13: =IFERROR(IF((Inputs!$B$11*(1-Inputs!$B$12)-Inputs!$B$27+EN7)>0,EN$5/(Inputs!$B$11*(1-Inputs!$B$12)-Inputs!$B$27+EN7),""),"") | FA13: =IFERROR(IF((Inputs!$B$11*(1-Inputs!$B$12)-Inputs!$B$27+FA7)>0,FA$5/(Inputs!$B$11*(1-Inputs!$B$12)-Inputs!$B$27+FA7),""),"") | FN13: =IFERROR(IF((Inputs!$B$11*(1-Inputs!$B$12)-Inputs!$B$27+FN7)>0,FN$5/(Inputs!$B$11*(1-Inputs!$B$12)-Inputs!$B$27+FN7),""),"") | GA13: =IFERROR(IF((Inputs!$B$11*(1-Inputs!$B$12)-Inputs!$B$27+GA7)>0,GA$5/(Inputs!$B$11*(1-Inputs!$B$12)-Inputs!$B$27+GA7),""),"") | GN13: =IFERROR(IF((Inputs!$B$11*(1-Inputs!$B$12)-Inputs!$B$27+GN7)>0,GN$5/(Inputs!$B$11*(1-Inputs!$B$12)-Inputs!$B$27+GN7),""),"") | HA13: =IFERROR(IF((Inputs!$B$11*(1-Inputs!$B$12)-Inputs!$B$27+HA7)>0,HA$5/(Inputs!$B$11*(1-Inputs!$B$12)-Inputs!$B$27+HA7),""),"") | HN13: =IFERROR(IF((Inputs!$B$11*(1-Inputs!$B$12)-Inputs!$B$27+HN7)>0,HN$5/(Inputs!$B$11*(1-Inputs!$B$12)-Inputs!$B$27+HN7),""),"") | IA13: =IFERROR(IF((Inputs!$B$11*(1-Inputs!$B$12)-Inputs!$B$27+IA7)>0,IA$5/(Inputs!$B$11*(1-Inputs!$B$12)-Inputs!$B$27+IA7),""),"") | IN13: =IFERROR(IF((Inputs!$B$11*(1-Inputs!$B$12)-Inputs!$B$27+IN7)>0,IN$5/(Inputs!$B$11*(1-Inputs!$B$12)-Inputs!$B$27+IN7),""),"") | JA13: =IFERROR(IF((Inputs!$B$11*(1-Inputs!$B$12)-Inputs!$B$27+JA7)>0,JA$5/(Inputs!$B$11*(1-Inputs!$B$12)-Inputs!$B$27+JA7),""),"") | JN13: =IFERROR(IF((Inputs!$B$11*(1-Inputs!$B$12)-Inputs!$B$27+JN7)>0,JN$5/(Inputs!$B$11*(1-Inputs!$B$12)-Inputs!$B$27+JN7),""),"") | KA13: =IFERROR(IF((Inputs!$B$11*(1-Inputs!$B$12)-Inputs!$B$27+KA7)>0,KA$5/(Inputs!$B$11*(1-Inputs!$B$12)-Inputs!$B$27+KA7),""),"") | KN13: =IFERROR(IF((Inputs!$B$11*(1-Inputs!$B$12)-Inputs!$B$27+KN7)>0,KN$5/(Inputs!$B$11*(1-Inputs!$B$12)-Inputs!$B$27+KN7),""),"") | LA13: =IFERROR(IF((Inputs!$B$11*(1-Inputs!$B$12)-Inputs!$B$27+LA7)>0,LA$5/(Inputs!$B$11*(1-Inputs!$B$12)-Inputs!$B$27+LA7),""),"") | LN13: =IFERROR(IF((Inputs!$B$11*(1-Inputs!$B$12)-Inputs!$B$27+LN7)>0,LN$5/(Inputs!$B$11*(1-Inputs!$B$12)-Inputs!$B$27+LN7),""),"") | MA13: =IFERROR(IF((Inputs!$B$11*(1-Inputs!$B$12)-Inputs!$B$27+MA7)>0,MA$5/(Inputs!$B$11*(1-Inputs!$B$12)-Inputs!$B$27+MA7),""),"") | MN13: =IFERROR(IF((Inputs!$B$11*(1-Inputs!$B$12)-Inputs!$B$27+MN7)>0,MN$5/(Inputs!$B$11*(1-Inputs!$B$12)-Inputs!$B$27+MN7),""),"") | NA13: =IFERROR(IF((Inputs!$B$11*(1-Inputs!$B$12)-Inputs!$B$27+NA7)>0,NA$5/(Inputs!$B$11*(1-Inputs!$B$12)-Inputs!$B$27+NA7),""),"") | NN13: =IFERROR(IF((Inputs!$B$11*(1-Inputs!$B$12)-Inputs!$B$27+NN7)>0,NN$5/(Inputs!$B$11*(1-Inputs!$B$12)-Inputs!$B$27+NN7),""),"") | OA13: =IFERROR(IF((Inputs!$B$11*(1-Inputs!$B$12)-Inputs!$B$27+OA7)>0,OA$5/(Inputs!$B$11*(1-Inputs!$B$12)-Inputs!$B$27+OA7),""),"") | ON13: =IFERROR(IF((Inputs!$B$11*(1-Inputs!$B$12)-Inputs!$B$27+ON7)>0,ON$5/(Inputs!$B$11*(1-Inputs!$B$12)-Inputs!$B$27+ON7),""),"") | PA13: =IFERROR(IF((Inputs!$B$11*(1-Inputs!$B$12)-Inputs!$B$27+PA7)>0,PA$5/(Inputs!$B$11*(1-Inputs!$B$12)-Inputs!$B$27+PA7),""),"") | PN13: =IFERROR(IF((Inputs!$B$11*(1-Inputs!$B$12)-Inputs!$B$27+PN7)>0,PN$5/(Inputs!$B$11*(1-Inputs!$B$12)-Inputs!$B$27+PN7),""),"") | QA13: =IFERROR(IF((Inputs!$B$11*(1-Inputs!$B$12)-Inputs!$B$27+QA7)>0,QA$5/(Inputs!$B$11*(1-Inputs!$B$12)-Inputs!$B$27+QA7),""),"") | QN13: =IFERROR(IF((Inputs!$B$11*(1-Inputs!$B$12)-Inputs!$B$27+QN7)>0,QN$5/(Inputs!$B$11*(1-Inputs!$B$12)-Inputs!$B$27+QN7),""),"") | RA13: =IFERROR(IF((Inputs!$B$11*(1-Inputs!$B$12)-Inputs!$B$27+RA7)>0,RA$5/(Inputs!$B$11*(1-Inputs!$B$12)-Inputs!$B$27+RA7),""),"") | RN13: =IFERROR(IF((Inputs!$B$11*(1-Inputs!$B$12)-Inputs!$B$27+RN7)>0,RN$5/(Inputs!$B$11*(1-Inputs!$B$12)-Inputs!$B$27+RN7),""),"")
A15: INCOME STATEMENT
A16: Gross Rental Income | B16: =Inputs!$B$6/12 -> #N/A | C16: =B16 -> #N/A | D16: =C16 -> #N/A | E16: =D16 -> #N/A | F16: =E16 -> #N/A | G16: =F16 -> #N/A | H16: =G16 -> #N/A | I16: =H16 -> #N/A | J16: =I16 -> #N/A | ... M16: =L16 -> #N/A | N16: =SUM(B16:M16) -> #N/A | O16: =M16*(1+Inputs!$B$7) -> #N/A | P16: =O16 -> #N/A | Q16: =P16 -> #N/A | R16: =Q16 -> #N/A | S16: =R16 -> #N/A | T16: =S16 -> #N/A | U16: =T16 -> #N/A | V16: =U16 -> #N/A | W16: =V16 -> #N/A | ... Z16: =Y16 -> #N/A | AA16: =SUM(O16:Z16) -> #N/A | AB16: =Z16*(1+Inputs!$B$7) -> #N/A | AC16: =AB16 -> #N/A | AD16: =AC16 -> #N/A | AE16: =AD16 -> #N/A | AF16: =AE16 -> #N/A | AG16: =AF16 -> #N/A | AH16: =AG16 -> #N/A | AI16: =AH16 -> #N/A | AJ16: =AI16 -> #N/A | ... AM16: =AL16 -> #N/A | AN16: =SUM(AB16:AM16) -> #N/A | AO16: =AM16*(1+Inputs!$B$7) -> #N/A | AP16: =AO16 -> #N/A | AQ16: =AP16 -> #N/A | AR16: =AQ16 -> #N/A | AS16: =AR16 -> #N/A | AT16: =AS16 -> #N/A | AU16: =AT16 -> #N/A | AV16: =AU16 -> #N/A | AW16: =AV16 -> #N/A | ... AZ16: =AY16 -> #N/A | BA16: =SUM(AO16:AZ16) -> #N/A | BB16: =AZ16*(1+Inputs!$B$7) -> #N/A | BC16: =BB16 -> #N/A | BD16: =BC16 -> #N/A | BE16: =BD16 -> #N/A | BF16: =BE16 -> #N/A | BG16: =BF16 -> #N/A | BH16: =BG16 -> #N/A | BI16: =BH16 -> #N/A | BJ16: =BI16 -> #N/A | ... BM16: =BL16 -> #N/A | BN16: =SUM(BB16:BM16) -> #N/A | BO16: =BM16*(1+Inputs!$B$7) -> #N/A | BP16: =BO16 -> #N/A | BQ16: =BP16 -> #N/A | BR16: =BQ16 -> #N/A | BS16: =BR16 -> #N/A | BT16: =BS16 -> #N/A | BU16: =BT16 -> #N/A | BV16: =BU16 -> #N/A | BW16: =BV16 -> #N/A | ... BZ16: =BY16 -> #N/A | CA16: =SUM(BO16:BZ16) -> #N/A | CB16: =BZ16*(1+Inputs!$B$7) -> #N/A | CC16: =CB16 -> #N/A | CD16: =CC16 -> #N/A | CE16: =CD16 -> #N/A | CF16: =CE16 -> #N/A | CG16: =CF16 -> #N/A | CH16: =CG16 -> #N/A | CI16: =CH16 -> #N/A | CJ16: =CI16 -> #N/A | ... CM16: =CL16 -> #N/A | CN16: =SUM(CB16:CM16) -> #N/A | CO16: =CM16*(1+Inputs!$B$7) -> #N/A | CP16: =CO16 -> #N/A | CQ16: =CP16 -> #N/A | CR16: =CQ16 -> #N/A | CS16: =CR16 -> #N/A | CT16: =CS16 -> #N/A | CU16: =CT16 -> #N/A | CV16: =CU16 -> #N/A | CW16: =CV16 -> #N/A | ... CZ16: =CY16 -> #N/A | DA16: =SUM(CO16:CZ16) -> #N/A | DB16: =CZ16*(1+Inputs!$B$7) -> #N/A | DC16: =DB16 -> #N/A | DD16: =DC16 -> #N/A | DE16: =DD16 -> #N/A | DF16: =DE16 -> #N/A | DG16: =DF16 -> #N/A | DH16: =DG16 -> #N/A | DI16: =DH16 -> #N/A | DJ16: =DI16 -> #N/A | ... DM16: =DL16 -> #N/A | DN16: =SUM(DB16:DM16) -> #N/A | DO16: =DM16*(1+Inputs!$B$7) -> #N/A | DP16: =DO16 -> #N/A | DQ16: =DP16 -> #N/A | DR16: =DQ16 -> #N/A | DS16: =DR16 -> #N/A | DT16: =DS16 -> #N/A | DU16: =DT16 -> #N/A | DV16: =DU16 -> #N/A | DW16: =DV16 -> #N/A | ... DZ16: =DY16 -> #N/A | EA16: =SUM(DO16:DZ16) -> #N/A | EB16: =DZ16*(1+Inputs!$B$7) -> #N/A | EC16: =EB16 -> #N/A | ED16: =EC16 -> #N/A | EE16: =ED16 -> #N/A | EF16: =EE16 -> #N/A | EG16: =EF16 -> #N/A | EH16: =EG16 -> #N/A | EI16: =EH16 -> #N/A | EJ16: =EI16 -> #N/A | ... EM16: =EL16 -> #N/A | EN16: =SUM(EB16:EM16) -> #N/A | EO16: =EM16*(1+Inputs!$B$7) -> #N/A | EP16: =EO16 -> #N/A | EQ16: =EP16 -> #N/A | ER16: =EQ16 -> #N/A | ES16: =ER16 -> #N/A | ET16: =ES16 -> #N/A | EU16: =ET16 -> #N/A | EV16: =EU16 -> #N/A | EW16: =EV16 -> #N/A | ... EZ16: =EY16 -> #N/A | FA16: =SUM(EO16:EZ16) -> #N/A | FB16: =EZ16*(1+Inputs!$B$7) -> #N/A | FC16: =FB16 -> #N/A | FD16: =FC16 -> #N/A | FE16: =FD16 -> #N/A | FF16: =FE16 -> #N/A | FG16: =FF16 -> #N/A | FH16: =FG16 -> #N/A | FI16: =FH16 -> #N/A | FJ16: =FI16 -> #N/A | ... FM16: =FL16 -> #N/A | FN16: =SUM(FB16:FM16) -> #N/A | FO16: =FM16*(1+Inputs!$B$7) -> #N/A | FP16: =FO16 -> #N/A | FQ16: =FP16 -> #N/A | FR16: =FQ16 -> #N/A | FS16: =FR16 -> #N/A | FT16: =FS16 -> #N/A | FU16: =FT16 -> #N/A | FV16: =FU16 -> #N/A | FW16: =FV16 -> #N/A | ... FZ16: =FY16 -> #N/A | GA16: =SUM(FO16:FZ16) -> #N/A | GB16: =FZ16*(1+Inputs!$B$7) -> #N/A | GC16: =GB16 -> #N/A | GD16: =GC16 -> #N/A | GE16: =GD16 -> #N/A | GF16: =GE16 -> #N/A | GG16: =GF16 -> #N/A | GH16: =GG16 -> #N/A | GI16: =GH16 -> #N/A | GJ16: =GI16 -> #N/A | ... GM16: =GL16 -> #N/A | GN16: =SUM(GB16:GM16) -> #N/A | GO16: =GM16*(1+Inputs!$B$7) -> #N/A | GP16: =GO16 -> #N/A | GQ16: =GP16 -> #N/A | GR16: =GQ16 -> #N/A | GS16: =GR16 -> #N/A | GT16: =GS16 -> #N/A | GU16: =GT16 -> #N/A | GV16: =GU16 -> #N/A | GW16: =GV16 -> #N/A | ... GZ16: =GY16 -> #N/A | HA16: =SUM(GO16:GZ16) -> #N/A | HB16: =GZ16*(1+Inputs!$B$7) -> #N/A | HC16: =HB16 -> #N/A | HD16: =HC16 -> #N/A | HE16: =HD16 -> #N/A | HF16: =HE16 -> #N/A | HG16: =HF16 -> #N/A | HH16: =HG16 -> #N/A | HI16: =HH16 -> #N/A | HJ16: =HI16 -> #N/A | ... HM16: =HL16 -> #N/A | HN16: =SUM(HB16:HM16) -> #N/A | HO16: =HM16*(1+Inputs!$B$7) -> #N/A | HP16: =HO16 -> #N/A | HQ16: =HP16 -> #N/A | HR16: =HQ16 -> #N/A | HS16: =HR16 -> #N/A | HT16: =HS16 -> #N/A | HU16: =HT16 -> #N/A | HV16: =HU16 -> #N/A | HW16: =HV16 -> #N/A | ... HZ16: =HY16 -> #N/A | IA16: =SUM(HO16:HZ16) -> #N/A | IB16: =HZ16*(1+Inputs!$B$7) -> #N/A | IC16: =IB16 -> #N/A | ID16: =IC16 -> #N/A | IE16: =ID16 -> #N/A | IF16: =IE16 -> #N/A | IG16: =IF16 -> #N/A | IH16: =IG16 -> #N/A | II16: =IH16 -> #N/A | IJ16: =II16 -> #N/A | ... IM16: =IL16 -> #N/A | IN16: =SUM(IB16:IM16) -> #N/A | IO16: =IM16*(1+Inputs!$B$7) -> #N/A | IP16: =IO16 -> #N/A | IQ16: =IP16 -> #N/A | IR16: =IQ16 -> #N/A | IS16: =IR16 -> #N/A | IT16: =IS16 -> #N/A | IU16: =IT16 -> #N/A | IV16: =IU16 -> #N/A | IW16: =IV16 -> #N/A | ... IZ16: =IY16 -> #N/A | JA16: =SUM(IO16:IZ16) -> #N/A | JB16: =IZ16*(1+Inputs!$B$7) -> #N/A | JC16: =JB16 -> #N/A | JD16: =JC16 -> #N/A | JE16: =JD16 -> #N/A | JF16: =JE16 -> #N/A | JG16: =JF16 -> #N/A | JH16: =JG16 -> #N/A | JI16: =JH16 -> #N/A | JJ16: =JI16 -> #N/A | ... JM16: =JL16 -> #N/A | JN16: =SUM(JB16:JM16) -> #N/A | JO16: =JM16*(1+Inputs!$B$7) -> #N/A | JP16: =JO16 -> #N/A | JQ16: =JP16 -> #N/A | JR16: =JQ16 -> #N/A | JS16: =JR16 -> #N/A | JT16: =JS16 -> #N/A | JU16: =JT16 -> #N/A | JV16: =JU16 -> #N/A | JW16: =JV16 -> #N/A | ... JZ16: =JY16 -> #N/A | KA16: =SUM(JO16:JZ16) -> #N/A | KB16: =JZ16*(1+Inputs!$B$7) -> #N/A | KC16: =KB16 -> #N/A | KD16: =KC16 -> #N/A | KE16: =KD16 -> #N/A | KF16: =KE16 -> #N/A | KG16: =KF16 -> #N/A | KH16: =KG16 -> #N/A | KI16: =KH16 -> #N/A | KJ16: =KI16 -> #N/A | ... KM16: =KL16 -> #N/A | KN16: =SUM(KB16:KM16) -> #N/A | KO16: =KM16*(1+Inputs!$B$7) -> #N/A | KP16: =KO16 -> #N/A | KQ16: =KP16 -> #N/A | KR16: =KQ16 -> #N/A | KS16: =KR16 -> #N/A | KT16: =KS16 -> #N/A | KU16: =KT16 -> #N/A | KV16: =KU16 -> #N/A | KW16: =KV16 -> #N/A | ... KZ16: =KY16 -> #N/A | LA16: =SUM(KO16:KZ16) -> #N/A | LB16: =KZ16*(1+Inputs!$B$7) -> #N/A | LC16: =LB16 -> #N/A | LD16: =LC16 -> #N/A | LE16: =LD16 -> #N/A | LF16: =LE16 -> #N/A | LG16: =LF16 -> #N/A | LH16: =LG16 -> #N/A | LI16: =LH16 -> #N/A | LJ16: =LI16 -> #N/A | ... LM16: =LL16 -> #N/A | LN16: =SUM(LB16:LM16) -> #N/A | LO16: =LM16*(1+Inputs!$B$7) -> #N/A | LP16: =LO16 -> #N/A | LQ16: =LP16 -> #N/A | LR16: =LQ16 -> #N/A | LS16: =LR16 -> #N/A | LT16: =LS16 -> #N/A | LU16: =LT16 -> #N/A | LV16: =LU16 -> #N/A | LW16: =LV16 -> #N/A | ... LZ16: =LY16 -> #N/A | MA16: =SUM(LO16:LZ16) -> #N/A | MB16: =LZ16*(1+Inputs!$B$7) -> #N/A | MC16: =MB16 -> #N/A | MD16: =MC16 -> #N/A | ME16: =MD16 -> #N/A | MF16: =ME16 -> #N/A | MG16: =MF16 -> #N/A | MH16: =MG16 -> #N/A | MI16: =MH16 -> #N/A | MJ16: =MI16 -> #N/A | ... MM16: =ML16 -> #N/A | MN16: =SUM(MB16:MM16) -> #N/A | MO16: =MM16*(1+Inputs!$B$7) -> #N/A | MP16: =MO16 -> #N/A | MQ16: =MP16 -> #N/A | MR16: =MQ16 -> #N/A | MS16: =MR16 -> #N/A | MT16: =MS16 -> #N/A | MU16: =MT16 -> #N/A | MV16: =MU16 -> #N/A | MW16: =MV16 -> #N/A | ... MZ16: =MY16 -> #N/A | NA16: =SUM(MO16:MZ16) -> #N/A | NB16: =MZ16*(1+Inputs!$B$7) -> #N/A | NC16: =NB16 -> #N/A | ND16: =NC16 -> #N/A | NE16: =ND16 -> #N/A | NF16: =NE16 -> #N/A | NG16: =NF16 -> #N/A | NH16: =NG16 -> #N/A | NI16: =NH16 -> #N/A | NJ16: =NI16 -> #N/A | ... NM16: =NL16 -> #N/A | NN16: =SUM(NB16:NM16) -> #N/A | NO16: =NM16*(1+Inputs!$B$7) -> #N/A | NP16: =NO16 -> #N/A | NQ16: =NP16 -> #N/A | NR16: =NQ16 -> #N/A | NS16: =NR16 -> #N/A | NT16: =NS16 -> #N/A | NU16: =NT16 -> #N/A | NV16: =NU16 -> #N/A | NW16: =NV16 -> #N/A | ... NZ16: =NY16 -> #N/A | OA16: =SUM(NO16:NZ16) -> #N/A | OB16: =NZ16*(1+Inputs!$B$7) -> #N/A | OC16: =OB16 -> #N/A | OD16: =OC16 -> #N/A | OE16: =OD16 -> #N/A | OF16: =OE16 -> #N/A | OG16: =OF16 -> #N/A | OH16: =OG16 -> #N/A | OI16: =OH16 -> #N/A | OJ16: =OI16 -> #N/A | ... OM16: =OL16 -> #N/A | ON16: =SUM(OB16:OM16) -> #N/A | OO16: =OM16*(1+Inputs!$B$7) -> #N/A | OP16: =OO16 -> #N/A | OQ16: =OP16 -> #N/A | OR16: =OQ16 -> #N/A | OS16: =OR16 -> #N/A | OT16: =OS16 -> #N/A | OU16: =OT16 -> #N/A | OV16: =OU16 -> #N/A | OW16: =OV16 -> #N/A | ... OZ16: =OY16 -> #N/A | PA16: =SUM(OO16:OZ16) -> #N/A | PB16: =OZ16*(1+Inputs!$B$7) -> #N/A | PC16: =PB16 -> #N/A | PD16: =PC16 -> #N/A | PE16: =PD16 -> #N/A | PF16: =PE16 -> #N/A | PG16: =PF16 -> #N/A | PH16: =PG16 -> #N/A | PI16: =PH16 -> #N/A | PJ16: =PI16 -> #N/A | ... PM16: =PL16 -> #N/A | PN16: =SUM(PB16:PM16) -> #N/A | PO16: =PM16*(1+Inputs!$B$7) -> #N/A | PP16: =PO16 -> #N/A | PQ16: =PP16 -> #N/A | PR16: =PQ16 -> #N/A | PS16: =PR16 -> #N/A | PT16: =PS16 -> #N/A | PU16: =PT16 -> #N/A | PV16: =PU16 -> #N/A | PW16: =PV16 -> #N/A | ... PZ16: =PY16 -> #N/A | QA16: =SUM(PO16:PZ16) -> #N/A | QB16: =PZ16*(1+Inputs!$B$7) -> #N/A | QC16: =QB16 -> #N/A | QD16: =QC16 -> #N/A | QE16: =QD16 -> #N/A | QF16: =QE16 -> #N/A | QG16: =QF16 -> #N/A | QH16: =QG16 -> #N/A | QI16: =QH16 -> #N/A | QJ16: =QI16 -> #N/A | ... QM16: =QL16 -> #N/A | QN16: =SUM(QB16:QM16) -> #N/A | QO16: =QM16*(1+Inputs!$B$7) -> #N/A | QP16: =QO16 -> #N/A | QQ16: =QP16 -> #N/A | QR16: =QQ16 -> #N/A | QS16: =QR16 -> #N/A | QT16: =QS16 -> #N/A | QU16: =QT16 -> #N/A | QV16: =QU16 -> #N/A | QW16: =QV16 -> #N/A | ... QZ16: =QY16 -> #N/A | RA16: =SUM(QO16:QZ16) -> #N/A | RB16: =QZ16*(1+Inputs!$B$7) -> #N/A | RC16: =RB16 -> #N/A | RD16: =RC16 -> #N/A | RE16: =RD16 -> #N/A | RF16: =RE16 -> #N/A | RG16: =RF16 -> #N/A | RH16: =RG16 -> #N/A | RI16: =RH16 -> #N/A | RJ16: =RI16 -> #N/A | ... RM16: =RL16 -> #N/A | RN16: =SUM(RB16:RM16) -> #N/A
A17: Vacancy/Bad Debts | B17: =-Inputs!$B$8*Financials!B16 -> #N/A | C17: =-Inputs!$B$8*Financials!C16 -> #N/A | D17: =-Inputs!$B$8*Financials!D16 -> #N/A | E17: =-Inputs!$B$8*Financials!E16 -> #N/A | F17: =-Inputs!$B$8*Financials!F16 -> #N/A | G17: =-Inputs!$B$8*Financials!G16 -> #N/A | H17: =-Inputs!$B$8*Financials!H16 -> #N/A | I17: =-Inputs!$B$8*Financials!I16 -> #N/A | ... M17: =-Inputs!$B$8*Financials!M16 -> #N/A | N17: =SUM(B17:M17) -> #N/A | O17: =-Inputs!$B$8*Financials!O16 -> #N/A | P17: =-Inputs!$B$8*Financials!P16 -> #N/A | Q17: =-Inputs!$B$8*Financials!Q16 -> #N/A | R17: =-Inputs!$B$8*Financials!R16 -> #N/A | S17: =-Inputs!$B$8*Financials!S16 -> #N/A | T17: =-Inputs!$B$8*Financials!T16 -> #N/A | U17: =-Inputs!$B$8*Financials!U16 -> #N/A | V17: =-Inputs!$B$8*Financials!V16 -> #N/A | ... Z17: =-Inputs!$B$8*Financials!Z16 -> #N/A | AA17: =SUM(O17:Z17) -> #N/A | AB17: =-Inputs!$B$8*Financials!AB16 -> #N/A | AC17: =-Inputs!$B$8*Financials!AC16 -> #N/A | AD17: =-Inputs!$B$8*Financials!AD16 -> #N/A | AE17: =-Inputs!$B$8*Financials!AE16 -> #N/A | AF17: =-Inputs!$B$8*Financials!AF16 -> #N/A | AG17: =-Inputs!$B$8*Financials!AG16 -> #N/A | AH17: =-Inputs!$B$8*Financials!AH16 -> #N/A | AI17: =-Inputs!$B$8*Financials!AI16 -> #N/A | ... AM17: =-Inputs!$B$8*Financials!AM16 -> #N/A | AN17: =SUM(AB17:AM17) -> #N/A | AO17: =-Inputs!$B$8*Financials!AO16 -> #N/A | AP17: =-Inputs!$B$8*Financials!AP16 -> #N/A | AQ17: =-Inputs!$B$8*Financials!AQ16 -> #N/A | AR17: =-Inputs!$B$8*Financials!AR16 -> #N/A | AS17: =-Inputs!$B$8*Financials!AS16 -> #N/A | AT17: =-Inputs!$B$8*Financials!AT16 -> #N/A | AU17: =-Inputs!$B$8*Financials!AU16 -> #N/A | AV17: =-Inputs!$B$8*Financials!AV16 -> #N/A | ... AZ17: =-Inputs!$B$8*Financials!AZ16 -> #N/A | BA17: =SUM(AO17:AZ17) -> #N/A | BB17: =-Inputs!$B$8*Financials!BB16 -> #N/A | BC17: =-Inputs!$B$8*Financials!BC16 -> #N/A | BD17: =-Inputs!$B$8*Financials!BD16 -> #N/A | BE17: =-Inputs!$B$8*Financials!BE16 -> #N/A | BF17: =-Inputs!$B$8*Financials!BF16 -> #N/A | BG17: =-Inputs!$B$8*Financials!BG16 -> #N/A | BH17: =-Inputs!$B$8*Financials!BH16 -> #N/A | BI17: =-Inputs!$B$8*Financials!BI16 -> #N/A | ... BM17: =-Inputs!$B$8*Financials!BM16 -> #N/A | BN17: =SUM(BB17:BM17) -> #N/A | BO17: =-Inputs!$B$8*Financials!BO16 -> #N/A | BP17: =-Inputs!$B$8*Financials!BP16 -> #N/A | BQ17: =-Inputs!$B$8*Financials!BQ16 -> #N/A | BR17: =-Inputs!$B$8*Financials!BR16 -> #N/A | BS17: =-Inputs!$B$8*Financials!BS16 -> #N/A | BT17: =-Inputs!$B$8*Financials!BT16 -> #N/A | BU17: =-Inputs!$B$8*Financials!BU16 -> #N/A | BV17: =-Inputs!$B$8*Financials!BV16 -> #N/A | ... BZ17: =-Inputs!$B$8*Financials!BZ16 -> #N/A | CA17: =SUM(BO17:BZ17) -> #N/A | CB17: =-Inputs!$B$8*Financials!CB16 -> #N/A | CC17: =-Inputs!$B$8*Financials!CC16 -> #N/A | CD17: =-Inputs!$B$8*Financials!CD16 -> #N/A | CE17: =-Inputs!$B$8*Financials!CE16 -> #N/A | CF17: =-Inputs!$B$8*Financials!CF16 -> #N/A | CG17: =-Inputs!$B$8*Financials!CG16 -> #N/A | CH17: =-Inputs!$B$8*Financials!CH16 -> #N/A | CI17: =-Inputs!$B$8*Financials!CI16 -> #N/A | ... CM17: =-Inputs!$B$8*Financials!CM16 -> #N/A | CN17: =SUM(CB17:CM17) -> #N/A | CO17: =-Inputs!$B$8*Financials!CO16 -> #N/A | CP17: =-Inputs!$B$8*Financials!CP16 -> #N/A | CQ17: =-Inputs!$B$8*Financials!CQ16 -> #N/A | CR17: =-Inputs!$B$8*Financials!CR16 -> #N/A | CS17: =-Inputs!$B$8*Financials!CS16 -> #N/A | CT17: =-Inputs!$B$8*Financials!CT16 -> #N/A | CU17: =-Inputs!$B$8*Financials!CU16 -> #N/A | CV17: =-Inputs!$B$8*Financials!CV16 -> #N/A | ... CZ17: =-Inputs!$B$8*Financials!CZ16 -> #N/A | DA17: =SUM(CO17:CZ17) -> #N/A | DB17: =-Inputs!$B$8*Financials!DB16 -> #N/A | DC17: =-Inputs!$B$8*Financials!DC16 -> #N/A | DD17: =-Inputs!$B$8*Financials!DD16 -> #N/A | DE17: =-Inputs!$B$8*Financials!DE16 -> #N/A | DF17: =-Inputs!$B$8*Financials!DF16 -> #N/A | DG17: =-Inputs!$B$8*Financials!DG16 -> #N/A | DH17: =-Inputs!$B$8*Financials!DH16 -> #N/A | DI17: =-Inputs!$B$8*Financials!DI16 -> #N/A | ... DM17: =-Inputs!$B$8*Financials!DM16 -> #N/A | DN17: =SUM(DB17:DM17) -> #N/A | DO17: =-Inputs!$B$8*Financials!DO16 -> #N/A | DP17: =-Inputs!$B$8*Financials!DP16 -> #N/A | DQ17: =-Inputs!$B$8*Financials!DQ16 -> #N/A | DR17: =-Inputs!$B$8*Financials!DR16 -> #N/A | DS17: =-Inputs!$B$8*Financials!DS16 -> #N/A | DT17: =-Inputs!$B$8*Financials!DT16 -> #N/A | DU17: =-Inputs!$B$8*Financials!DU16 -> #N/A | DV17: =-Inputs!$B$8*Financials!DV16 -> #N/A | ... DZ17: =-Inputs!$B$8*Financials!DZ16 -> #N/A | EA17: =SUM(DO17:DZ17) -> #N/A | EB17: =-Inputs!$B$8*Financials!EB16 -> #N/A | EC17: =-Inputs!$B$8*Financials!EC16 -> #N/A | ED17: =-Inputs!$B$8*Financials!ED16 -> #N/A | EE17: =-Inputs!$B$8*Financials!EE16 -> #N/A | EF17: =-Inputs!$B$8*Financials!EF16 -> #N/A | EG17: =-Inputs!$B$8*Financials!EG16 -> #N/A | EH17: =-Inputs!$B$8*Financials!EH16 -> #N/A | EI17: =-Inputs!$B$8*Financials!EI16 -> #N/A | ... EM17: =-Inputs!$B$8*Financials!EM16 -> #N/A | EN17: =SUM(EB17:EM17) -> #N/A | EO17: =-Inputs!$B$8*Financials!EO16 -> #N/A | EP17: =-Inputs!$B$8*Financials!EP16 -> #N/A | EQ17: =-Inputs!$B$8*Financials!EQ16 -> #N/A | ER17: =-Inputs!$B$8*Financials!ER16 -> #N/A | ES17: =-Inputs!$B$8*Financials!ES16 -> #N/A | ET17: =-Inputs!$B$8*Financials!ET16 -> #N/A | EU17: =-Inputs!$B$8*Financials!EU16 -> #N/A | EV17: =-Inputs!$B$8*Financials!EV16 -> #N/A | ... EZ17: =-Inputs!$B$8*Financials!EZ16 -> #N/A | FA17: =SUM(EO17:EZ17) -> #N/A | FB17: =-Inputs!$B$8*Financials!FB16 -> #N/A | FC17: =-Inputs!$B$8*Financials!FC16 -> #N/A | FD17: =-Inputs!$B$8*Financials!FD16 -> #N/A | FE17: =-Inputs!$B$8*Financials!FE16 -> #N/A | FF17: =-Inputs!$B$8*Financials!FF16 -> #N/A | FG17: =-Inputs!$B$8*Financials!FG16 -> #N/A | FH17: =-Inputs!$B$8*Financials!FH16 -> #N/A | FI17: =-Inputs!$B$8*Financials!FI16 -> #N/A | ... FM17: =-Inputs!$B$8*Financials!FM16 -> #N/A | FN17: =SUM(FB17:FM17) -> #N/A | FO17: =-Inputs!$B$8*Financials!FO16 -> #N/A | FP17: =-Inputs!$B$8*Financials!FP16 -> #N/A | FQ17: =-Inputs!$B$8*Financials!FQ16 -> #N/A | FR17: =-Inputs!$B$8*Financials!FR16 -> #N/A | FS17: =-Inputs!$B$8*Financials!FS16 -> #N/A | FT17: =-Inputs!$B$8*Financials!FT16 -> #N/A | FU17: =-Inputs!$B$8*Financials!FU16 -> #N/A | FV17: =-Inputs!$B$8*Financials!FV16 -> #N/A | ... FZ17: =-Inputs!$B$8*Financials!FZ16 -> #N/A | GA17: =SUM(FO17:FZ17) -> #N/A | GB17: =-Inputs!$B$8*Financials!GB16 -> #N/A | GC17: =-Inputs!$B$8*Financials!GC16 -> #N/A | GD17: =-Inputs!$B$8*Financials!GD16 -> #N/A | GE17: =-Inputs!$B$8*Financials!GE16 -> #N/A | GF17: =-Inputs!$B$8*Financials!GF16 -> #N/A | GG17: =-Inputs!$B$8*Financials!GG16 -> #N/A | GH17: =-Inputs!$B$8*Financials!GH16 -> #N/A | GI17: =-Inputs!$B$8*Financials!GI16 -> #N/A | ... GM17: =-Inputs!$B$8*Financials!GM16 -> #N/A | GN17: =SUM(GB17:GM17) -> #N/A | GO17: =-Inputs!$B$8*Financials!GO16 -> #N/A | GP17: =-Inputs!$B$8*Financials!GP16 -> #N/A | GQ17: =-Inputs!$B$8*Financials!GQ16 -> #N/A | GR17: =-Inputs!$B$8*Financials!GR16 -> #N/A | GS17: =-Inputs!$B$8*Financials!GS16 -> #N/A | GT17: =-Inputs!$B$8*Financials!GT16 -> #N/A | GU17: =-Inputs!$B$8*Financials!GU16 -> #N/A | GV17: =-Inputs!$B$8*Financials!GV16 -> #N/A | ... GZ17: =-Inputs!$B$8*Financials!GZ16 -> #N/A | HA17: =SUM(GO17:GZ17) -> #N/A | HB17: =-Inputs!$B$8*Financials!HB16 -> #N/A | HC17: =-Inputs!$B$8*Financials!HC16 -> #N/A | HD17: =-Inputs!$B$8*Financials!HD16 -> #N/A | HE17: =-Inputs!$B$8*Financials!HE16 -> #N/A | HF17: =-Inputs!$B$8*Financials!HF16 -> #N/A | HG17: =-Inputs!$B$8*Financials!HG16 -> #N/A | HH17: =-Inputs!$B$8*Financials!HH16 -> #N/A | HI17: =-Inputs!$B$8*Financials!HI16 -> #N/A | ... HM17: =-Inputs!$B$8*Financials!HM16 -> #N/A | HN17: =SUM(HB17:HM17) -> #N/A | HO17: =-Inputs!$B$8*Financials!HO16 -> #N/A | HP17: =-Inputs!$B$8*Financials!HP16 -> #N/A | HQ17: =-Inputs!$B$8*Financials!HQ16 -> #N/A | HR17: =-Inputs!$B$8*Financials!HR16 -> #N/A | HS17: =-Inputs!$B$8*Financials!HS16 -> #N/A | HT17: =-Inputs!$B$8*Financials!HT16 -> #N/A | HU17: =-Inputs!$B$8*Financials!HU16 -> #N/A | HV17: =-Inputs!$B$8*Financials!HV16 -> #N/A | ... HZ17: =-Inputs!$B$8*Financials!HZ16 -> #N/A | IA17: =SUM(HO17:HZ17) -> #N/A | IB17: =-Inputs!$B$8*Financials!IB16 -> #N/A | IC17: =-Inputs!$B$8*Financials!IC16 -> #N/A | ID17: =-Inputs!$B$8*Financials!ID16 -> #N/A | IE17: =-Inputs!$B$8*Financials!IE16 -> #N/A | IF17: =-Inputs!$B$8*Financials!IF16 -> #N/A | IG17: =-Inputs!$B$8*Financials!IG16 -> #N/A | IH17: =-Inputs!$B$8*Financials!IH16 -> #N/A | II17: =-Inputs!$B$8*Financials!II16 -> #N/A | ... IM17: =-Inputs!$B$8*Financials!IM16 -> #N/A | IN17: =SUM(IB17:IM17) -> #N/A | IO17: =-Inputs!$B$8*Financials!IO16 -> #N/A | IP17: =-Inputs!$B$8*Financials!IP16 -> #N/A | IQ17: =-Inputs!$B$8*Financials!IQ16 -> #N/A | IR17: =-Inputs!$B$8*Financials!IR16 -> #N/A | IS17: =-Inputs!$B$8*Financials!IS16 -> #N/A | IT17: =-Inputs!$B$8*Financials!IT16 -> #N/A | IU17: =-Inputs!$B$8*Financials!IU16 -> #N/A | IV17: =-Inputs!$B$8*Financials!IV16 -> #N/A | ... IZ17: =-Inputs!$B$8*Financials!IZ16 -> #N/A | JA17: =SUM(IO17:IZ17) -> #N/A | JB17: =-Inputs!$B$8*Financials!JB16 -> #N/A | JC17: =-Inputs!$B$8*Financials!JC16 -> #N/A | JD17: =-Inputs!$B$8*Financials!JD16 -> #N/A | JE17: =-Inputs!$B$8*Financials!JE16 -> #N/A | JF17: =-Inputs!$B$8*Financials!JF16 -> #N/A | JG17: =-Inputs!$B$8*Financials!JG16 -> #N/A | JH17: =-Inputs!$B$8*Financials!JH16 -> #N/A | JI17: =-Inputs!$B$8*Financials!JI16 -> #N/A | ... JM17: =-Inputs!$B$8*Financials!JM16 -> #N/A | JN17: =SUM(JB17:JM17) -> #N/A | JO17: =-Inputs!$B$8*Financials!JO16 -> #N/A | JP17: =-Inputs!$B$8*Financials!JP16 -> #N/A | JQ17: =-Inputs!$B$8*Financials!JQ16 -> #N/A | JR17: =-Inputs!$B$8*Financials!JR16 -> #N/A | JS17: =-Inputs!$B$8*Financials!JS16 -> #N/A | JT17: =-Inputs!$B$8*Financials!JT16 -> #N/A | JU17: =-Inputs!$B$8*Financials!JU16 -> #N/A | JV17: =-Inputs!$B$8*Financials!JV16 -> #N/A | ... JZ17: =-Inputs!$B$8*Financials!JZ16 -> #N/A | KA17: =SUM(JO17:JZ17) -> #N/A | KB17: =-Inputs!$B$8*Financials!KB16 -> #N/A | KC17: =-Inputs!$B$8*Financials!KC16 -> #N/A | KD17: =-Inputs!$B$8*Financials!KD16 -> #N/A | KE17: =-Inputs!$B$8*Financials!KE16 -> #N/A | KF17: =-Inputs!$B$8*Financials!KF16 -> #N/A | KG17: =-Inputs!$B$8*Financials!KG16 -> #N/A | KH17: =-Inputs!$B$8*Financials!KH16 -> #N/A | KI17: =-Inputs!$B$8*Financials!KI16 -> #N/A | ... KM17: =-Inputs!$B$8*Financials!KM16 -> #N/A | KN17: =SUM(KB17:KM17) -> #N/A | KO17: =-Inputs!$B$8*Financials!KO16 -> #N/A | KP17: =-Inputs!$B$8*Financials!KP16 -> #N/A | KQ17: =-Inputs!$B$8*Financials!KQ16 -> #N/A | KR17: =-Inputs!$B$8*Financials!KR16 -> #N/A | KS17: =-Inputs!$B$8*Financials!KS16 -> #N/A | KT17: =-Inputs!$B$8*Financials!KT16 -> #N/A | KU17: =-Inputs!$B$8*Financials!KU16 -> #N/A | KV17: =-Inputs!$B$8*Financials!KV16 -> #N/A | ... KZ17: =-Inputs!$B$8*Financials!KZ16 -> #N/A | LA17: =SUM(KO17:KZ17) -> #N/A | LB17: =-Inputs!$B$8*Financials!LB16 -> #N/A | LC17: =-Inputs!$B$8*Financials!LC16 -> #N/A | LD17: =-Inputs!$B$8*Financials!LD16 -> #N/A | LE17: =-Inputs!$B$8*Financials!LE16 -> #N/A | LF17: =-Inputs!$B$8*Financials!LF16 -> #N/A | LG17: =-Inputs!$B$8*Financials!LG16 -> #N/A | LH17: =-Inputs!$B$8*Financials!LH16 -> #N/A | LI17: =-Inputs!$B$8*Financials!LI16 -> #N/A | ... LM17: =-Inputs!$B$8*Financials!LM16 -> #N/A | LN17: =SUM(LB17:LM17) -> #N/A | LO17: =-Inputs!$B$8*Financials!LO16 -> #N/A | LP17: =-Inputs!$B$8*Financials!LP16 -> #N/A | LQ17: =-Inputs!$B$8*Financials!LQ16 -> #N/A | LR17: =-Inputs!$B$8*Financials!LR16 -> #N/A | LS17: =-Inputs!$B$8*Financials!LS16 -> #N/A | LT17: =-Inputs!$B$8*Financials!LT16 -> #N/A | LU17: =-Inputs!$B$8*Financials!LU16 -> #N/A | LV17: =-Inputs!$B$8*Financials!LV16 -> #N/A | ... LZ17: =-Inputs!$B$8*Financials!LZ16 -> #N/A | MA17: =SUM(LO17:LZ17) -> #N/A | MB17: =-Inputs!$B$8*Financials!MB16 -> #N/A | MC17: =-Inputs!$B$8*Financials!MC16 -> #N/A | MD17: =-Inputs!$B$8*Financials!MD16 -> #N/A | ME17: =-Inputs!$B$8*Financials!ME16 -> #N/A | MF17: =-Inputs!$B$8*Financials!MF16 -> #N/A | MG17: =-Inputs!$B$8*Financials!MG16 -> #N/A | MH17: =-Inputs!$B$8*Financials!MH16 -> #N/A | MI17: =-Inputs!$B$8*Financials!MI16 -> #N/A | ... MM17: =-Inputs!$B$8*Financials!MM16 -> #N/A | MN17: =SUM(MB17:MM17) -> #N/A | MO17: =-Inputs!$B$8*Financials!MO16 -> #N/A | MP17: =-Inputs!$B$8*Financials!MP16 -> #N/A | MQ17: =-Inputs!$B$8*Financials!MQ16 -> #N/A | MR17: =-Inputs!$B$8*Financials!MR16 -> #N/A | MS17: =-Inputs!$B$8*Financials!MS16 -> #N/A | MT17: =-Inputs!$B$8*Financials!MT16 -> #N/A | MU17: =-Inputs!$B$8*Financials!MU16 -> #N/A | MV17: =-Inputs!$B$8*Financials!MV16 -> #N/A | ... MZ17: =-Inputs!$B$8*Financials!MZ16 -> #N/A | NA17: =SUM(MO17:MZ17) -> #N/A | NB17: =-Inputs!$B$8*Financials!NB16 -> #N/A | NC17: =-Inputs!$B$8*Financials!NC16 -> #N/A | ND17: =-Inputs!$B$8*Financials!ND16 -> #N/A | NE17: =-Inputs!$B$8*Financials!NE16 -> #N/A | NF17: =-Inputs!$B$8*Financials!NF16 -> #N/A | NG17: =-Inputs!$B$8*Financials!NG16 -> #N/A | NH17: =-Inputs!$B$8*Financials!NH16 -> #N/A | NI17: =-Inputs!$B$8*Financials!NI16 -> #N/A | ... NM17: =-Inputs!$B$8*Financials!NM16 -> #N/A | NN17: =SUM(NB17:NM17) -> #N/A | NO17: =-Inputs!$B$8*Financials!NO16 -> #N/A | NP17: =-Inputs!$B$8*Financials!NP16 -> #N/A | NQ17: =-Inputs!$B$8*Financials!NQ16 -> #N/A | NR17: =-Inputs!$B$8*Financials!NR16 -> #N/A | NS17: =-Inputs!$B$8*Financials!NS16 -> #N/A | NT17: =-Inputs!$B$8*Financials!NT16 -> #N/A | NU17: =-Inputs!$B$8*Financials!NU16 -> #N/A | NV17: =-Inputs!$B$8*Financials!NV16 -> #N/A | ... NZ17: =-Inputs!$B$8*Financials!NZ16 -> #N/A | OA17: =SUM(NO17:NZ17) -> #N/A | OB17: =-Inputs!$B$8*Financials!OB16 -> #N/A | OC17: =-Inputs!$B$8*Financials!OC16 -> #N/A | OD17: =-Inputs!$B$8*Financials!OD16 -> #N/A | OE17: =-Inputs!$B$8*Financials!OE16 -> #N/A | OF17: =-Inputs!$B$8*Financials!OF16 -> #N/A | OG17: =-Inputs!$B$8*Financials!OG16 -> #N/A | OH17: =-Inputs!$B$8*Financials!OH16 -> #N/A | OI17: =-Inputs!$B$8*Financials!OI16 -> #N/A | ... OM17: =-Inputs!$B$8*Financials!OM16 -> #N/A | ON17: =SUM(OB17:OM17) -> #N/A | OO17: =-Inputs!$B$8*Financials!OO16 -> #N/A | OP17: =-Inputs!$B$8*Financials!OP16 -> #N/A | OQ17: =-Inputs!$B$8*Financials!OQ16 -> #N/A | OR17: =-Inputs!$B$8*Financials!OR16 -> #N/A | OS17: =-Inputs!$B$8*Financials!OS16 -> #N/A | OT17: =-Inputs!$B$8*Financials!OT16 -> #N/A | OU17: =-Inputs!$B$8*Financials!OU16 -> #N/A | OV17: =-Inputs!$B$8*Financials!OV16 -> #N/A | ... OZ17: =-Inputs!$B$8*Financials!OZ16 -> #N/A | PA17: =SUM(OO17:OZ17) -> #N/A | PB17: =-Inputs!$B$8*Financials!PB16 -> #N/A | PC17: =-Inputs!$B$8*Financials!PC16 -> #N/A | PD17: =-Inputs!$B$8*Financials!PD16 -> #N/A | PE17: =-Inputs!$B$8*Financials!PE16 -> #N/A | PF17: =-Inputs!$B$8*Financials!PF16 -> #N/A | PG17: =-Inputs!$B$8*Financials!PG16 -> #N/A | PH17: =-Inputs!$B$8*Financials!PH16 -> #N/A | PI17: =-Inputs!$B$8*Financials!PI16 -> #N/A | ... PM17: =-Inputs!$B$8*Financials!PM16 -> #N/A | PN17: =SUM(PB17:PM17) -> #N/A | PO17: =-Inputs!$B$8*Financials!PO16 -> #N/A | PP17: =-Inputs!$B$8*Financials!PP16 -> #N/A | PQ17: =-Inputs!$B$8*Financials!PQ16 -> #N/A | PR17: =-Inputs!$B$8*Financials!PR16 -> #N/A | PS17: =-Inputs!$B$8*Financials!PS16 -> #N/A | PT17: =-Inputs!$B$8*Financials!PT16 -> #N/A | PU17: =-Inputs!$B$8*Financials!PU16 -> #N/A | PV17: =-Inputs!$B$8*Financials!PV16 -> #N/A | ... PZ17: =-Inputs!$B$8*Financials!PZ16 -> #N/A | QA17: =SUM(PO17:PZ17) -> #N/A | QB17: =-Inputs!$B$8*Financials!QB16 -> #N/A | QC17: =-Inputs!$B$8*Financials!QC16 -> #N/A | QD17: =-Inputs!$B$8*Financials!QD16 -> #N/A | QE17: =-Inputs!$B$8*Financials!QE16 -> #N/A | QF17: =-Inputs!$B$8*Financials!QF16 -> #N/A | QG17: =-Inputs!$B$8*Financials!QG16 -> #N/A | QH17: =-Inputs!$B$8*Financials!QH16 -> #N/A | QI17: =-Inputs!$B$8*Financials!QI16 -> #N/A | ... QM17: =-Inputs!$B$8*Financials!QM16 -> #N/A | QN17: =SUM(QB17:QM17) -> #N/A | QO17: =-Inputs!$B$8*Financials!QO16 -> #N/A | QP17: =-Inputs!$B$8*Financials!QP16 -> #N/A | QQ17: =-Inputs!$B$8*Financials!QQ16 -> #N/A | QR17: =-Inputs!$B$8*Financials!QR16 -> #N/A | QS17: =-Inputs!$B$8*Financials!QS16 -> #N/A | QT17: =-Inputs!$B$8*Financials!QT16 -> #N/A | QU17: =-Inputs!$B$8*Financials!QU16 -> #N/A | QV17: =-Inputs!$B$8*Financials!QV16 -> #N/A | ... QZ17: =-Inputs!$B$8*Financials!QZ16 -> #N/A | RA17: =SUM(QO17:QZ17) -> #N/A | RB17: =-Inputs!$B$8*Financials!RB16 -> #N/A | RC17: =-Inputs!$B$8*Financials!RC16 -> #N/A | RD17: =-Inputs!$B$8*Financials!RD16 -> #N/A | RE17: =-Inputs!$B$8*Financials!RE16 -> #N/A | RF17: =-Inputs!$B$8*Financials!RF16 -> #N/A | RG17: =-Inputs!$B$8*Financials!RG16 -> #N/A | RH17: =-Inputs!$B$8*Financials!RH16 -> #N/A | RI17: =-Inputs!$B$8*Financials!RI16 -> #N/A | ... RM17: =-Inputs!$B$8*Financials!RM16 -> #N/A | RN17: =SUM(RB17:RM17) -> #N/A
